Workbook

Sheet Analyse_RH_Projet.xlsx
A1: Employee_Name | B1: EmpID | C1: MarriedID | D1: MaritalStatuID | E1: GenderIS | F1: EmpstatutID | G1: DeptID | H1: PerfScoreID | I1: FromDiver | J1: Salary | K1: Termd | L1: PositionID | M1: Psition | N1: State | O1: Zip | P1: DOB | Q1: Sex | R1: MaritalDESC | S1: Citizedesc | T1: HispanicLatin | U1: Racedesc | V1: Dateofhire | W1: Dateoftermi | X1: Termreason | Y1: Employement | Z1: Department | AA1: Managernat | AB1: ManagerID | AC1: Recrutment | AD1: Performance | AE1: Engagement | AF1: EmploySatisfy | AG1: SpecialProjet | AH1: LastPERF | AI1: DayLatel | AJ1: Absences
A2: Adinolfi Wilson K | B2: 10026 | C2: 0 | D2: 0 | E2: 1 | F2: 1 | G2: 5 | H2: 4 | I2: 0 | J2: 62506 | K2: 0 | L2: 19 | M2: Production Technician I | N2: MA | O2: 1960 | P2: 30596 | Q2: M | R2: Single | S2: US Citizen | T2: No | U2: White | V2: 40670 | X2: N/A-StillEmployed | Y2: Active | Z2: Production | AA2: Michael Albert | AB2: 22 | AC2: LinkedIn | AD2: Exceeds | AE2: 4.60 | AF2: 5 | AG2: 0 | AH2: 1/17/2019 | AI2: 0 | AJ2: 1
A3: Ait Sidi Karthikeyan | B3: 10084 | C3: 1 | D3: 1 | E3: 1 | F3: 5 | G3: 3 | H3: 3 | I3: 0 | J3: 104437 | K3: 1 | L3: 27 | M3: Sr. DBA | N3: MA | O3: 2148 | P3: 27519 | Q3: M | R3: Married | S3: US Citizen | T3: No | U3: White | V3: 3/30/2015 | W3: 6/16/2016 | X3: career change | Y3: Voluntarily Terminated | Z3: IT/IS | AA3: Simon Roup | AB3: 4 | AC3: Indeed | AD3: Fully Meets | AE3: 4.96 | AF3: 3 | AG3: 6 | AH3: 2/24/2016 | AI3: 0 | AJ3: 17
A4: Akinkuolie Sarah | B4: 10196 | C4: 1 | D4: 1 | E4: 0 | F4: 5 | G4: 5 | H4: 3 | I4: 0 | J4: 64955 | K4: 1 | L4: 20 | M4: Production Technician II | N4: MA | O4: 1810 | P4: 09/19/88 | Q4: F | R4: Married | S4: US Citizen | T4: No | U4: White | V4: 40670 | W4: 9/24/2012 | X4: hours | Y4: Voluntarily Terminated | Z4: Production | AA4: Kissy Sullivan | AB4: 20 | AC4: LinkedIn | AD4: Fully Meets | AE4: 3.02 | AF4: 3 | AG4: 0 | AH4: 5/15/2012 | AI4: 0 | AJ4: 3
A5: Alagbe Trina | B5: 10088 | C5: 1 | D5: 1 | E5: 0 | F5: 1 | G5: 5 | H5: 3 | I5: 0 | J5: 64991 | K5: 0 | L5: 19 | M5: Production Technician I | N5: MA | O5: 1886 | P5: 09/27/88 | Q5: F | R5: Married | S5: US Citizen | T5: No | U5: White | V5: 39630 | X5: N/A-StillEmployed | Y5: Active | Z5: Production | AA5: Elijiah Gray | AB5: 16 | AC5: Indeed | AD5: Fully Meets | AE5: 4.84 | AF5: 5 | AG5: 0 | AH5: 43525 | AI5: 0 | AJ5: 15
A6: Anderson Carol | B6: 10069 | C6: 0 | D6: 2 | E6: 0 | F6: 5 | G6: 5 | H6: 3 | I6: 0 | J6: 50825 | K6: 1 | L6: 19 | M6: Production Technician I | N6: MA | O6: 2169 | P6: 32729 | Q6: F | R6: Divorced | S6: US Citizen | T6: No | U6: White | V6: 40854 | W6: 42530 | X6: return to school | Y6: Voluntarily Terminated | Z6: Production | AA6: Webster Butler | AB6: 39 | AC6: Google Search | AD6: Fully Meets | AE6: 5.00 | AF6: 4 | AG6: 0 | AH6: 42371 | AI6: 0 | AJ6: 2
A7: Anderson Linda | B7: 10002 | C7: 0 | D7: 0 | E7: 0 | F7: 1 | G7: 5 | H7: 4 | I7: 0 | J7: 57568 | K7: 0 | L7: 19 | M7: Production Technician I | N7: MA | O7: 1844 | P7: 05/22/77 | Q7: F | R7: Single | S7: US Citizen | T7: No | U7: White | V7: 41153 | X7: N/A-StillEmployed | Y7: Active | Z7: Production | AA7: Amy Dunn | AB7: 11 | AC7: LinkedIn | AD7: Exceeds | AE7: 5.00 | AF7: 5 | AG7: 0 | AH7: 43647 | AI7: 0 | AJ7: 15
A8: Andreola Colby | B8: 10194 | C8: 0 | D8: 0 | E8: 0 | F8: 1 | G8: 4 | H8: 3 | I8: 0 | J8: 95660 | K8: 0 | L8: 24 | M8: Software Engineer | N8: MA | O8: 2110 | P8: 05/24/79 | Q8: F | R8: Single | S8: US Citizen | T8: No | U8: White | V8: 41923 | X8: N/A-StillEmployed | Y8: Active | Z8: Software Engineering | AA8: Alex Sweetwater | AB8: 10 | AC8: LinkedIn | AD8: Fully Meets | AE8: 3.04 | AF8: 3 | AG8: 4 | AH8: 43497 | AI8: 0 | AJ8: 19
A9: Athwal Sam | B9: 10062 | C9: 0 | D9: 4 | E9: 1 | F9: 1 | G9: 5 | H9: 3 | I9: 0 | J9: 59365 | K9: 0 | L9: 19 | M9: Production Technician I | N9: MA | O9: 2199 | P9: 02/18/83 | Q9: M | R9: Widowed | S9: US Citizen | T9: No | U9: White | V9: 9/30/2013 | X9: N/A-StillEmployed | Y9: Active | Z9: Production | AA9: Ketsia Liebig | AB9: 19 | AC9: Employee Referral | AD9: Fully Meets | AE9: 5.00 | AF9: 4 | AG9: 0 | AH9: 2/25/2019 | AI9: 0 | AJ9: 19
A10: Bachiochi Linda | B10: 10114 | C10: 0 | D10: 0 | E10: 0 | F10: 3 | G10: 5 | H10: 3 | I10: 1 | J10: 47837 | K10: 0 | L10: 19 | M10: Production Technician I | N10: MA | O10: 1902 | P10: 25874 | Q10: F | R10: Single | S10: US Citizen | T10: No | U10: Black or African American | V10: 39971 | X10: N/A-StillEmployed | Y10: Active | Z10: Production | AA10: Brannon Miller | AB10: 12 | AC10: Diversity Job Fair | AD10: Fully Meets | AE10: 4.46 | AF10: 3 | AG10: 0 | AH10: 1/25/2019 | AI10: 0 | AJ10: 4
A11: Bacong Alejandro | B11: 10250 | C11: 0 | D11: 2 | E11: 1 | F11: 1 | G11: 3 | H11: 3 | I11: 0 | J11: 50178 | K11: 0 | L11: 14 | M11: IT Support | N11: MA | O11: 1886 | P11: 32325 | Q11: M | R11: Divorced | S11: US Citizen | T11: No | U11: White | V11: 42125 | X11: N/A-StillEmployed | Y11: Active | Z11: IT/IS | AA11: Peter Monroe | AB11: 7 | AC11: Indeed | AD11: Fully Meets | AE11: 5.00 | AF11: 5 | AG11: 6 | AH11: 2/18/2019 | AI11: 0 | AJ11: 16
A12: Baczenski Rachael | B12: 10252 | C12: 1 | D12: 1 | E12: 0 | F12: 5 | G12: 5 | H12: 3 | I12: 1 | J12: 54670 | K12: 1 | L12: 19 | M12: Production Technician I | N12: MA | O12: 1902 | P12: 27364 | Q12: F | R12: Married | S12: US Citizen | T12: Yes | U12: Black or African American | V12: 40817 | W12: 43070 | X12: Another position | Y12: Voluntarily Terminated | Z12: Production | AA12: David Stanley | AB12: 14 | AC12: Diversity Job Fair | AD12: Fully Meets | AE12: 4.20 | AF12: 4 | AG12: 0 | AH12: 1/30/2016 | AI12: 0 | AJ12: 12
A13: Barbara Thomas | B13: 10242 | C13: 1 | D13: 1 | E13: 1 | F13: 5 | G13: 5 | H13: 3 | I13: 1 | J13: 47211 | K13: 1 | L13: 19 | M13: Production Technician I | N13: MA | O13: 2062 | P13: 02/21/74 | Q13: M | R13: Married | S13: US Citizen | T13: Yes | U13: Black or African American | V13: 40943 | W13: 9/19/2016 | X13: unhappy | Y13: Voluntarily Terminated | Z13: Production | AA13: Kissy Sullivan | AB13: 20 | AC13: Diversity Job Fair | AD13: Fully Meets | AE13: 4.20 | AF13: 3 | AG13: 0 | AH13: 42526 | AI13: 0 | AJ13: 15
A14: Barbossa Hector | B14: 10012 | C14: 0 | D14: 2 | E14: 1 | F14: 1 | G14: 3 | H14: 4 | I14: 1 | J14: 92328 | K14: 0 | L14: 9 | M14: Data Analyst | N14: TX | O14: 78230 | P14: 32240 | Q14: M | R14: Divorced | S14: US Citizen | T14: No | U14: Black or African American | V14: 41923 | X14: N/A-StillEmployed | Y14: Active | Z14: IT/IS | AA14: Simon Roup | AB14: 4 | AC14: Diversity Job Fair | AD14: Exceeds | AE14: 4.28 | AF14: 4 | AG14: 5 | AH14: 2/25/2019 | AI14: 0 | AJ14: 9
A15: Barone Francesco A | B15: 10265 | C15: 0 | D15: 0 | E15: 1 | F15: 1 | G15: 5 | H15: 3 | I15: 0 | J15: 58709 | K15: 0 | L15: 19 | M15: Production Technician I | N15: MA | O15: 1810 | P15: 07/20/83 | Q15: M | R15: Single | S15: US Citizen | T15: No | U15: Two or more races | V15: 2/20/2012 | X15: N/A-StillEmployed | Y15: Active | Z15: Production | AA15: Kelley Spirea | AB15: 18 | AC15: Google Search | AD15: Fully Meets | AE15: 4.60 | AF15: 4 | AG15: 0 | AH15: 2/14/2019 | AI15: 0 | AJ15: 7
A16: Barton Nader | B16: 10066 | C16: 0 | D16: 2 | E16: 1 | F16: 5 | G16: 5 | H16: 3 | I16: 0 | J16: 52505 | K16: 1 | L16: 19 | M16: Production Technician I | N16: MA | O16: 2747 | P16: 07/15/77 | Q16: M | R16: Divorced | S16: US Citizen | T16: No | U16: White | V16: 9/24/2012 | W16: 42890 | X16: Another position | Y16: Voluntarily Terminated | Z16: Production | AA16: Michael Albert | AB16: 22 | AC16: On-line Web application | AD16: Fully Meets | AE16: 5.00 | AF16: 5 | AG16: 0 | AH16: 42769 | AI16: 0 | AJ16: 1
A17: Bates Norman | B17: 10061 | C17: 0 | D17: 0 | E17: 1 | F17: 4 | G17: 5 | H17: 3 | I17: 0 | J17: 57834 | K17: 1 | L17: 19 | M17: Production Technician I | N17: MA | O17: 2050 | P17: 10/18/81 | Q17: M | R17: Single | S17: US Citizen | T17: No | U17: White | V17: 2/21/2011 | W17: 42833 | X17: attendance | Y17: Terminated for Cause | Z17: Production | AA17: Kelley Spirea | AB17: 18 | AC17: Google Search | AD17: Fully Meets | AE17: 5.00 | AF17: 4 | AG17: 0 | AH17: 42859 | AI17: 0 | AJ17: 20
A18: Beak Kimberly | B18: 10023 | C18: 1 | D18: 1 | E18: 0 | F18: 2 | G18: 5 | H18: 4 | I18: 0 | J18: 70131 | K18: 0 | L18: 20 | M18: Production Technician II | N18: MA | O18: 2145 | P18: 04/17/66 | Q18: F | R18: Married | S18: US Citizen | T18: No | U18: White | V18: 7/21/2016 | X18: N/A-StillEmployed | Y18: Active | Z18: Production | AA18: Kelley Spirea | AB18: 18 | AC18: Employee Referral | AD18: Exceeds | AE18: 4.40 | AF18: 3 | AG18: 0 | AH18: 1/14/2019 | AI18: 0 | AJ18: 16
A19: Beatrice Courtney | B19: 10055 | C19: 0 | D19: 0 | E19: 0 | F19: 1 | G19: 5 | H19: 3 | I19: 0 | J19: 59026 | K19: 0 | L19: 19 | M19: Production Technician I | N19: MA | O19: 1915 | P19: 10/27/70 | Q19: F | R19: Single | S19: Eligible NonCitizen | T19: No | U19: White | V19: 40637 | X19: N/A-StillEmployed | Y19: Active | Z19: Production | AA19: Elijiah Gray | AB19: 16 | AC19: Google Search | AD19: Fully Meets | AE19: 5.00 | AF19: 5 | AG19: 0 | AH19: 1/14/2019 | AI19: 0 | AJ19: 12
A20: Becker Renee | B20: 10245 | C20: 0 | D20: 0 | E20: 0 | F20: 4 | G20: 3 | H20: 3 | I20: 0 | J20: 110000 | K20: 1 | L20: 8 | M20: Database Administrator | N20: MA | O20: 2026 | P20: 31506 | Q20: F | R20: Single | S20: US Citizen | T20: Yes | U20: White | V20: 41827 | W20: 42347 | X20: performance | Y20: Terminated for Cause | Z20: IT/IS | AA20: Simon Roup | AB20: 4 | AC20: Google Search | AD20: Fully Meets | AE20: 4.50 | AF20: 4 | AG20: 5 | AH20: 1/15/2015 | AI20: 0 | AJ20: 8
A21: Becker Scott | B21: 10277 | C21: 0 | D21: 0 | E21: 1 | F21: 3 | G21: 5 | H21: 3 | I21: 0 | J21: 53250 | K21: 0 | L21: 19 | M21: Production Technician I | N21: MA | O21: 2452 | P21: 29010 | Q21: M | R21: Single | S21: US Citizen | T21: No | U21: Asian | V21: 41493 | X21: N/A-StillEmployed | Y21: Active | Z21: Production | AA21: Webster Butler | AC21: LinkedIn | AD21: Fully Meets | AE21: 4.20 | AF21: 4 | AG21: 0 | AH21: 43770 | AI21: 0 | AJ21: 13
A22: Bernstein Sean | B22: 10046 | C22: 0 | D22: 0 | E22: 1 | F22: 1 | G22: 5 | H22: 3 | I22: 0 | J22: 51044 | K22: 0 | L22: 19 | M22: Production Technician I | N22: MA | O22: 2072 | P22: 12/22/70 | Q22: M | R22: Single | S22: US Citizen | T22: Yes | U22: White | V22: 40943 | X22: N/A-StillEmployed | Y22: Active | Z22: Production | AA22: Amy Dunn | AB22: 11 | AC22: Google Search | AD22: Fully Meets | AE22: 5.00 | AF22: 3 | AG22: 0 | AH22: 1/14/2019 | AI22: 0 | AJ22: 13
A23: Biden Lowan M | B23: 10226 | C23: 0 | D23: 2 | E23: 0 | F23: 1 | G23: 5 | H23: 3 | I23: 0 | J23: 64919 | K23: 0 | L23: 19 | M23: Production Technician I | N23: MA | O23: 2027 | P23: 12/27/58 | Q23: F | R23: Divorced | S23: US Citizen | T23: No | U23: Asian | V23: 8/19/2013 | X23: N/A-StillEmployed | Y23: Active | Z23: Production | AA23: Ketsia Liebig | AB23: 19 | AC23: Indeed | AD23: Fully Meets | AE23: 4.20 | AF23: 3 | AG23: 0 | AH23: 43739 | AI23: 0 | AJ23: 2
A24: Billis Helen | B24: 10003 | C24: 1 | D24: 1 | E24: 0 | F24: 1 | G24: 5 | H24: 4 | I24: 0 | J24: 62910 | K24: 0 | L24: 19 | M24: Production Technician I | N24: MA | O24: 2031 | P24: 32517 | Q24: F | R24: Married | S24: US Citizen | T24: No | U24: White | V24: 41827 | X24: N/A-StillEmployed | Y24: Active | Z24: Production | AA24: Brannon Miller | AB24: 12 | AC24: Indeed | AD24: Exceeds | AE24: 5.00 | AF24: 3 | AG24: 0 | AH24: 2/27/2019 | AI24: 0 | AJ24: 19
A25: Blount Dianna | B25: 10294 | C25: 0 | D25: 0 | E25: 0 | F25: 1 | G25: 5 | H25: 2 | I25: 0 | J25: 66441 | K25: 0 | L25: 20 | M25: Production Technician II | N25: MA | O25: 2171 | P25: 09/21/90 | Q25: F | R25: Single | S25: US Citizen | T25: No | U25: White | V25: 40637 | X25: N/A-StillEmployed | Y25: Active | Z25: Production | AA25: Michael Albert | AB25: 22 | AC25: CareerBuilder | AD25: Needs Improvement | AE25: 2.00 | AF25: 3 | AG25: 0 | AH25: 2/27/2019 | AI25: 2 | AJ25: 3
A26: Bondwell Betsy | B26: 10267 | C26: 0 | D26: 0 | E26: 0 | F26: 5 | G26: 5 | H26: 3 | I26: 0 | J26: 57815 | K26: 1 | L26: 20 | M26: Production Technician II | N26: MA | O26: 2210 | P26: 01/16/67 | Q26: F | R26: Single | S26: US Citizen | T26: No | U26: White | V26: 40817 | W26: 41733 | X26: career change | Y26: Voluntarily Terminated | Z26: Production | AA26: Elijiah Gray | AB26: 16 | AC26: Google Search | AD26: Fully Meets | AE26: 4.80 | AF26: 5 | AG26: 0 | AH26: 41732 | AI26: 0 | AJ26: 5
A27: Booth Frank | B27: 10199 | C27: 0 | D27: 0 | E27: 1 | F27: 4 | G27: 3 | H27: 3 | I27: 0 | J27: 103613 | K27: 1 | L27: 30 | M27: Enterprise Architect | N27: CT | O27: 6033 | P27: 07/30/64 | Q27: M | R27: Single | S27: US Citizen | T27: No | U27: Black or African American | V27: 2/17/2014 | W27: 2/19/2016 | X27: Learned that he is a gangster | Y27: Terminated for Cause | Z27: IT/IS | AA27: Simon Roup | AB27: 4 | AC27: LinkedIn | AD27: Fully Meets | AE27: 3.50 | AF27: 5 | AG27: 7 | AH27: 42644 | AI27: 0 | AJ27: 2
A28: Boutwell Bonalyn | B28: 10081 | C28: 1 | D28: 1 | E28: 0 | F28: 1 | G28: 1 | H28: 3 | I28: 1 | J28: 106367 | K28: 0 | L28: 26 | M28: Sr. Accountant | N28: MA | O28: 2468 | P28: 31871 | Q28: F | R28: Married | S28: US Citizen | T28: No | U28: Black or African American | V28: 2/16/2015 | X28: N/A-StillEmployed | Y28: Active | Z28: Admin Offices | AA28: Brandon R. LeBlanc | AB28: 3 | AC28: Diversity Job Fair | AD28: Fully Meets | AE28: 5.00 | AF28: 4 | AG28: 3 | AH28: 2/18/2019 | AI28: 0 | AJ28: 4
A29: Bozzi Charles | B29: 10175 | C29: 0 | D29: 0 | E29: 1 | F29: 5 | G29: 5 | H29: 3 | I29: 0 | J29: 74312 | K29: 1 | L29: 18 | M29: Production Manager | N29: MA | O29: 1901 | P29: 25844 | Q29: M | R29: Single | S29: US Citizen | T29: No | U29: Asian | V29: 9/30/2013 | W29: 41828 | X29: retiring | Y29: Voluntarily Terminated | Z29: Production | AA29: Janet King | AB29: 2 | AC29: Indeed | AD29: Fully Meets | AE29: 3.39 | AF29: 3 | AG29: 0 | AH29: 2/20/2014 | AI29: 0 | AJ29: 14
A30: Brill Donna | B30: 10177 | C30: 1 | D30: 1 | E30: 0 | F30: 5 | G30: 5 | H30: 3 | I30: 0 | J30: 53492 | K30: 1 | L30: 19 | M30: Production Technician I | N30: MA | O30: 1701 | P30: 08/24/90 | Q30: F | R30: Married | S30: US Citizen | T30: No | U30: White | V30: 40943 | W30: 6/15/2013 | X30: Another position | Y30: Voluntarily Terminated | Z30: Production | AA30: David Stanley | AB30: 14 | AC30: Google Search | AD30: Fully Meets | AE30: 3.35 | AF30: 4 | AG30: 0 | AH30: 41367 | AI30: 0 | AJ30: 6
A31: Brown Mia | B31: 10238 | C31: 1 | D31: 1 | E31: 0 | F31: 1 | G31: 1 | H31: 3 | I31: 1 | J31: 63000 | K31: 0 | L31: 1 | M31: Accountant I | N31: MA | O31: 1450 | P31: 11/24/87 | Q31: F | R31: Married | S31: US Citizen | T31: No | U31: Black or African American | V31: 10/27/2008 | X31: N/A-StillEmployed | Y31: Active | Z31: Admin Offices | AA31: Brandon R. LeBlanc | AB31: 1 | AC31: Diversity Job Fair | AD31: Fully Meets | AE31: 4.50 | AF31: 2 | AG31: 6 | AH31: 1/15/2019 | AI31: 0 | AJ31: 14
A32: Buccheri Joseph | B32: 10184 | C32: 0 | D32: 0 | E32: 1 | F32: 1 | G32: 5 | H32: 3 | I32: 0 | J32: 65288 | K32: 0 | L32: 20 | M32: Production Technician II | N32: MA | O32: 1013 | P32: 07/28/83 | Q32: M | R32: Single | S32: US Citizen | T32: No | U32: White | V32: 9/29/2014 | X32: N/A-StillEmployed | Y32: Active | Z32: Production | AA32: Webster Butler | AC32: Google Search | AD32: Fully Meets | AE32: 3.19 | AF32: 3 | AG32: 0 | AH32: 43467 | AI32: 0 | AJ32: 9
A33: Bugali Josephine | B33: 10203 | C33: 0 | D33: 3 | E33: 0 | F33: 3 | G33: 5 | H33: 3 | I33: 1 | J33: 64375 | K33: 0 | L33: 19 | M33: Production Technician I | N33: MA | O33: 2043 | P33: 10/30/69 | Q33: F | R33: Separated | S33: US Citizen | T33: No | U33: Black or African American | V33: 41589 | X33: N/A-StillEmployed | Y33: Active | Z33: Production | AA33: Kissy Sullivan | AB33: 20 | AC33: Diversity Job Fair | AD33: Fully Meets | AE33: 3.50 | AF33: 5 | AG33: 0 | AH33: 1/21/2019 | AI33: 0 | AJ33: 17
A34: Bunbury Jessica | B34: 10188 | C34: 1 | D34: 1 | E34: 0 | F34: 5 | G34: 6 | H34: 3 | I34: 0 | J34: 74326 | K34: 1 | L34: 3 | M34: Area Sales Manager | N34: VA | O34: 21851 | P34: 23382 | Q34: F | R34: Married | S34: Eligible NonCitizen | T34: No | U34: Black or African American | V34: 8/15/2011 | W34: 41678 | X34: Another position | Y34: Voluntarily Terminated | Z34: Sales | AA34: John Smith | AB34: 17 | AC34: Google Search | AD34: Fully Meets | AE34: 3.14 | AF34: 5 | AG34: 0 | AH34: 41549 | AI34: 1 | AJ34: 19
A35: Burke Joelle | B35: 10107 | C35: 0 | D35: 0 | E35: 0 | F35: 1 | G35: 5 | H35: 3 | I35: 0 | J35: 63763 | K35: 0 | L35: 20 | M35: Production Technician II | N35: MA | O35: 2148 | P35: 29254 | Q35: F | R35: Single | S35: US Citizen | T35: No | U35: Black or African American | V35: 41032 | X35: N/A-StillEmployed | Y35: Active | Z35: Production | AA35: Amy Dunn | AB35: 11 | AC35: Employee Referral | AD35: Fully Meets | AE35: 4.51 | AF35: 4 | AG35: 0 | AH35: 2/21/2019 | AI35: 0 | AJ35: 3
A36: Burkett Benjamin | B36: 10181 | C36: 1 | D36: 1 | E36: 1 | F36: 1 | G36: 5 | H36: 3 | I36: 0 | J36: 62162 | K36: 0 | L36: 20 | M36: Production Technician II | N36: MA | O36: 1890 | P36: 08/19/77 | Q36: M | R36: Married | S36: US Citizen | T36: No | U36: White | V36: 40637 | X36: N/A-StillEmployed | Y36: Active | Z36: Production | AA36: Ketsia Liebig | AB36: 19 | AC36: Indeed | AD36: Fully Meets | AE36: 3.25 | AF36: 5 | AG36: 0 | AH36: 1/14/2019 | AI36: 0 | AJ36: 15
A37: Cady Max | B37: 10150 | C37: 0 | D37: 0 | E37: 1 | F37: 1 | G37: 4 | H37: 3 | I37: 0 | J37: 77692 | K37: 0 | L37: 25 | M37: Software Engineering Manager | N37: MA | O37: 2184 | P37: 11/22/66 | Q37: M | R37: Single | S37: US Citizen | T37: No | U37: White | V37: 8/15/2011 | X37: N/A-StillEmployed | Y37: Active | Z37: Software Engineering | AA37: Jennifer Zamora | AB37: 5 | AC37: Google Search | AD37: Fully Meets | AE37: 3.84 | AF37: 3 | AG37: 5 | AH37: 1/21/2019 | AI37: 0 | AJ37: 4
A38: Candie Calvin | B38: 10001 | C38: 0 | D38: 0 | E38: 1 | F38: 1 | G38: 5 | H38: 4 | I38: 0 | J38: 72640 | K38: 0 | L38: 18 | M38: Production Manager | N38: MA | O38: 2169 | P38: 30567 | Q38: M | R38: Single | S38: US Citizen | T38: No | U38: White | V38: 1/28/2016 | X38: N/A-StillEmployed | Y38: Active | Z38: Production | AA38: Janet King | AB38: 2 | AC38: Indeed | AD38: Exceeds | AE38: 5.00 | AF38: 3 | AG38: 0 | AH38: 2/22/2019 | AI38: 0 | AJ38: 14
A39: Carabbio Judith | B39: 10085 | C39: 0 | D39: 0 | E39: 0 | F39: 1 | G39: 4 | H39: 3 | I39: 0 | J39: 93396 | K39: 0 | L39: 24 | M39: Software Engineer | N39: MA | O39: 2132 | P39: 31901 | Q39: F | R39: Single | S39: US Citizen | T39: No | U39: White | V39: 41589 | X39: N/A-StillEmployed | Y39: Active | Z39: Software Engineering | AA39: Alex Sweetwater | AB39: 10 | AC39: Indeed | AD39: Fully Meets | AE39: 4.96 | AF39: 4 | AG39: 6 | AH39: 1/30/2019 | AI39: 0 | AJ39: 3
A40: Carey Michael | B40: 10115 | C40: 0 | D40: 0 | E40: 1 | F40: 1 | G40: 5 | H40: 3 | I40: 0 | J40: 52846 | K40: 0 | L40: 19 | M40: Production Technician I | N40: MA | O40: 1701 | P40: 30349 | Q40: M | R40: Single | S40: US Citizen | T40: No | U40: Black or African American | V40: 3/31/2014 | X40: N/A-StillEmployed | Y40: Active | Z40: Production | AA40: Kelley Spirea | AB40: 18 | AC40: LinkedIn | AD40: Fully Meets | AE40: 4.43 | AF40: 3 | AG40: 0 | AH40: 43467 | AI40: 0 | AJ40: 14
A41: Carr Claudia N | B41: 10082 | C41: 0 | D41: 0 | E41: 0 | F41: 2 | G41: 3 | H41: 3 | I41: 0 | J41: 100031 | K41: 0 | L41: 27 | M41: Sr. DBA | N41: MA | O41: 1886 | P41: 31569 | Q41: F | R41: Single | S41: US Citizen | T41: No | U41: Black or African American | V41: 6/30/2016 | X41: N/A-StillEmployed | Y41: Active | Z41: IT/IS | AA41: Simon Roup | AB41: 4 | AC41: LinkedIn | AD41: Fully Meets | AE41: 5.00 | AF41: 5 | AG41: 6 | AH41: 2/18/2019 | AI41: 0 | AJ41: 7
A42: Carter Michelle | B42: 10040 | C42: 0 | D42: 0 | E42: 0 | F42: 1 | G42: 6 | H42: 3 | I42: 0 | J42: 71860 | K42: 0 | L42: 3 | M42: Area Sales Manager | N42: VT | O42: 5664 | P42: 05/15/63 | Q42: F | R42: Single | S42: US Citizen | T42: No | U42: White | V42: 8/18/2014 | X42: N/A-StillEmployed | Y42: Active | Z42: Sales | AA42: John Smith | AB42: 17 | AC42: Indeed | AD42: Fully Meets | AE42: 5.00 | AF42: 5 | AG42: 0 | AH42: 1/21/2019 | AI42: 0 | AJ42: 7
A43: Chace Beatrice | B43: 10067 | C43: 0 | D43: 0 | E43: 0 | F43: 1 | G43: 5 | H43: 3 | I43: 0 | J43: 61656 | K43: 0 | L43: 19 | M43: Production Technician I | N43: MA | O43: 2763 | P43: 18660 | Q43: F | R43: Single | S43: US Citizen | T43: No | U43: White | V43: 9/29/2014 | X43: N/A-StillEmployed | Y43: Active | Z43: Production | AA43: Michael Albert | AB43: 22 | AC43: Google Search | AD43: Fully Meets | AE43: 5.00 | AF43: 4 | AG43: 0 | AH43: 43801 | AI43: 0 | AJ43: 11
A44: Champaigne Brian | B44: 10108 | C44: 1 | D44: 1 | E44: 1 | F44: 1 | G44: 3 | H44: 3 | I44: 0 | J44: 110929 | K44: 0 | L44: 5 | M44: BI Director | N44: MA | O44: 2045 | P44: 26544 | Q44: M | R44: Married | S44: US Citizen | T44: No | U44: White | V44: 42530 | X44: N/A-StillEmployed | Y44: Active | Z44: IT/IS | AA44: Jennifer Zamora | AB44: 5 | AC44: Indeed | AD44: Fully Meets | AE44: 4.50 | AF44: 5 | AG44: 7 | AH44: 1/15/2019 | AI44: 0 | AJ44: 8
A45: Chan Lin | B45: 10210 | C45: 0 | D45: 0 | E45: 0 | F45: 1 | G45: 5 | H45: 3 | I45: 0 | J45: 54237 | K45: 0 | L45: 19 | M45: Production Technician I | N45: MA | O45: 2170 | P45: 29191 | Q45: F | R45: Single | S45: US Citizen | T45: No | U45: White | V45: 41978 | X45: N/A-StillEmployed | Y45: Active | Z45: Production | AA45: Elijiah Gray | AB45: 16 | AC45: Indeed | AD45: Fully Meets | AE45: 3.30 | AF45: 4 | AG45: 0 | AH45: 2/19/2019 | AI45: 0 | AJ45: 11
A46: Chang Donovan E | B46: 10154 | C46: 0 | D46: 0 | E46: 1 | F46: 1 | G46: 5 | H46: 3 | I46: 0 | J46: 60380 | K46: 0 | L46: 19 | M46: Production Technician I | N46: MA | O46: 1845 | P46: 08/24/83 | Q46: M | R46: Single | S46: US Citizen | T46: No | U46: White | V46: 41493 | X46: N/A-StillEmployed | Y46: Active | Z46: Production | AA46: Webster Butler | AC46: LinkedIn | AD46: Fully Meets | AE46: 3.80 | AF46: 5 | AG46: 0 | AH46: 1/14/2019 | AI46: 0 | AJ46: 4
A47: Chigurh Anton | B47: 10200 | C47: 0 | D47: 0 | E47: 1 | F47: 1 | G47: 6 | H47: 3 | I47: 0 | J47: 66808 | K47: 0 | L47: 3 | M47: Area Sales Manager | N47: TX | O47: 78207 | P47: 25878 | Q47: M | R47: Single | S47: Eligible NonCitizen | T47: No | U47: Black or African American | V47: 5/14/2012 | X47: N/A-StillEmployed | Y47: Active | Z47: Sales | AA47: Lynn Daneault | AB47: 21 | AC47: Employee Referral | AD47: Fully Meets | AE47: 3.00 | AF47: 5 | AG47: 0 | AH47: 1/19/2019 | AI47: 0 | AJ47: 17
A48: Chivukula Enola | B48: 10240 | C48: 0 | D48: 0 | E48: 0 | F48: 5 | G48: 5 | H48: 3 | I48: 0 | J48: 64786 | K48: 1 | L48: 19 | M48: Production Technician I | N48: MA | O48: 1775 | P48: 08/27/83 | Q48: F | R48: Single | S48: US Citizen | T48: No | U48: White | V48: 6/27/2011 | W48: 11/15/2015 | X48: relocation out of area | Y48: Voluntarily Terminated | Z48: Production | AA48: Amy Dunn | AB48: 11 | AC48: Indeed | AD48: Fully Meets | AE48: 4.30 | AF48: 4 | AG48: 0 | AH48: 42280 | AI48: 0 | AJ48: 3
A49: Cierpiszewski Caroline | B49: 10168 | C49: 0 | D49: 0 | E49: 0 | F49: 1 | G49: 5 | H49: 3 | I49: 0 | J49: 64816 | K49: 0 | L49: 19 | M49: Production Technician I | N49: MA | O49: 2044 | P49: 05/31/88 | Q49: F | R49: Single | S49: Non-Citizen | T49: No | U49: Black or African American | V49: 40612 | X49: N/A-StillEmployed | Y49: Active | Z49: Production | AA49: Ketsia Liebig | AB49: 19 | AC49: Indeed | AD49: Fully Meets | AE49: 3.58 | AF49: 5 | AG49: 0 | AH49: 1/30/2019 | AI49: 0 | AJ49: 3
A50: Clayton Rick | B50: 10220 | C50: 0 | D50: 0 | E50: 1 | F50: 1 | G50: 3 | H50: 3 | I50: 0 | J50: 68678 | K50: 0 | L50: 14 | M50: IT Support | N50: MA | O50: 2170 | P50: 31176 | Q50: M | R50: Single | S50: US Citizen | T50: No | U50: White | V50: 41038 | X50: N/A-StillEmployed | Y50: Active | Z50: IT/IS | AA50: Eric Dougall | AB50: 6 | AC50: Indeed | AD50: Fully Meets | AE50: 4.70 | AF50: 3 | AG50: 6 | AH50: 2/27/2019 | AI50: 0 | AJ50: 2
A51: Cloninger Jennifer | B51: 10275 | C51: 1 | D51: 1 | E51: 0 | F51: 5 | G51: 5 | H51: 3 | I51: 0 | J51: 64066 | K51: 1 | L51: 20 | M51: Production Technician II | N51: MA | O51: 1752 | P51: 08/31/81 | Q51: F | R51: Married | S51: US Citizen | T51: No | U51: White | V51: 5/16/2011 | W51: 41456 | X51: unhappy | Y51: Voluntarily Terminated | Z51: Production | AA51: Brannon Miller | AB51: 12 | AC51: Google Search | AD51: Fully Meets | AE51: 4.20 | AF51: 5 | AG51: 0 | AH51: 40973 | AI51: 0 | AJ51: 9
A52: Close Phil | B52: 10269 | C52: 1 | D52: 1 | E52: 1 | F52: 5 | G52: 5 | H52: 3 | I52: 0 | J52: 59369 | K52: 1 | L52: 20 | M52: Production Technician II | N52: MA | O52: 2169 | P52: 11/25/78 | Q52: M | R52: Married | S52: US Citizen | T52: No | U52: White | V52: 8/30/2010 | W52: 9/26/2011 | X52: career change | Y52: Voluntarily Terminated | Z52: Production | AA52: David Stanley | AB52: 14 | AC52: Indeed | AD52: Fully Meets | AE52: 4.20 | AF52: 4 | AG52: 0 | AH52: 40638 | AI52: 0 | AJ52: 6
A53: Clukey Elijian | B53: 10029 | C53: 1 | D53: 1 | E53: 1 | F53: 2 | G53: 5 | H53: 4 | I53: 0 | J53: 50373 | K53: 0 | L53: 19 | M53: Production Technician I | N53: MA | O53: 2134 | P53: 08/26/80 | Q53: M | R53: Married | S53: US Citizen | T53: No | U53: White | V53: 42528 | X53: N/A-StillEmployed | Y53: Active | Z53: Production | AA53: Brannon Miller | AB53: 12 | AC53: Employee Referral | AD53: Exceeds | AE53: 4.10 | AF53: 4 | AG53: 0 | AH53: 2/28/2019 | AI53: 0 | AJ53: 5
A54: Cockel James | B54: 10261 | C54: 0 | D54: 0 | E54: 1 | F54: 1 | G54: 5 | H54: 3 | I54: 0 | J54: 63108 | K54: 0 | L54: 19 | M54: Production Technician I | N54: MA | O54: 2452 | P54: 28346 | Q54: M | R54: Single | S54: US Citizen | T54: No | U54: White | V54: 41493 | X54: N/A-StillEmployed | Y54: Active | Z54: Production | AA54: David Stanley | AB54: 14 | AC54: Employee Referral | AD54: Fully Meets | AE54: 4.40 | AF54: 5 | AG54: 0 | AH54: 1/14/2019 | AI54: 0 | AJ54: 3
A55: Cole Spencer | B55: 10292 | C55: 0 | D55: 0 | E55: 1 | F55: 4 | G55: 5 | H55: 2 | I55: 0 | J55: 59144 | K55: 1 | L55: 19 | M55: Production Technician I | N55: MA | O55: 1880 | P55: 29197 | Q55: M | R55: Single | S55: US Citizen | T55: No | U55: Black or African American | V55: 40854 | W55: 9/23/2016 | X55: performance | Y55: Terminated for Cause | Z55: Production | AA55: Kissy Sullivan | AB55: 20 | AC55: LinkedIn | AD55: Needs Improvement | AE55: 2.00 | AF55: 3 | AG55: 0 | AH55: 42374 | AI55: 5 | AJ55: 16
A56: Corleone Michael | B56: 10282 | C56: 0 | D56: 2 | E56: 1 | F56: 1 | G56: 5 | H56: 2 | I56: 0 | J56: 68051 | K56: 0 | L56: 18 | M56: Production Manager | N56: MA | O56: 1803 | P56: 12/17/75 | Q56: M | R56: Divorced | S56: US Citizen | T56: No | U56: White | V56: 7/20/2010 | X56: N/A-StillEmployed | Y56: Active | Z56: Production | AA56: Janet King | AB56: 2 | AC56: CareerBuilder | AD56: Needs Improvement | AE56: 4.13 | AF56: 2 | AG56: 0 | AH56: 1/14/2019 | AI56: 3 | AJ56: 3
A57: Corleone Vito | B57: 10019 | C57: 0 | D57: 0 | E57: 1 | F57: 1 | G57: 5 | H57: 4 | I57: 0 | J57: 170500 | K57: 0 | L57: 10 | M57: Director of Operations | N57: MA | O57: 2030 | P57: 03/19/83 | Q57: M | R57: Single | S57: US Citizen | T57: No | U57: Black or African American | V57: 39934 | X57: N/A-StillEmployed | Y57: Active | Z57: Production | AA57: Janet King | AB57: 2 | AC57: Indeed | AD57: Exceeds | AE57: 3.70 | AF57: 5 | AG57: 0 | AH57: 43557 | AI57: 0 | AJ57: 15
A58: Cornett Lisa | B58: 10094 | C58: 1 | D58: 1 | E58: 0 | F58: 1 | G58: 5 | H58: 3 | I58: 0 | J58: 63381 | K58: 0 | L58: 19 | M58: Production Technician I | N58: MA | O58: 2189 | P58: 03/31/77 | Q58: F | R58: Married | S58: US Citizen | T58: Yes | U58: White | V58: 42125 | X58: N/A-StillEmployed | Y58: Active | Z58: Production | AA58: Kelley Spirea | AB58: 18 | AC58: Indeed | AD58: Fully Meets | AE58: 4.73 | AF58: 5 | AG58: 0 | AH58: 2/14/2019 | AI58: 0 | AJ58: 6
A59: Costello Frank | B59: 10193 | C59: 1 | D59: 1 | E59: 1 | F59: 1 | G59: 3 | H59: 3 | I59: 0 | J59: 83552 | K59: 0 | L59: 9 | M59: Data Analyst | N59: MA | O59: 1810 | P59: 08/26/86 | Q59: M | R59: Married | S59: US Citizen | T59: No | U59: White | V59: 3/30/2015 | X59: N/A-StillEmployed | Y59: Active | Z59: IT/IS | AA59: Simon Roup | AB59: 4 | AC59: Indeed | AD59: Fully Meets | AE59: 3.04 | AF59: 3 | AG59: 6 | AH59: 1/22/2019 | AI59: 0 | AJ59: 2
A60: Crimmings Jean | B60: 10132 | C60: 0 | D60: 0 | E60: 0 | F60: 2 | G60: 5 | H60: 3 | I60: 0 | J60: 56149 | K60: 0 | L60: 19 | M60: Production Technician I | N60: MA | O60: 1821 | P60: 32054 | Q60: F | R60: Single | S60: US Citizen | T60: No | U60: White | V60: 42528 | X60: N/A-StillEmployed | Y60: Active | Z60: Production | AA60: Michael Albert | AB60: 22 | AC60: LinkedIn | AD60: Fully Meets | AE60: 4.12 | AF60: 5 | AG60: 0 | AH60: 1/28/2019 | AI60: 0 | AJ60: 15
A61: Cross Noah | B61: 10083 | C61: 0 | D61: 0 | E61: 1 | F61: 1 | G61: 3 | H61: 3 | I61: 0 | J61: 92329 | K61: 0 | L61: 28 | M61: Sr. Network Engineer | N61: CT | O61: 6278 | P61: 23994 | Q61: M | R61: Single | S61: US Citizen | T61: No | U61: White | V61: 41923 | X61: N/A-StillEmployed | Y61: Active | Z61: IT/IS | AA61: Peter Monroe | AB61: 7 | AC61: Employee Referral | AD61: Fully Meets | AE61: 5.00 | AF61: 3 | AG61: 4 | AH61: 43497 | AI61: 0 | AJ61: 5
A62: Daneault Lynn | B62: 10099 | C62: 0 | D62: 0 | E62: 0 | F62: 1 | G62: 6 | H62: 3 | I62: 0 | J62: 65729 | K62: 0 | L62: 21 | M62: Sales Manager | N62: VT | O62: 5473 | P62: 04/19/90 | Q62: F | R62: Single | S62: US Citizen | T62: No | U62: White | V62: 41764 | X62: N/A-StillEmployed | Y62: Active | Z62: Sales | AA62: Debra Houlihan | AB62: 15 | AC62: Indeed | AD62: Fully Meets | AE62: 4.62 | AF62: 4 | AG62: 0 | AH62: 1/24/2019 | AI62: 0 | AJ62: 8
A63: Daniele Ann | B63: 10212 | C63: 1 | D63: 1 | E63: 0 | F63: 3 | G63: 3 | H63: 3 | I63: 0 | J63: 85028 | K63: 0 | L63: 28 | M63: Sr. Network Engineer | N63: CT | O63: 6033 | P63: 01/18/52 | Q63: F | R63: Married | S63: US Citizen | T63: No | U63: White | V63: 41923 | X63: N/A-StillEmployed | Y63: Active | Z63: IT/IS | AA63: Peter Monroe | AB63: 7 | AC63: LinkedIn | AD63: Fully Meets | AE63: 3.10 | AF63: 5 | AG63: 8 | AH63: 43801 | AI63: 0 | AJ63: 19
A64: Darson Jene'ya | B64: 10056 | C64: 1 | D64: 1 | E64: 0 | F64: 1 | G64: 5 | H64: 3 | I64: 0 | J64: 57583 | K64: 0 | L64: 19 | M64: Production Technician I | N64: MA | O64: 2110 | P64: 28621 | Q64: F | R64: Married | S64: US Citizen | T64: No | U64: White | V64: 40946 | X64: N/A-StillEmployed | Y64: Active | Z64: Production | AA64: Elijiah Gray | AB64: 16 | AC64: Indeed | AD64: Fully Meets | AE64: 5.00 | AF64: 3 | AG64: 0 | AH64: 2/25/2019 | AI64: 0 | AJ64: 1
A65: Davis Daniel | B65: 10143 | C65: 0 | D65: 0 | E65: 1 | F65: 1 | G65: 5 | H65: 3 | I65: 0 | J65: 56294 | K65: 0 | L65: 20 | M65: Production Technician II | N65: MA | O65: 2458 | P65: 09/14/79 | Q65: M | R65: Single | S65: Eligible NonCitizen | T65: No | U65: Two or more races | V65: 40735 | X65: N/A-StillEmployed | Y65: Active | Z65: Production | AA65: Kissy Sullivan | AB65: 20 | AC65: LinkedIn | AD65: Fully Meets | AE65: 3.96 | AF65: 4 | AG65: 0 | AH65: 2/27/2019 | AI65: 0 | AJ65: 6
A66: Dee Randy | B66: 10311 | C66: 1 | D66: 1 | E66: 1 | F66: 1 | G66: 6 | H66: 1 | I66: 0 | J66: 56991 | K66: 0 | L66: 19 | M66: Production Technician I | N66: MA | O66: 2138 | P66: 04/15/88 | Q66: M | R66: Married | S66: US Citizen | T66: No | U66: White | V66: 43350 | X66: N/A-StillEmployed | Y66: Active | Z66: Production | AA66: Brannon Miller | AB66: 12 | AC66: Indeed | AD66: Fully Meets | AE66: 4.3 | AF66: 4 | AG66: 3 | AH66: 1/31/2019 | AI66: 2 | AJ66: 2
A67: DeGweck James | B67: 10070 | C67: 1 | D67: 1 | E67: 1 | F67: 5 | G67: 5 | H67: 3 | I67: 0 | J67: 55722 | K67: 1 | L67: 19 | M67: Production Technician I | N67: MA | O67: 1810 | P67: 10/31/77 | Q67: M | R67: Married | S67: US Citizen | T67: No | U67: White | V67: 5/16/2011 | W67: 42588 | X67: unhappy | Y67: Voluntarily Terminated | Z67: Production | AA67: Webster Butler | AB67: 39 | AC67: Indeed | AD67: Fully Meets | AE67: 5.00 | AF67: 4 | AG67: 0 | AH67: 42404 | AI67: 0 | AJ67: 14
A68: Del Bosque Keyla | B68: 10155 | C68: 0 | D68: 0 | E68: 0 | F68: 1 | G68: 4 | H68: 3 | I68: 0 | J68: 101199 | K68: 0 | L68: 24 | M68: Software Engineer | N68: MA | O68: 2176 | P68: 28982 | Q68: F | R68: Single | S68: US Citizen | T68: No | U68: Black or African American | V68: 41153 | X68: N/A-StillEmployed | Y68: Active | Z68: Software Engineering | AA68: Alex Sweetwater | AB68: 10 | AC68: CareerBuilder | AD68: Fully Meets | AE68: 3.79 | AF68: 5 | AG68: 5 | AH68: 1/25/2019 | AI68: 0 | AJ68: 8
A69: Delarge Alex | B69: 10306 | C69: 0 | D69: 0 | E69: 1 | F69: 1 | G69: 6 | H69: 1 | I69: 0 | J69: 61568 | K69: 0 | L69: 3 | M69: Area Sales Manager | N69: AL | O69: 36006 | P69: 27436 | Q69: M | R69: Single | S69: US Citizen | T69: No | U69: Two or more races | V69: 9/29/2014 | X69: N/A-StillEmployed | Y69: Active | Z69: Sales | AA69: John Smith | AB69: 17 | AC69: Indeed | AD69: PIP | AE69: 1.93 | AF69: 3 | AG69: 0 | AH69: 1/30/2019 | AI69: 6 | AJ69: 5
A70: Demita Carla | B70: 10100 | C70: 0 | D70: 3 | E70: 0 | F70: 5 | G70: 5 | H70: 3 | I70: 0 | J70: 58275 | K70: 1 | L70: 20 | M70: Production Technician II | N70: MA | O70: 2343 | P70: 02/25/51 | Q70: F | R70: Separated | S70: US Citizen | T70: No | U70: Black or African American | V70: 40637 | W70: 42105 | X70: more money | Y70: Voluntarily Terminated | Z70: Production | AA70: Kelley Spirea | AB70: 18 | AC70: Google Search | AD70: Fully Meets | AE70: 4.62 | AF70: 5 | AG70: 0 | AH70: 42160 | AI70: 0 | AJ70: 1
A71: Desimone Carl | B71: 10310 | C71: 1 | D71: 1 | E71: 1 | F71: 1 | G71: 5 | H71: 1 | I71: 0 | J71: 53189 | K71: 0 | L71: 19 | M71: Production Technician I | N71: MA | O71: 2061 | P71: 04/19/67 | Q71: M | R71: Married | S71: US Citizen | T71: No | U71: White | V71: 41827 | X71: N/A-StillEmployed | Y71: Active | Z71: Production | AA71: Amy Dunn | AB71: 11 | AC71: Indeed | AD71: PIP | AE71: 1.12 | AF71: 2 | AG71: 0 | AH71: 1/31/2019 | AI71: 4 | AJ71: 9
A72: DeVito Tommy | B72: 10197 | C72: 0 | D72: 0 | E72: 1 | F72: 1 | G72: 3 | H72: 3 | I72: 0 | J72: 96820 | K72: 0 | L72: 4 | M72: BI Developer | N72: MA | O72: 2045 | P72: 30415 | Q72: M | R72: Single | S72: US Citizen | T72: No | U72: White | V72: 2/15/2017 | X72: N/A-StillEmployed | Y72: Active | Z72: IT/IS | AA72: Brian Champaigne | AB72: 13 | AC72: Indeed | AD72: Fully Meets | AE72: 3.01 | AF72: 5 | AG72: 7 | AH72: 1/23/2019 | AI72: 0 | AJ72: 15
A73: Dickinson Geoff | B73: 10276 | C73: 0 | D73: 0 | E73: 1 | F73: 1 | G73: 5 | H73: 3 | I73: 0 | J73: 51259 | K73: 0 | L73: 19 | M73: Production Technician I | N73: MA | O73: 2180 | P73: 11/15/82 | Q73: M | R73: Single | S73: US Citizen | T73: No | U73: White | V73: 41978 | X73: N/A-StillEmployed | Y73: Active | Z73: Production | AA73: Ketsia Liebig | AB73: 19 | AC73: Indeed | AD73: Fully Meets | AE73: 4.30 | AF73: 4 | AG73: 0 | AH73: 2/19/2019 | AI73: 0 | AJ73: 1
A74: Dietrich Jenna | B74: 10304 | C74: 0 | D74: 0 | E74: 0 | F74: 1 | G74: 6 | H74: 1 | I74: 0 | J74: 59231 | K74: 0 | L74: 3 | M74: Area Sales Manager | N74: WA | O74: 98052 | P74: 05/14/87 | Q74: F | R74: Single | S74: US Citizen | T74: Yes | U74: White | V74: 2/20/2012 | X74: N/A-StillEmployed | Y74: Active | Z74: Sales | AA74: John Smith | AB74: 17 | AC74: Website | AD74: PIP | AE74: 2.30 | AF74: 1 | AG74: 0 | AH74: 1/29/2019 | AI74: 2 | AJ74: 17
A75: DiNocco Lily | B75: 10284 | C75: 1 | D75: 1 | E75: 0 | F75: 1 | G75: 5 | H75: 2 | I75: 0 | J75: 61584 | K75: 0 | L75: 19 | M75: Production Technician I | N75: MA | O75: 2351 | P75: 28533 | Q75: F | R75: Married | S75: US Citizen | T75: No | U75: Black or African American | V75: 41456 | X75: N/A-StillEmployed | Y75: Active | Z75: Production | AA75: Brannon Miller | AB75: 12 | AC75: Indeed | AD75: Needs Improvement | AE75: 3.88 | AF75: 4 | AG75: 0 | AH75: 1/18/2019 | AI75: 0 | AJ75: 6
A76: Dobrin Denisa S | B76: 10207 | C76: 0 | D76: 0 | E76: 0 | F76: 1 | G76: 5 | H76: 3 | I76: 0 | J76: 46335 | K76: 0 | L76: 19 | M76: Production Technician I | N76: MA | O76: 2125 | P76: 31603 | Q76: F | R76: Single | S76: US Citizen | T76: Yes | U76: White | V76: 40943 | X76: N/A-StillEmployed | Y76: Active | Z76: Production | AA76: David Stanley | AB76: 14 | AC76: CareerBuilder | AD76: Fully Meets | AE76: 3.40 | AF76: 5 | AG76: 0 | AH76: 2/19/2019 | AI76: 0 | AJ76: 15
A77: Dolan Linda | B77: 10133 | C77: 1 | D77: 1 | E77: 0 | F77: 1 | G77: 3 | H77: 3 | I77: 0 | J77: 70621 | K77: 0 | L77: 14 | M77: IT Support | N77: MA | O77: 2119 | P77: 07/18/88 | Q77: F | R77: Married | S77: US Citizen | T77: No | U77: White | V77: 42125 | X77: N/A-StillEmployed | Y77: Active | Z77: IT/IS | AA77: Peter Monroe | AB77: 7 | AC77: Employee Referral | AD77: Fully Meets | AE77: 4.11 | AF77: 4 | AG77: 6 | AH77: 2/25/2019 | AI77: 0 | AJ77: 16
A78: Dougall Eric | B78: 10028 | C78: 0 | D78: 0 | E78: 1 | F78: 1 | G78: 3 | H78: 4 | I78: 0 | J78: 138888 | K78: 0 | L78: 13 | M78: IT Manager - Support | N78: MA | O78: 1886 | P78: 25818 | Q78: M | R78: Single | S78: US Citizen | T78: No | U78: Black or African American | V78: 41760 | X78: N/A-StillEmployed | Y78: Active | Z78: IT/IS | AA78: Jennifer Zamora | AB78: 5 | AC78: Indeed | AD78: Exceeds | AE78: 4.30 | AF78: 5 | AG78: 5 | AH78: 43556 | AI78: 0 | AJ78: 4
A79: Driver Elle | B79: 10006 | C79: 0 | D79: 0 | E79: 0 | F79: 1 | G79: 6 | H79: 4 | I79: 0 | J79: 74241 | K79: 0 | L79: 3 | M79: Area Sales Manager | N79: CA | O79: 90007 | P79: 32366 | Q79: F | R79: Single | S79: US Citizen | T79: No | U79: White | V79: 40817 | X79: N/A-StillEmployed | Y79: Active | Z79: Sales | AA79: Lynn Daneault | AB79: 21 | AC79: Indeed | AD79: Exceeds | AE79: 4.77 | AF79: 5 | AG79: 0 | AH79: 1/27/2019 | AI79: 0 | AJ79: 14
A80: Dunn Amy | B80: 10105 | C80: 0 | D80: 0 | E80: 0 | F80: 1 | G80: 5 | H80: 3 | I80: 0 | J80: 75188 | K80: 0 | L80: 18 | M80: Production Manager | N80: MA | O80: 1731 | P80: 11/28/73 | Q80: F | R80: Single | S80: US Citizen | T80: No | U80: White | V80: 9/18/2014 | X80: N/A-StillEmployed | Y80: Active | Z80: Production | AA80: Janet King | AB80: 2 | AC80: Google Search | AD80: Fully Meets | AE80: 4.52 | AF80: 4 | AG80: 0 | AH80: 1/15/2019 | AI80: 0 | AJ80: 4
A81: Dunne Amy | B81: 10211 | C81: 1 | D81: 1 | E81: 0 | F81: 1 | G81: 5 | H81: 3 | I81: 0 | J81: 62514 | K81: 0 | L81: 19 | M81: Production Technician I | N81: MA | O81: 1749 | P81: 09/23/73 | Q81: F | R81: Married | S81: US Citizen | T81: No | U81: White | V81: 4/26/2010 | X81: N/A-StillEmployed | Y81: Active | Z81: Production | AA81: Ketsia Liebig | AB81: 19 | AC81: Google Search | AD81: Fully Meets | AE81: 2.90 | AF81: 3 | AG81: 0 | AH81: 1/21/2019 | AI81: 0 | AJ81: 6
A82: Eaton Marianne | B82: 10064 | C82: 1 | D82: 1 | E82: 0 | F82: 5 | G82: 5 | H82: 3 | I82: 0 | J82: 60070 | K82: 1 | L82: 19 | M82: Production Technician I | N82: MA | O82: 2343 | P82: 33367 | Q82: F | R82: Married | S82: US Citizen | T82: No | U82: White | V82: 40637 | W82: 42892 | X82: military | Y82: Voluntarily Terminated | Z82: Production | AA82: Kissy Sullivan | AB82: 20 | AC82: Google Search | AD82: Fully Meets | AE82: 5.00 | AF82: 3 | AG82: 0 | AH82: 42982 | AI82: 0 | AJ82: 7
A83: Engdahl Jean | B83: 10247 | C83: 0 | D83: 0 | E83: 1 | F83: 1 | G83: 5 | H83: 3 | I83: 0 | J83: 48888 | K83: 0 | L83: 19 | M83: Production Technician I | N83: MA | O83: 2026 | P83: 05/31/74 | Q83: M | R83: Single | S83: US Citizen | T83: No | U83: White | V83: 41923 | X83: N/A-StillEmployed | Y83: Active | Z83: Production | AA83: Kelley Spirea | AB83: 18 | AC83: LinkedIn | AD83: Fully Meets | AE83: 4.70 | AF83: 5 | AG83: 0 | AH83: 2/13/2019 | AI83: 0 | AJ83: 8
A84: England Rex | B84: 10235 | C84: 1 | D84: 1 | E84: 1 | F84: 1 | G84: 5 | H84: 3 | I84: 0 | J84: 54285 | K84: 0 | L84: 19 | M84: Production Technician I | N84: MA | O84: 2045 | P84: 08/25/78 | Q84: M | R84: Married | S84: US Citizen | T84: No | U84: White | V84: 3/31/2014 | X84: N/A-StillEmployed | Y84: Active | Z84: Production | AA84: Kelley Spirea | AB84: 18 | AC84: Employee Referral | AD84: Fully Meets | AE84: 4.20 | AF84: 3 | AG84: 0 | AH84: 43770 | AI84: 0 | AJ84: 3
A85: Erilus Angela | B85: 10299 | C85: 0 | D85: 3 | E85: 0 | F85: 1 | G85: 5 | H85: 1 | I85: 0 | J85: 56847 | K85: 0 | L85: 20 | M85: Production Technician II | N85: MA | O85: 2133 | P85: 08/25/89 | Q85: F | R85: Separated | S85: US Citizen | T85: No | U85: White | V85: 41827 | X85: N/A-StillEmployed | Y85: Active | Z85: Production | AA85: Michael Albert | AB85: 22 | AC85: Indeed | AD85: PIP | AE85: 3.00 | AF85: 1 | AG85: 0 | AH85: 2/25/2019 | AI85: 2 | AJ85: 5
A86: Estremera Miguel | B86: 10280 | C86: 0 | D86: 0 | E86: 1 | F86: 4 | G86: 5 | H86: 2 | I86: 0 | J86: 60340 | K86: 1 | L86: 19 | M86: Production Technician I | N86: MA | O86: 2129 | P86: 30356 | Q86: M | R86: Single | S86: US Citizen | T86: No | U86: White | V86: 40943 | W86: 9/27/2018 | X86: attendance | Y86: Terminated for Cause | Z86: Production | AA86: Michael Albert | AB86: 22 | AC86: Google Search | AD86: Needs Improvement | AE86: 5.00 | AF86: 4 | AG86: 0 | AH86: 43438 | AI86: 5 | AJ86: 16
A87: Evensen April | B87: 10296 | C87: 0 | D87: 0 | E87: 0 | F87: 4 | G87: 5 | H87: 2 | I87: 0 | J87: 59124 | K87: 1 | L87: 19 | M87: Production Technician I | N87: MA | O87: 2458 | P87: 32664 | Q87: F | R87: Single | S87: US Citizen | T87: No | U87: White | V87: 2/17/2014 | W87: 2/25/2018 | X87: no-call, no-show | Y87: Terminated for Cause | Z87: Production | AA87: Elijiah Gray | AB87: 16 | AC87: Google Search | AD87: Needs Improvement | AE87: 2.30 | AF87: 3 | AG87: 0 | AH87: 1/15/2017 | AI87: 5 | AJ87: 19
A88: Exantus Susan | B88: 10290 | C88: 1 | D88: 1 | E88: 0 | F88: 4 | G88: 4 | H88: 2 | I88: 0 | J88: 99280 | K88: 1 | L88: 24 | M88: Software Engineer | N88: MA | O88: 1749 | P88: 05/15/87 | Q88: F | R88: Married | S88: US Citizen | T88: No | U88: Black or African American | V88: 40579 | W88: 41400 | X88: attendance | Y88: Terminated for Cause | Z88: Software Engineering | AA88: Alex Sweetwater | AB88: 10 | AC88: Indeed | AD88: Needs Improvement | AE88: 2.10 | AF88: 5 | AG88: 4 | AH88: 41190 | AI88: 4 | AJ88: 19
A89: Faller Megan | B89: 10263 | C89: 1 | D89: 1 | E89: 0 | F89: 1 | G89: 5 | H89: 3 | I89: 0 | J89: 71776 | K89: 0 | L89: 20 | M89: Production Technician II | N89: MA | O89: 1824 | P89: 09/22/78 | Q89: F | R89: Married | S89: US Citizen | T89: No | U89: Black or African American | V89: 41827 | X89: N/A-StillEmployed | Y89: Active | Z89: Production | AA89: Elijiah Gray | AB89: 16 | AC89: LinkedIn | AD89: Fully Meets | AE89: 4.40 | AF89: 5 | AG89: 0 | AH89: 2/22/2019 | AI89: 0 | AJ89: 17
A90: Fancett Nicole | B90: 10136 | C90: 0 | D90: 0 | E90: 0 | F90: 1 | G90: 5 | H90: 3 | I90: 0 | J90: 65902 | K90: 0 | L90: 20 | M90: Production Technician II | N90: MA | O90: 2324 | P90: 09/27/87 | Q90: F | R90: Single | S90: US Citizen | T90: No | U90: Black or African American | V90: 2/17/2014 | X90: N/A-StillEmployed | Y90: Active | Z90: Production | AA90: Webster Butler | AC90: LinkedIn | AD90: Fully Meets | AE90: 4.00 | AF90: 4 | AG90: 0 | AH90: 43647 | AI90: 0 | AJ90: 7
A91: Ferguson Susan | B91: 10189 | C91: 1 | D91: 1 | E91: 0 | F91: 5 | G91: 5 | H91: 3 | I91: 0 | J91: 57748 | K91: 1 | L91: 19 | M91: Production Technician I | N91: MA | O91: 2176 | P91: 04/14/55 | Q91: F | R91: Married | S91: US Citizen | T91: No | U91: White | V91: 40735 | W91: 5/17/2016 | X91: military | Y91: Voluntarily Terminated | Z91: Production | AA91: Webster Butler | AB91: 39 | AC91: Google Search | AD91: Fully Meets | AE91: 3.13 | AF91: 3 | AG91: 0 | AH91: 42462 | AI91: 0 | AJ91: 16
A92: Fernandes Nilson | B92: 10308 | C92: 1 | D92: 1 | E92: 1 | F92: 1 | G92: 5 | H92: 1 | I92: 0 | J92: 64057 | K92: 0 | L92: 19 | M92: Production Technician I | N92: MA | O92: 2132 | P92: 10/18/89 | Q92: M | R92: Married | S92: US Citizen | T92: No | U92: White | V92: 42313 | X92: N/A-StillEmployed | Y92: Active | Z92: Production | AA92: Amy Dunn | AB92: 11 | AC92: Indeed | AD92: PIP | AE92: 1.56 | AF92: 5 | AG92: 0 | AH92: 43525 | AI92: 6 | AJ92: 15
A93: Fett Boba | B93: 10309 | C93: 0 | D93: 0 | E93: 1 | F93: 1 | G93: 3 | H93: 1 | I93: 0 | J93: 53366 | K93: 0 | L93: 15 | M93: Network Engineer | N93: MA | O93: 2138 | P93: 06/18/87 | Q93: M | R93: Single | S93: US Citizen | T93: No | U93: White | V93: 3/30/2015 | X93: N/A-StillEmployed | Y93: Active | Z93: IT/IS | AA93: Peter Monroe | AB93: 7 | AC93: LinkedIn | AD93: PIP | AE93: 1.20 | AF93: 3 | AG93: 6 | AH93: 43557 | AI93: 3 | AJ93: 2
A94: Fidelia Libby | B94: 10049 | C94: 1 | D94: 1 | E94: 0 | F94: 1 | G94: 5 | H94: 3 | I94: 0 | J94: 58530 | K94: 0 | L94: 19 | M94: Production Technician I | N94: MA | O94: 2155 | P94: 03/16/81 | Q94: F | R94: Married | S94: US Citizen | T94: No | U94: White | V94: 41153 | X94: N/A-StillEmployed | Y94: Active | Z94: Production | AA94: Brannon Miller | AB94: 12 | AC94: Google Search | AD94: Fully Meets | AE94: 5.00 | AF94: 5 | AG94: 0 | AH94: 1/29/2019 | AI94: 0 | AJ94: 19
A95: Fitzpatrick Michael J | B95: 10093 | C95: 0 | D95: 0 | E95: 1 | F95: 5 | G95: 5 | H95: 3 | I95: 0 | J95: 72609 | K95: 1 | L95: 20 | M95: Production Technician II | N95: MA | O95: 2143 | P95: 29596 | Q95: M | R95: Single | S95: US Citizen | T95: Yes | U95: White | V95: 5/16/2011 | W95: 6/24/2013 | X95: hours | Y95: Voluntarily Terminated | Z95: Production | AA95: Amy Dunn | AB95: 11 | AC95: Google Search | AD95: Fully Meets | AE95: 4.76 | AF95: 5 | AG95: 0 | AH95: 41398 | AI95: 0 | AJ95: 20
A96: Foreman Tanya | B96: 10163 | C96: 1 | D96: 1 | E96: 0 | F96: 5 | G96: 5 | H96: 3 | I96: 0 | J96: 55965 | K96: 1 | L96: 20 | M96: Production Technician II | N96: MA | O96: 2170 | P96: 30539 | Q96: F | R96: Married | S96: US Citizen | T96: No | U96: White | V96: 40637 | W96: 41518 | X96: career change | Y96: Voluntarily Terminated | Z96: Production | AA96: Ketsia Liebig | AB96: 19 | AC96: Google Search | AD96: Fully Meets | AE96: 3.66 | AF96: 3 | AG96: 0 | AH96: 41091 | AI96: 0 | AJ96: 6
A97: Forrest Alex | B97: 10305 | C97: 1 | D97: 1 | E97: 1 | F97: 1 | G97: 6 | H97: 3 | I97: 0 | J97: 70187 | K97: 1 | L97: 3 | M97: Area Sales Manager | N97: MA | O97: 2330 | P97: 27582 | Q97: M | R97: Married | S97: US Citizen | T97: No | U97: White | V97: 9/29/2014 | W97: 8/19/2018 | X97: Fatal attraction | Y97: Terminated for Cause | Z97: Sales | AA97: Lynn Daneault | AB97: 21 | AC97: Employee Referral | AD97: PIP | AE97: 2.00 | AF97: 5 | AG97: 0 | AH97: 1/28/2019 | AI97: 4 | AJ97: 7
A98: Foss Jason | B98: 10015 | C98: 0 | D98: 0 | E98: 1 | F98: 1 | G98: 3 | H98: 4 | I98: 0 | J98: 178000 | K98: 0 | L98: 12 | M98: IT Director | N98: MA | O98: 1460 | P98: 29348 | Q98: M | R98: Single | S98: US Citizen | T98: No | U98: Black or African American | V98: 4/15/2011 | X98: N/A-StillEmployed | Y98: Active | Z98: IT/IS | AA98: Jennifer Zamora | AB98: 5 | AC98: Indeed | AD98: Exceeds | AE98: 5.00 | AF98: 5 | AG98: 5 | AH98: 43647 | AI98: 0 | AJ98: 15
A99: Foster-Baker Amy | B99: 10080 | C99: 1 | D99: 1 | E99: 0 | F99: 1 | G99: 1 | H99: 3 | I99: 0 | J99: 99351 | K99: 0 | L99: 26 | M99: Sr. Accountant | N99: MA | O99: 2050 | P99: 04/16/79 | Q99: F | R99: Married | S99: US Citizen | T99: no | U99: White | V99: 39934 | X99: N/A-StillEmployed | Y99: Active | Z99: Admin Offices | AA99: Board of Directors | AB99: 9 | AC99: Other | AD99: Fully Meets | AE99: 5.00 | AF99: 3 | AG99: 2 | AH99: 43679 | AI99: 0 | AJ99: 3
A100: Fraval Maruk | B100: 10258 | C100: 0 | D100: 0 | E100: 1 | F100: 1 | G100: 6 | H100: 3 | I100: 0 | J100: 67251 | K100: 0 | L100: 3 | M100: Area Sales Manager | N100: CT | O100: 6050 | P100: 08/28/63 | Q100: M | R100: Single | S100: US Citizen | T100: No | U100: Black or African American | V100: 40703 | X100: N/A-StillEmployed | Y100: Active | Z100: Sales | AA100: Lynn Daneault | AB100: 21 | AC100: CareerBuilder | AD100: Fully Meets | AE100: 4.30 | AF100: 3 | AG100: 0 | AH100: 1/27/2019 | AI100: 2 | AJ100: 7
...

Sheet Feuil3
A3: Étiquettes de lignes | B3: Somme de Termd2 | C3: Somme de Termd
A4: Admin Offices | B4: 0.019230769 | C4: 2
A5: Executive Office | B5: 0 | C5: 0
A6: IT/IS | B6: 0.096153846 | C6: 10
A7: Production | B7: 0.79807692 | C7: 83
A8: Sales | B8: 0.048076923 | C8: 5
A9: Software Engineering | B9: 0.038461538 | C9: 4
A10: (vide) | B10: 0
A11: Total général | B11: 1 | C11: 104

Sheet Feuil4
A3: Étiquettes de lignes | B3: Moyenne de Salary
A4: Exceeds | B4: 77144.865
A5: Fully Meets | B5: 68421.025
A6: Needs Improvement | B6: 68407.556
A7: PIP | B7: 57956
A8: (vide)
A9: Total général | B9: 69020.685

Sheet Feuil5
A3: Étiquettes de lignes | B3: Nombre de Recrutment
A4: CareerBuilder | B4: 23
A5: Diversity Job Fair | B5: 29
A6: Employee Referral | B6: 31
A7: Google Search | B7: 49
A8: Indeed | B8: 87
A9: LinkedIn | B9: 76
A10: On-line Web application | B10: 1
A11: Other | B11: 2
A12: Website | B12: 13
A13: (vide)
A14: Total général | B14: 311

Sheet Feuil6
A3: Étiquettes de lignes | B3: Moyenne de Absences
A4: Exceeds | B4: 10.486486
A5: Fully Meets | B5: 10.242798
A6: Needs Improvement | B6: 11.333333
A7: PIP | B7: 7.9230769
A8: (vide)
A9: Total général | B9: 10.237942

Sheet Feuil9
A3: Nombre de Employee_Name | B3: Étiquettes de colonnes
A4: Étiquettes de lignes | B4: FAIBLE | C4: SURVEILLER | D4: (vide) | E4: Total général
A5: Admin Offices | B5: 0.019292605 | C5: 0.0096463023 | D5: 0 | E5: 0.028938907
A6: Executive Office | B6: 0.0032154341 | C6: 0 | D6: 0 | E6: 0.0032154341
A7: IT/IS | B7: 0.080385852 | C7: 0.080385852 | D7: 0 | E7: 0.1607717
A8: Production | B8: 0.33440514 | C8: 0.33762058 | D8: 0 | E8: 0.67202572
A9: Sales | B9: 0.048231511 | C9: 0.051446945 | D9: 0 | E9: 0.099678457
A10: Software Engineering | B10: 0.022508039 | C10: 0.012861736 | D10: 0 | E10: 0.035369775
A11: (vide) | B11: 0 | C11: 0 | D11: 0 | E11: 0
A12: Total général | B12: 0.50803859 | C12: 0.49196141 | D12: 0 | E12: 1

Sheet Feuil1
A1: Employee_Name | B1: EmpID | C1: MarriedID | D1: MaritalStatuID | E1: GenderIS | F1: EmpstatutID | G1: DeptID | H1: PerfScoreID | I1: FromDiver | J1: Salary | K1: Termd | L1: PositionID | M1: Psition | N1: State | O1: Zip | P1: DOB | Q1: Sex | R1: MaritalDESC | S1: Citizedesc | T1: HispanicLatin | U1: Racedesc | V1: Dateofhire | W1: Dateoftermi | X1: Termreason | Y1: Employement | Z1: Department | AA1: Managernat | AB1: ManagerID | AC1: Recrutment | AD1: Performance | AE1: Engagement | AF1: EmploySatisfy | AG1: SpecialProjet | AH1: LastPERF | AI1: DayLatel | AJ1: Absences | AK1: Age | AL1: Anciennete | AM1: Type_depart | AN1: Trancge_Age | AO1: Groupe_PERFORMANCE | AP1: Risque_départ
A2: Adinolfi Wilson K | B2: 10026 | C2: 0 | D2: 0 | E2: 1 | F2: 1 | G2: 5 | H2: 4 | I2: 0 | J2: 62506 | K2: 0 | L2: 19 | M2: Production Technician I | N2: MA | O2: 1960 | P2: 30596 | Q2: M | R2: Single | S2: US Citizen | T2: No | U2: White | V2: 40670 | X2: N/A-StillEmployed | Y2: Active | Z2: Production | AA2: Michael Albert | AB2: 22 | AC2: LinkedIn | AD2: Exceeds | AE2: 4.60 | AF2: 5 | AG2: 0 | AH2: 1/17/2019 | AI2: 0 | AJ2: 1 | AK2: =DATEDIF(P2, TODAY(), "Y") -> 42 | AL2: =INT((IF(K2=0, TODAY(), W2) - V2) / 365.25) -> 14 | AM2: =IF(K2=0, "Actif", IF(OR(X2="Another position", X2="more money", X2="unhappy", X2="career change", X2="return to school", X2="relocation out of area", X2="medical issues", X2="military", X2="retiring"), "Volontaire", "Involontaire")) -> Actif | AN2: =IF(AK2<30, "Moins de 30", IF(AK2<45, "30-44 ans", IF(AK2<60, "45-59 ans", "60 ans et plus"))) -> 30-44 ans | AO2: =IF(H2=1, "PIP", IF(H2=2, "Needs Improvement", IF(H2=3, "Fully Meets", IF(H2=4, "Exceeds", "Non défini")))) -> Exceeds | AP2: =IF(AND(AE2<3, AF2<3, AJ2>15), "CRITIQUE", IF(OR(AE2<3, AJ2>10), "SURVEILLER", "FAIBLE")) -> FAIBLE
A3: Ait Sidi Karthikeyan | B3: 10084 | C3: 1 | D3: 1 | E3: 1 | F3: 5 | G3: 3 | H3: 3 | I3: 0 | J3: 104437 | K3: 1 | L3: 27 | M3: Sr. DBA | N3: MA | O3: 2148 | P3: 27519 | Q3: M | R3: Married | S3: US Citizen | T3: No | U3: White | V3: 42093 | W3: 42537 | X3: career change | Y3: Voluntarily Terminated | Z3: IT/IS | AA3: Simon Roup | AB3: 4 | AC3: Indeed | AD3: Fully Meets | AE3: 4.96 | AF3: 3 | AG3: 6 | AH3: 2/24/2016 | AI3: 0 | AJ3: 17 | AK3: =DATEDIF(P2, TODAY(), "Y") -> 42 | AL3: =INT((IF(K3=0, TODAY(), W3) - V3) / 365.25) -> 1 | AM3: =IF(K3=0, "Actif", IF(OR(X3="Another position", X3="more money", X3="unhappy", X3="career change", X3="return to school", X3="relocation out of area", X3="medical issues", X3="military", X3="retiring"), "Volontaire", "Involontaire")) -> Volontaire | AN3: =IF(AK3<30, "Moins de 30", IF(AK3<45, "30-44 ans", IF(AK3<60, "45-59 ans", "60 ans et plus"))) -> 30-44 ans | AO3: =IF(H3=1, "PIP", IF(H3=2, "Needs Improvement", IF(H3=3, "Fully Meets", IF(H3=4, "Exceeds", "Non défini")))) -> Fully Meets | AP3: =IF(AND(AE3<3, AF3<3, AJ3>15), "CRITIQUE", IF(OR(AE3<3, AJ3>10), "SURVEILLER", "FAIBLE")) -> SURVEILLER
A4: Akinkuolie Sarah | B4: 10196 | C4: 1 | D4: 1 | E4: 0 | F4: 5 | G4: 5 | H4: 3 | I4: 0 | J4: 64955 | K4: 1 | L4: 20 | M4: Production Technician II | N4: MA | O4: 1810 | P4: 32405 | Q4: F | R4: Married | S4: US Citizen | T4: No | U4: White | V4: 40670 | W4: 41176 | X4: hours | Y4: Voluntarily Terminated | Z4: Production | AA4: Kissy Sullivan | AB4: 20 | AC4: LinkedIn | AD4: Fully Meets | AE4: 3.02 | AF4: 3 | AG4: 0 | AH4: 5/15/2012 | AI4: 0 | AJ4: 3 | AK4: =DATEDIF(P4, TODAY(), "Y") -> 37 | AL4: =INT((IF(K4=0, TODAY(), W4) - V4) / 365.25) -> 1 | AM4: =IF(K4=0, "Actif", IF(OR(X4="Another position", X4="more money", X4="unhappy", X4="career change", X4="return to school", X4="relocation out of area", X4="medical issues", X4="military", X4="retiring"), "Volontaire", "Involontaire")) -> Involontaire | AN4: =IF(AK4<30, "Moins de 30", IF(AK4<45, "30-44 ans", IF(AK4<60, "45-59 ans", "60 ans et plus"))) -> 30-44 ans | AO4: =IF(H4=1, "PIP", IF(H4=2, "Needs Improvement", IF(H4=3, "Fully Meets", IF(H4=4, "Exceeds", "Non défini")))) -> Fully Meets | AP4: =IF(AND(AE4<3, AF4<3, AJ4>15), "CRITIQUE", IF(OR(AE4<3, AJ4>10), "SURVEILLER", "FAIBLE")) -> FAIBLE
A5: Alagbe Trina | B5: 10088 | C5: 1 | D5: 1 | E5: 0 | F5: 1 | G5: 5 | H5: 3 | I5: 0 | J5: 64991 | K5: 0 | L5: 19 | M5: Production Technician I | N5: MA | O5: 1886 | P5: 32413 | Q5: F | R5: Married | S5: US Citizen | T5: No | U5: White | V5: 39630 | X5: N/A-StillEmployed | Y5: Active | Z5: Production | AA5: Elijiah Gray | AB5: 16 | AC5: Indeed | AD5: Fully Meets | AE5: 4.84 | AF5: 5 | AG5: 0 | AH5: 43525 | AI5: 0 | AJ5: 15 | AK5: =DATEDIF(P5, TODAY(), "Y") -> 37 | AL5: =INT((IF(K5=0, TODAY(), W5) - V5) / 365.25) -> 17 | AM5: =IF(K5=0, "Actif", IF(OR(X5="Another position", X5="more money", X5="unhappy", X5="career change", X5="return to school", X5="relocation out of area", X5="medical issues", X5="military", X5="retiring"), "Volontaire", "Involontaire")) -> Actif | AN5: =IF(AK5<30, "Moins de 30", IF(AK5<45, "30-44 ans", IF(AK5<60, "45-59 ans", "60 ans et plus"))) -> 30-44 ans | AO5: =IF(H5=1, "PIP", IF(H5=2, "Needs Improvement", IF(H5=3, "Fully Meets", IF(H5=4, "Exceeds", "Non défini")))) -> Fully Meets | AP5: =IF(AND(AE5<3, AF5<3, AJ5>15), "CRITIQUE", IF(OR(AE5<3, AJ5>10), "SURVEILLER", "FAIBLE")) -> SURVEILLER
A6: Anderson Carol | B6: 10069 | C6: 0 | D6: 2 | E6: 0 | F6: 5 | G6: 5 | H6: 3 | I6: 0 | J6: 50825 | K6: 1 | L6: 19 | M6: Production Technician I | N6: MA | O6: 2169 | P6: 32729 | Q6: F | R6: Divorced | S6: US Citizen | T6: No | U6: White | V6: 40854 | W6: 42530 | X6: return to school | Y6: Voluntarily Terminated | Z6: Production | AA6: Webster Butler | AB6: 39 | AC6: Google Search | AD6: Fully Meets | AE6: 5.00 | AF6: 4 | AG6: 0 | AH6: 42371 | AI6: 0 | AJ6: 2 | AK6: =DATEDIF(P6, TODAY(), "Y") -> 36 | AL6: =INT((IF(K6=0, TODAY(), W6) - V6) / 365.25) -> 4 | AM6: =IF(K6=0, "Actif", IF(OR(X6="Another position", X6="more money", X6="unhappy", X6="career change", X6="return to school", X6="relocation out of area", X6="medical issues", X6="military", X6="retiring"), "Volontaire", "Involontaire")) -> Volontaire | AN6: =IF(AK6<30, "Moins de 30", IF(AK6<45, "30-44 ans", IF(AK6<60, "45-59 ans", "60 ans et plus"))) -> 30-44 ans | AO6: =IF(H6=1, "PIP", IF(H6=2, "Needs Improvement", IF(H6=3, "Fully Meets", IF(H6=4, "Exceeds", "Non défini")))) -> Fully Meets | AP6: =IF(AND(AE6<3, AF6<3, AJ6>15), "CRITIQUE", IF(OR(AE6<3, AJ6>10), "SURVEILLER", "FAIBLE")) -> FAIBLE
A7: Anderson Linda | B7: 10002 | C7: 0 | D7: 0 | E7: 0 | F7: 1 | G7: 5 | H7: 4 | I7: 0 | J7: 57568 | K7: 0 | L7: 19 | M7: Production Technician I | N7: MA | O7: 1844 | P7: 28267 | Q7: F | R7: Single | S7: US Citizen | T7: No | U7: White | V7: 41153 | X7: N/A-StillEmployed | Y7: Active | Z7: Production | AA7: Amy Dunn | AB7: 11 | AC7: LinkedIn | AD7: Exceeds | AE7: 5.00 | AF7: 5 | AG7: 0 | AH7: 43647 | AI7: 0 | AJ7: 15 | AK7: =DATEDIF(P7, TODAY(), "Y") -> 48 | AL7: =INT((IF(K7=0, TODAY(), W7) - V7) / 365.25) -> 13 | AM7: =IF(K7=0, "Actif", IF(OR(X7="Another position", X7="more money", X7="unhappy", X7="career change", X7="return to school", X7="relocation out of area", X7="medical issues", X7="military", X7="retiring"), "Volontaire", "Involontaire")) -> Actif | AN7: =IF(AK7<30, "Moins de 30", IF(AK7<45, "30-44 ans", IF(AK7<60, "45-59 ans", "60 ans et plus"))) -> 45-59 ans | AO7: =IF(H7=1, "PIP", IF(H7=2, "Needs Improvement", IF(H7=3, "Fully Meets", IF(H7=4, "Exceeds", "Non défini")))) -> Exceeds | AP7: =IF(AND(AE7<3, AF7<3, AJ7>15), "CRITIQUE", IF(OR(AE7<3, AJ7>10), "SURVEILLER", "FAIBLE")) -> SURVEILLER
A8: Andreola Colby | B8: 10194 | C8: 0 | D8: 0 | E8: 0 | F8: 1 | G8: 4 | H8: 3 | I8: 0 | J8: 95660 | K8: 0 | L8: 24 | M8: Software Engineer | N8: MA | O8: 2110 | P8: 28999 | Q8: F | R8: Single | S8: US Citizen | T8: No | U8: White | V8: 41923 | X8: N/A-StillEmployed | Y8: Active | Z8: Software Engineering | AA8: Alex Sweetwater | AB8: 10 | AC8: LinkedIn | AD8: Fully Meets | AE8: 3.04 | AF8: 3 | AG8: 4 | AH8: 43497 | AI8: 0 | AJ8: 19 | AK8: =DATEDIF(P8, TODAY(), "Y") -> 46 | AL8: =INT((IF(K8=0, TODAY(), W8) - V8) / 365.25) -> 11 | AM8: =IF(K8=0, "Actif", IF(OR(X8="Another position", X8="more money", X8="unhappy", X8="career change", X8="return to school", X8="relocation out of area", X8="medical issues", X8="military", X8="retiring"), "Volontaire", "Involontaire")) -> Actif | AN8: =IF(AK8<30, "Moins de 30", IF(AK8<45, "30-44 ans", IF(AK8<60, "45-59 ans", "60 ans et plus"))) -> 45-59 ans | AO8: =IF(H8=1, "PIP", IF(H8=2, "Needs Improvement", IF(H8=3, "Fully Meets", IF(H8=4, "Exceeds", "Non défini")))) -> Fully Meets | AP8: =IF(AND(AE8<3, AF8<3, AJ8>15), "CRITIQUE", IF(OR(AE8<3, AJ8>10), "SURVEILLER", "FAIBLE")) -> SURVEILLER
A9: Athwal Sam | B9: 10062 | C9: 0 | D9: 4 | E9: 1 | F9: 1 | G9: 5 | H9: 3 | I9: 0 | J9: 59365 | K9: 0 | L9: 19 | M9: Production Technician I | N9: MA | O9: 2199 | P9: 30365 | Q9: M | R9: Widowed | S9: US Citizen | T9: No | U9: White | V9: 41547 | X9: N/A-StillEmployed | Y9: Active | Z9: Production | AA9: Ketsia Liebig | AB9: 19 | AC9: Employee Referral | AD9: Fully Meets | AE9: 5.00 | AF9: 4 | AG9: 0 | AH9: 2/25/2019 | AI9: 0 | AJ9: 19 | AK9: =DATEDIF(P9, TODAY(), "Y") -> 43 | AL9: =INT((IF(K9=0, TODAY(), W9) - V9) / 365.25) -> 12 | AM9: =IF(K9=0, "Actif", IF(OR(X9="Another position", X9="more money", X9="unhappy", X9="career change", X9="return to school", X9="relocation out of area", X9="medical issues", X9="military", X9="retiring"), "Volontaire", "Involontaire")) -> Actif | AN9: =IF(AK9<30, "Moins de 30", IF(AK9<45, "30-44 ans", IF(AK9<60, "45-59 ans", "60 ans et plus"))) -> 30-44 ans | AO9: =IF(H9=1, "PIP", IF(H9=2, "Needs Improvement", IF(H9=3, "Fully Meets", IF(H9=4, "Exceeds", "Non défini")))) -> Fully Meets | AP9: =IF(AND(AE9<3, AF9<3, AJ9>15), "CRITIQUE", IF(OR(AE9<3, AJ9>10), "SURVEILLER", "FAIBLE")) -> SURVEILLER
A10: Bachiochi Linda | B10: 10114 | C10: 0 | D10: 0 | E10: 0 | F10: 3 | G10: 5 | H10: 3 | I10: 1 | J10: 47837 | K10: 0 | L10: 19 | M10: Production Technician I | N10: MA | O10: 1902 | P10: 25874 | Q10: F | R10: Single | S10: US Citizen | T10: No | U10: Black or African American | V10: 39971 | X10: N/A-StillEmployed | Y10: Active | Z10: Production | AA10: Brannon Miller | AB10: 12 | AC10: Diversity Job Fair | AD10: Fully Meets | AE10: 4.46 | AF10: 3 | AG10: 0 | AH10: 1/25/2019 | AI10: 0 | AJ10: 4 | AK10: =DATEDIF(P10, TODAY(), "Y") -> 55 | AL10: =INT((IF(K10=0, TODAY(), W10) - V10) / 365.25) -> 16 | AM10: =IF(K10=0, "Actif", IF(OR(X10="Another position", X10="more money", X10="unhappy", X10="career change", X10="return to school", X10="relocation out of area", X10="medical issues", X10="military", X10="retiring"), "Volontaire", "Involontaire")) -> Actif | AN10: =IF(AK10<30, "Moins de 30", IF(AK10<45, "30-44 ans", IF(AK10<60, "45-59 ans", "60 ans et plus"))) -> 45-59 ans | AO10: =IF(H10=1, "PIP", IF(H10=2, "Needs Improvement", IF(H10=3, "Fully Meets", IF(H10=4, "Exceeds", "Non défini")))) -> Fully Meets | AP10: =IF(AND(AE10<3, AF10<3, AJ10>15), "CRITIQUE", IF(OR(AE10<3, AJ10>10), "SURVEILLER", "FAIBLE")) -> FAIBLE
A11: Bacong Alejandro | B11: 10250 | C11: 0 | D11: 2 | E11: 1 | F11: 1 | G11: 3 | H11: 3 | I11: 0 | J11: 50178 | K11: 0 | L11: 14 | M11: IT Support | N11: MA | O11: 1886 | P11: 32325 | Q11: M | R11: Divorced | S11: US Citizen | T11: No | U11: White | V11: 42125 | X11: N/A-StillEmployed | Y11: Active | Z11: IT/IS | AA11: Peter Monroe | AB11: 7 | AC11: Indeed | AD11: Fully Meets | AE11: 5.00 | AF11: 5 | AG11: 6 | AH11: 2/18/2019 | AI11: 0 | AJ11: 16 | AK11: =DATEDIF(P11, TODAY(), "Y") -> 37 | AL11: =INT((IF(K11=0, TODAY(), W11) - V11) / 365.25) -> 10 | AM11: =IF(K11=0, "Actif", IF(OR(X11="Another position", X11="more money", X11="unhappy", X11="career change", X11="return to school", X11="relocation out of area", X11="medical issues", X11="military", X11="retiring"), "Volontaire", "Involontaire")) -> Actif | AN11: =IF(AK11<30, "Moins de 30", IF(AK11<45, "30-44 ans", IF(AK11<60, "45-59 ans", "60 ans et plus"))) -> 30-44 ans | AO11: =IF(H11=1, "PIP", IF(H11=2, "Needs Improvement", IF(H11=3, "Fully Meets", IF(H11=4, "Exceeds", "Non défini")))) -> Fully Meets | AP11: =IF(AND(AE11<3, AF11<3, AJ11>15), "CRITIQUE", IF(OR(AE11<3, AJ11>10), "SURVEILLER", "FAIBLE")) -> SURVEILLER
A12: Baczenski Rachael | B12: 10252 | C12: 1 | D12: 1 | E12: 0 | F12: 5 | G12: 5 | H12: 3 | I12: 1 | J12: 54670 | K12: 1 | L12: 19 | M12: Production Technician I | N12: MA | O12: 1902 | P12: 27364 | Q12: F | R12: Married | S12: US Citizen | T12: Yes | U12: Black or African American | V12: 40817 | W12: 43070 | X12: Another position | Y12: Voluntarily Terminated | Z12: Production | AA12: David Stanley | AB12: 14 | AC12: Diversity Job Fair | AD12: Fully Meets | AE12: 4.20 | AF12: 4 | AG12: 0 | AH12: 1/30/2016 | AI12: 0 | AJ12: 12 | AK12: =DATEDIF(P12, TODAY(), "Y") -> 51 | AL12: =INT((IF(K12=0, TODAY(), W12) - V12) / 365.25) -> 6 | AM12: =IF(K12=0, "Actif", IF(OR(X12="Another position", X12="more money", X12="unhappy", X12="career change", X12="return to school", X12="relocation out of area", X12="medical issues", X12="military", X12="retiring"), "Volontaire", "Involontaire")) -> Volontaire | AN12: =IF(AK12<30, "Moins de 30", IF(AK12<45, "30-44 ans", IF(AK12<60, "45-59 ans", "60 ans et plus"))) -> 45-59 ans | AO12: =IF(H12=1, "PIP", IF(H12=2, "Needs Improvement", IF(H12=3, "Fully Meets", IF(H12=4, "Exceeds", "Non défini")))) -> Fully Meets | AP12: =IF(AND(AE12<3, AF12<3, AJ12>15), "CRITIQUE", IF(OR(AE12<3, AJ12>10), "SURVEILLER", "FAIBLE")) -> SURVEILLER
A13: Barbara Thomas | B13: 10242 | C13: 1 | D13: 1 | E13: 1 | F13: 5 | G13: 5 | H13: 3 | I13: 1 | J13: 47211 | K13: 1 | L13: 19 | M13: Production Technician I | N13: MA | O13: 2062 | P13: 27081 | Q13: M | R13: Married | S13: US Citizen | T13: Yes | U13: Black or African American | V13: 40943 | W13: 42632 | X13: unhappy | Y13: Voluntarily Terminated | Z13: Production | AA13: Kissy Sullivan | AB13: 20 | AC13: Diversity Job Fair | AD13: Fully Meets | AE13: 4.20 | AF13: 3 | AG13: 0 | AH13: 42526 | AI13: 0 | AJ13: 15 | AK13: =DATEDIF(P13, TODAY(), "Y") -> 52 | AL13: =INT((IF(K13=0, TODAY(), W13) - V13) / 365.25) -> 4 | AM13: =IF(K13=0, "Actif", IF(OR(X13="Another position", X13="more money", X13="unhappy", X13="career change", X13="return to school", X13="relocation out of area", X13="medical issues", X13="military", X13="retiring"), "Volontaire", "Involontaire")) -> Volontaire | AN13: =IF(AK13<30, "Moins de 30", IF(AK13<45, "30-44 ans", IF(AK13<60, "45-59 ans", "60 ans et plus"))) -> 45-59 ans | AO13: =IF(H13=1, "PIP", IF(H13=2, "Needs Improvement", IF(H13=3, "Fully Meets", IF(H13=4, "Exceeds", "Non défini")))) -> Fully Meets | AP13: =IF(AND(AE13<3, AF13<3, AJ13>15), "CRITIQUE", IF(OR(AE13<3, AJ13>10), "SURVEILLER", "FAIBLE")) -> SURVEILLER
A14: Barbossa Hector | B14: 10012 | C14: 0 | D14: 2 | E14: 1 | F14: 1 | G14: 3 | H14: 4 | I14: 1 | J14: 92328 | K14: 0 | L14: 9 | M14: Data Analyst | N14: TX | O14: 78230 | P14: 32240 | Q14: M | R14: Divorced | S14: US Citizen | T14: No | U14: Black or African American | V14: 41923 | X14: N/A-StillEmployed | Y14: Active | Z14: IT/IS | AA14: Simon Roup | AB14: 4 | AC14: Diversity Job Fair | AD14: Exceeds | AE14: 4.28 | AF14: 4 | AG14: 5 | AH14: 2/25/2019 | AI14: 0 | AJ14: 9 | AK14: =DATEDIF(P14, TODAY(), "Y") -> 37 | AL14: =INT((IF(K14=0, TODAY(), W14) - V14) / 365.25) -> 11 | AM14: =IF(K14=0, "Actif", IF(OR(X14="Another position", X14="more money", X14="unhappy", X14="career change", X14="return to school", X14="relocation out of area", X14="medical issues", X14="military", X14="retiring"), "Volontaire", "Involontaire")) -> Actif | AN14: =IF(AK14<30, "Moins de 30", IF(AK14<45, "30-44 ans", IF(AK14<60, "45-59 ans", "60 ans et plus"))) -> 30-44 ans | AO14: =IF(H14=1, "PIP", IF(H14=2, "Needs Improvement", IF(H14=3, "Fully Meets", IF(H14=4, "Exceeds", "Non défini")))) -> Exceeds | AP14: =IF(AND(AE14<3, AF14<3, AJ14>15), "CRITIQUE", IF(OR(AE14<3, AJ14>10), "SURVEILLER", "FAIBLE")) -> FAIBLE
A15: Barone Francesco A | B15: 10265 | C15: 0 | D15: 0 | E15: 1 | F15: 1 | G15: 5 | H15: 3 | I15: 0 | J15: 58709 | K15: 0 | L15: 19 | M15: Production Technician I | N15: MA | O15: 1810 | P15: 30517 | Q15: M | R15: Single | S15: US Citizen | T15: No | U15: Two or more races | V15: 40959 | X15: N/A-StillEmployed | Y15: Active | Z15: Production | AA15: Kelley Spirea | AB15: 18 | AC15: Google Search | AD15: Fully Meets | AE15: 4.60 | AF15: 4 | AG15: 0 | AH15: 2/14/2019 | AI15: 0 | AJ15: 7 | AK15: =DATEDIF(P15, TODAY(), "Y") -> 42 | AL15: =INT((IF(K15=0, TODAY(), W15) - V15) / 365.25) -> 14 | AM15: =IF(K15=0, "Actif", IF(OR(X15="Another position", X15="more money", X15="unhappy", X15="career change", X15="return to school", X15="relocation out of area", X15="medical issues", X15="military", X15="retiring"), "Volontaire", "Involontaire")) -> Actif | AN15: =IF(AK15<30, "Moins de 30", IF(AK15<45, "30-44 ans", IF(AK15<60, "45-59 ans", "60 ans et plus"))) -> 30-44 ans | AO15: =IF(H15=1, "PIP", IF(H15=2, "Needs Improvement", IF(H15=3, "Fully Meets", IF(H15=4, "Exceeds", "Non défini")))) -> Fully Meets | AP15: =IF(AND(AE15<3, AF15<3, AJ15>15), "CRITIQUE", IF(OR(AE15<3, AJ15>10), "SURVEILLER", "FAIBLE")) -> FAIBLE
A16: Barton Nader | B16: 10066 | C16: 0 | D16: 2 | E16: 1 | F16: 5 | G16: 5 | H16: 3 | I16: 0 | J16: 52505 | K16: 1 | L16: 19 | M16: Production Technician I | N16: MA | O16: 2747 | P16: 28321 | Q16: M | R16: Divorced | S16: US Citizen | T16: No | U16: White | V16: 41176 | W16: 42890 | X16: Another position | Y16: Voluntarily Terminated | Z16: Production | AA16: Michael Albert | AB16: 22 | AC16: On-line Web application | AD16: Fully Meets | AE16: 5.00 | AF16: 5 | AG16: 0 | AH16: 42769 | AI16: 0 | AJ16: 1 | AK16: =DATEDIF(P16, TODAY(), "Y") -> 48 | AL16: =INT((IF(K16=0, TODAY(), W16) - V16) / 365.25) -> 4 | AM16: =IF(K16=0, "Actif", IF(OR(X16="Another position", X16="more money", X16="unhappy", X16="career change", X16="return to school", X16="relocation out of area", X16="medical issues", X16="military", X16="retiring"), "Volontaire", "Involontaire")) -> Volontaire | AN16: =IF(AK16<30, "Moins de 30", IF(AK16<45, "30-44 ans", IF(AK16<60, "45-59 ans", "60 ans et plus"))) -> 45-59 ans | AO16: =IF(H16=1, "PIP", IF(H16=2, "Needs Improvement", IF(H16=3, "Fully Meets", IF(H16=4, "Exceeds", "Non défini")))) -> Fully Meets | AP16: =IF(AND(AE16<3, AF16<3, AJ16>15), "CRITIQUE", IF(OR(AE16<3, AJ16>10), "SURVEILLER", "FAIBLE")) -> FAIBLE
A17: Bates Norman | B17: 10061 | C17: 0 | D17: 0 | E17: 1 | F17: 4 | G17: 5 | H17: 3 | I17: 0 | J17: 57834 | K17: 1 | L17: 19 | M17: Production Technician I | N17: MA | O17: 2050 | P17: 29877 | Q17: M | R17: Single | S17: US Citizen | T17: No | U17: White | V17: 40595 | W17: 42833 | X17: attendance | Y17: Terminated for Cause | Z17: Production | AA17: Kelley Spirea | AB17: 18 | AC17: Google Search | AD17: Fully Meets | AE17: 5.00 | AF17: 4 | AG17: 0 | AH17: 42859 | AI17: 0 | AJ17: 20 | AK17: =DATEDIF(P17, TODAY(), "Y") -> 44 | AL17: =INT((IF(K17=0, TODAY(), W17) - V17) / 365.25) -> 6 | AM17: =IF(K17=0, "Actif", IF(OR(X17="Another position", X17="more money", X17="unhappy", X17="career change", X17="return to school", X17="relocation out of area", X17="medical issues", X17="military", X17="retiring"), "Volontaire", "Involontaire")) -> Involontaire | AN17: =IF(AK17<30, "Moins de 30", IF(AK17<45, "30-44 ans", IF(AK17<60, "45-59 ans", "60 ans et plus"))) -> 30-44 ans | AO17: =IF(H17=1, "PIP", IF(H17=2, "Needs Improvement", IF(H17=3, "Fully Meets", IF(H17=4, "Exceeds", "Non défini")))) -> Fully Meets | AP17: =IF(AND(AE17<3, AF17<3, AJ17>15), "CRITIQUE", IF(OR(AE17<3, AJ17>10), "SURVEILLER", "FAIBLE")) -> SURVEILLER
A18: Beak Kimberly | B18: 10023 | C18: 1 | D18: 1 | E18: 0 | F18: 2 | G18: 5 | H18: 4 | I18: 0 | J18: 70131 | K18: 0 | L18: 20 | M18: Production Technician II | N18: MA | O18: 2145 | P18: 24214 | Q18: F | R18: Married | S18: US Citizen | T18: No | U18: White | V18: 42572 | X18: N/A-StillEmployed | Y18: Active | Z18: Production | AA18: Kelley Spirea | AB18: 18 | AC18: Employee Referral | AD18: Exceeds | AE18: 4.40 | AF18: 3 | AG18: 0 | AH18: 1/14/2019 | AI18: 0 | AJ18: 16 | AK18: =DATEDIF(P18, TODAY(), "Y") -> 59 | AL18: =INT((IF(K18=0, TODAY(), W18) - V18) / 365.25) -> 9 | AM18: =IF(K18=0, "Actif", IF(OR(X18="Another position", X18="more money", X18="unhappy", X18="career change", X18="return to school", X18="relocation out of area", X18="medical issues", X18="military", X18="retiring"), "Volontaire", "Involontaire")) -> Actif | AN18: =IF(AK18<30, "Moins de 30", IF(AK18<45, "30-44 ans", IF(AK18<60, "45-59 ans", "60 ans et plus"))) -> 45-59 ans | AO18: =IF(H18=1, "PIP", IF(H18=2, "Needs Improvement", IF(H18=3, "Fully Meets", IF(H18=4, "Exceeds", "Non défini")))) -> Exceeds | AP18: =IF(AND(AE18<3, AF18<3, AJ18>15), "CRITIQUE", IF(OR(AE18<3, AJ18>10), "SURVEILLER", "FAIBLE")) -> SURVEILLER
A19: Beatrice Courtney | B19: 10055 | C19: 0 | D19: 0 | E19: 0 | F19: 1 | G19: 5 | H19: 3 | I19: 0 | J19: 59026 | K19: 0 | L19: 19 | M19: Production Technician I | N19: MA | O19: 1915 | P19: 25868 | Q19: F | R19: Single | S19: Eligible NonCitizen | T19: No | U19: White | V19: 40637 | X19: N/A-StillEmployed | Y19: Active | Z19: Production | AA19: Elijiah Gray | AB19: 16 | AC19: Google Search | AD19: Fully Meets | AE19: 5.00 | AF19: 5 | AG19: 0 | AH19: 1/14/2019 | AI19: 0 | AJ19: 12 | AK19: =DATEDIF(P19, TODAY(), "Y") -> 55 | AL19: =INT((IF(K19=0, TODAY(), W19) - V19) / 365.25) -> 15 | AM19: =IF(K19=0, "Actif", IF(OR(X19="Another position", X19="more money", X19="unhappy", X19="career change", X19="return to school", X19="relocation out of area", X19="medical issues", X19="military", X19="retiring"), "Volontaire", "Involontaire")) -> Actif | AN19: =IF(AK19<30, "Moins de 30", IF(AK19<45, "30-44 ans", IF(AK19<60, "45-59 ans", "60 ans et plus"))) -> 45-59 ans | AO19: =IF(H19=1, "PIP", IF(H19=2, "Needs Improvement", IF(H19=3, "Fully Meets", IF(H19=4, "Exceeds", "Non défini")))) -> Fully Meets | AP19: =IF(AND(AE19<3, AF19<3, AJ19>15), "CRITIQUE", IF(OR(AE19<3, AJ19>10), "SURVEILLER", "FAIBLE")) -> SURVEILLER
A20: Becker Renee | B20: 10245 | C20: 0 | D20: 0 | E20: 0 | F20: 4 | G20: 3 | H20: 3 | I20: 0 | J20: 110000 | K20: 1 | L20: 8 | M20: Database Administrator | N20: MA | O20: 2026 | P20: 31506 | Q20: F | R20: Single | S20: US Citizen | T20: Yes | U20: White | V20: 41827 | W20: 42347 | X20: performance | Y20: Terminated for Cause | Z20: IT/IS | AA20: Simon Roup | AB20: 4 | AC20: Google Search | AD20: Fully Meets | AE20: 4.50 | AF20: 4 | AG20: 5 | AH20: 1/15/2015 | AI20: 0 | AJ20: 8 | AK20: =DATEDIF(P20, TODAY(), "Y") -> 40 | AL20: =INT((IF(K20=0, TODAY(), W20) - V20) / 365.25) -> 1 | AM20: =IF(K20=0, "Actif", IF(OR(X20="Another position", X20="more money", X20="unhappy", X20="career change", X20="return to school", X20="relocation out of area", X20="medical issues", X20="military", X20="retiring"), "Volontaire", "Involontaire")) -> Involontaire | AN20: =IF(AK20<30, "Moins de 30", IF(AK20<45, "30-44 ans", IF(AK20<60, "45-59 ans", "60 ans et plus"))) -> 30-44 ans | AO20: =IF(H20=1, "PIP", IF(H20=2, "Needs Improvement", IF(H20=3, "Fully Meets", IF(H20=4, "Exceeds", "Non défini")))) -> Fully Meets | AP20: =IF(AND(AE20<3, AF20<3, AJ20>15), "CRITIQUE", IF(OR(AE20<3, AJ20>10), "SURVEILLER", "FAIBLE")) -> FAIBLE
A21: Becker Scott | B21: 10277 | C21: 0 | D21: 0 | E21: 1 | F21: 3 | G21: 5 | H21: 3 | I21: 0 | J21: 53250 | K21: 0 | L21: 19 | M21: Production Technician I | N21: MA | O21: 2452 | P21: 29010 | Q21: M | R21: Single | S21: US Citizen | T21: No | U21: Asian | V21: 41493 | X21: N/A-StillEmployed | Y21: Active | Z21: Production | AA21: Webster Butler | AC21: LinkedIn | AD21: Fully Meets | AE21: 4.20 | AF21: 4 | AG21: 0 | AH21: 43770 | AI21: 0 | AJ21: 13 | AK21: =DATEDIF(P21, TODAY(), "Y") -> 46 | AL21: =INT((IF(K21=0, TODAY(), W21) - V21) / 365.25) -> 12 | AM21: =IF(K21=0, "Actif", IF(OR(X21="Another position", X21="more money", X21="unhappy", X21="career change", X21="return to school", X21="relocation out of area", X21="medical issues", X21="military", X21="retiring"), "Volontaire", "Involontaire")) -> Actif | AN21: =IF(AK21<30, "Moins de 30", IF(AK21<45, "30-44 ans", IF(AK21<60, "45-59 ans", "60 ans et plus"))) -> 45-59 ans | AO21: =IF(H21=1, "PIP", IF(H21=2, "Needs Improvement", IF(H21=3, "Fully Meets", IF(H21=4, "Exceeds", "Non défini")))) -> Fully Meets | AP21: =IF(AND(AE21<3, AF21<3, AJ21>15), "CRITIQUE", IF(OR(AE21<3, AJ21>10), "SURVEILLER", "FAIBLE")) -> SURVEILLER
A22: Bernstein Sean | B22: 10046 | C22: 0 | D22: 0 | E22: 1 | F22: 1 | G22: 5 | H22: 3 | I22: 0 | J22: 51044 | K22: 0 | L22: 19 | M22: Production Technician I | N22: MA | O22: 2072 | P22: 25924 | Q22: M | R22: Single | S22: US Citizen | T22: Yes | U22: White | V22: 40943 | X22: N/A-StillEmployed | Y22: Active | Z22: Production | AA22: Amy Dunn | AB22: 11 | AC22: Google Search | AD22: Fully Meets | AE22: 5.00 | AF22: 3 | AG22: 0 | AH22: 1/14/2019 | AI22: 0 | AJ22: 13 | AK22: =DATEDIF(P22, TODAY(), "Y") -> 55 | AL22: =INT((IF(K22=0, TODAY(), W22) - V22) / 365.25) -> 14 | AM22: =IF(K22=0, "Actif", IF(OR(X22="Another position", X22="more money", X22="unhappy", X22="career change", X22="return to school", X22="relocation out of area", X22="medical issues", X22="military", X22="retiring"), "Volontaire", "Involontaire")) -> Actif | AN22: =IF(AK22<30, "Moins de 30", IF(AK22<45, "30-44 ans", IF(AK22<60, "45-59 ans", "60 ans et plus"))) -> 45-59 ans | AO22: =IF(H22=1, "PIP", IF(H22=2, "Needs Improvement", IF(H22=3, "Fully Meets", IF(H22=4, "Exceeds", "Non défini")))) -> Fully Meets | AP22: =IF(AND(AE22<3, AF22<3, AJ22>15), "CRITIQUE", IF(OR(AE22<3, AJ22>10), "SURVEILLER", "FAIBLE")) -> SURVEILLER
A23: Biden Lowan M | B23: 10226 | C23: 0 | D23: 2 | E23: 0 | F23: 1 | G23: 5 | H23: 3 | I23: 0 | J23: 64919 | K23: 0 | L23: 19 | M23: Production Technician I | N23: MA | O23: 2027 | P23: 21546 | Q23: F | R23: Divorced | S23: US Citizen | T23: No | U23: Asian | V23: 41505 | X23: N/A-StillEmployed | Y23: Active | Z23: Production | AA23: Ketsia Liebig | AB23: 19 | AC23: Indeed | AD23: Fully Meets | AE23: 4.20 | AF23: 3 | AG23: 0 | AH23: 43739 | AI23: 0 | AJ23: 2 | AK23: =DATEDIF(P23, TODAY(), "Y") -> 67 | AL23: =INT((IF(K23=0, TODAY(), W23) - V23) / 365.25) -> 12 | AM23: =IF(K23=0, "Actif", IF(OR(X23="Another position", X23="more money", X23="unhappy", X23="career change", X23="return to school", X23="relocation out of area", X23="medical issues", X23="military", X23="retiring"), "Volontaire", "Involontaire")) -> Actif | AN23: =IF(AK23<30, "Moins de 30", IF(AK23<45, "30-44 ans", IF(AK23<60, "45-59 ans", "60 ans et plus"))) -> 60 ans et plus | AO23: =IF(H23=1, "PIP", IF(H23=2, "Needs Improvement", IF(H23=3, "Fully Meets", IF(H23=4, "Exceeds", "Non défini")))) -> Fully Meets | AP23: =IF(AND(AE23<3, AF23<3, AJ23>15), "CRITIQUE", IF(OR(AE23<3, AJ23>10), "SURVEILLER", "FAIBLE")) -> FAIBLE
A24: Billis Helen | B24: 10003 | C24: 1 | D24: 1 | E24: 0 | F24: 1 | G24: 5 | H24: 4 | I24: 0 | J24: 62910 | K24: 0 | L24: 19 | M24: Production Technician I | N24: MA | O24: 2031 | P24: 32517 | Q24: F | R24: Married | S24: US Citizen | T24: No | U24: White | V24: 41827 | X24: N/A-StillEmployed | Y24: Active | Z24: Production | AA24: Brannon Miller | AB24: 12 | AC24: Indeed | AD24: Exceeds | AE24: 5.00 | AF24: 3 | AG24: 0 | AH24: 2/27/2019 | AI24: 0 | AJ24: 19 | AK24: =DATEDIF(P24, TODAY(), "Y") -> 37 | AL24: =INT((IF(K24=0, TODAY(), W24) - V24) / 365.25) -> 11 | AM24: =IF(K24=0, "Actif", IF(OR(X24="Another position", X24="more money", X24="unhappy", X24="career change", X24="return to school", X24="relocation out of area", X24="medical issues", X24="military", X24="retiring"), "Volontaire", "Involontaire")) -> Actif | AN24: =IF(AK24<30, "Moins de 30", IF(AK24<45, "30-44 ans", IF(AK24<60, "45-59 ans", "60 ans et plus"))) -> 30-44 ans | AO24: =IF(H24=1, "PIP", IF(H24=2, "Needs Improvement", IF(H24=3, "Fully Meets", IF(H24=4, "Exceeds", "Non défini")))) -> Exceeds | AP24: =IF(AND(AE24<3, AF24<3, AJ24>15), "CRITIQUE", IF(OR(AE24<3, AJ24>10), "SURVEILLER", "FAIBLE")) -> SURVEILLER
A25: Blount Dianna | B25: 10294 | C25: 0 | D25: 0 | E25: 0 | F25: 1 | G25: 5 | H25: 2 | I25: 0 | J25: 66441 | K25: 0 | L25: 20 | M25: Production Technician II | N25: MA | O25: 2171 | P25: 33137 | Q25: F | R25: Single | S25: US Citizen | T25: No | U25: White | V25: 40637 | X25: N/A-StillEmployed | Y25: Active | Z25: Production | AA25: Michael Albert | AB25: 22 | AC25: CareerBuilder | AD25: Needs Improvement | AE25: 2.00 | AF25: 3 | AG25: 0 | AH25: 2/27/2019 | AI25: 2 | AJ25: 3 | AK25: =DATEDIF(P25, TODAY(), "Y") -> 35 | AL25: =INT((IF(K25=0, TODAY(), W25) - V25) / 365.25) -> 15 | AM25: =IF(K25=0, "Actif", IF(OR(X25="Another position", X25="more money", X25="unhappy", X25="career change", X25="return to school", X25="relocation out of area", X25="medical issues", X25="military", X25="retiring"), "Volontaire", "Involontaire")) -> Actif | AN25: =IF(AK25<30, "Moins de 30", IF(AK25<45, "30-44 ans", IF(AK25<60, "45-59 ans", "60 ans et plus"))) -> 30-44 ans | AO25: =IF(H25=1, "PIP", IF(H25=2, "Needs Improvement", IF(H25=3, "Fully Meets", IF(H25=4, "Exceeds", "Non défini")))) -> Needs Improvement | AP25: =IF(AND(AE25<3, AF25<3, AJ25>15), "CRITIQUE", IF(OR(AE25<3, AJ25>10), "SURVEILLER", "FAIBLE")) -> FAIBLE
A26: Bondwell Betsy | B26: 10267 | C26: 0 | D26: 0 | E26: 0 | F26: 5 | G26: 5 | H26: 3 | I26: 0 | J26: 57815 | K26: 1 | L26: 20 | M26: Production Technician II | N26: MA | O26: 2210 | P26: 24488 | Q26: F | R26: Single | S26: US Citizen | T26: No | U26: White | V26: 40817 | W26: 41733 | X26: career change | Y26: Voluntarily Terminated | Z26: Production | AA26: Elijiah Gray | AB26: 16 | AC26: Google Search | AD26: Fully Meets | AE26: 4.80 | AF26: 5 | AG26: 0 | AH26: 41732 | AI26: 0 | AJ26: 5 | AK26: =DATEDIF(P26, TODAY(), "Y") -> 59 | AL26: =INT((IF(K26=0, TODAY(), W26) - V26) / 365.25) -> 2 | AM26: =IF(K26=0, "Actif", IF(OR(X26="Another position", X26="more money", X26="unhappy", X26="career change", X26="return to school", X26="relocation out of area", X26="medical issues", X26="military", X26="retiring"), "Volontaire", "Involontaire")) -> Volontaire | AN26: =IF(AK26<30, "Moins de 30", IF(AK26<45, "30-44 ans", IF(AK26<60, "45-59 ans", "60 ans et plus"))) -> 45-59 ans | AO26: =IF(H26=1, "PIP", IF(H26=2, "Needs Improvement", IF(H26=3, "Fully Meets", IF(H26=4, "Exceeds", "Non défini")))) -> Fully Meets | AP26: =IF(AND(AE26<3, AF26<3, AJ26>15), "CRITIQUE", IF(OR(AE26<3, AJ26>10), "SURVEILLER", "FAIBLE")) -> FAIBLE
A27: Booth Frank | B27: 10199 | C27: 0 | D27: 0 | E27: 1 | F27: 4 | G27: 3 | H27: 3 | I27: 0 | J27: 103613 | K27: 1 | L27: 30 | M27: Enterprise Architect | N27: CT | O27: 6033 | P27: 23588 | Q27: M | R27: Single | S27: US Citizen | T27: No | U27: Black or African American | V27: 41687 | W27: 42419 | X27: Learned that he is a gangster | Y27: Terminated for Cause | Z27: IT/IS | AA27: Simon Roup | AB27: 4 | AC27: LinkedIn | AD27: Fully Meets | AE27: 3.50 | AF27: 5 | AG27: 7 | AH27: 42644 | AI27: 0 | AJ27: 2 | AK27: =DATEDIF(P27, TODAY(), "Y") -> 61 | AL27: =INT((IF(K27=0, TODAY(), W27) - V27) / 365.25) -> 2 | AM27: =IF(K27=0, "Actif", IF(OR(X27="Another position", X27="more money", X27="unhappy", X27="career change", X27="return to school", X27="relocation out of area", X27="medical issues", X27="military", X27="retiring"), "Volontaire", "Involontaire")) -> Involontaire | AN27: =IF(AK27<30, "Moins de 30", IF(AK27<45, "30-44 ans", IF(AK27<60, "45-59 ans", "60 ans et plus"))) -> 60 ans et plus | AO27: =IF(H27=1, "PIP", IF(H27=2, "Needs Improvement", IF(H27=3, "Fully Meets", IF(H27=4, "Exceeds", "Non défini")))) -> Fully Meets | AP27: =IF(AND(AE27<3, AF27<3, AJ27>15), "CRITIQUE", IF(OR(AE27<3, AJ27>10), "SURVEILLER", "FAIBLE")) -> FAIBLE
A28: Boutwell Bonalyn | B28: 10081 | C28: 1 | D28: 1 | E28: 0 | F28: 1 | G28: 1 | H28: 3 | I28: 1 | J28: 106367 | K28: 0 | L28: 26 | M28: Sr. Accountant | N28: MA | O28: 2468 | P28: 31871 | Q28: F | R28: Married | S28: US Citizen | T28: No | U28: Black or African American | V28: 42051 | X28: N/A-StillEmployed | Y28: Active | Z28: Admin Offices | AA28: Brandon R. LeBlanc | AB28: 3 | AC28: Diversity Job Fair | AD28: Fully Meets | AE28: 5.00 | AF28: 4 | AG28: 3 | AH28: 2/18/2019 | AI28: 0 | AJ28: 4 | AK28: =DATEDIF(P28, TODAY(), "Y") -> 39 | AL28: =INT((IF(K28=0, TODAY(), W28) - V28) / 365.25) -> 11 | AM28: =IF(K28=0, "Actif", IF(OR(X28="Another position", X28="more money", X28="unhappy", X28="career change", X28="return to school", X28="relocation out of area", X28="medical issues", X28="military", X28="retiring"), "Volontaire", "Involontaire")) -> Actif | AN28: =IF(AK28<30, "Moins de 30", IF(AK28<45, "30-44 ans", IF(AK28<60, "45-59 ans", "60 ans et plus"))) -> 30-44 ans | AO28: =IF(H28=1, "PIP", IF(H28=2, "Needs Improvement", IF(H28=3, "Fully Meets", IF(H28=4, "Exceeds", "Non défini")))) -> Fully Meets | AP28: =IF(AND(AE28<3, AF28<3, AJ28>15), "CRITIQUE", IF(OR(AE28<3, AJ28>10), "SURVEILLER", "FAIBLE")) -> FAIBLE
A29: Bozzi Charles | B29: 10175 | C29: 0 | D29: 0 | E29: 1 | F29: 5 | G29: 5 | H29: 3 | I29: 0 | J29: 74312 | K29: 1 | L29: 18 | M29: Production Manager | N29: MA | O29: 1901 | P29: 25844 | Q29: M | R29: Single | S29: US Citizen | T29: No | U29: Asian | V29: 41547 | W29: 41828 | X29: retiring | Y29: Voluntarily Terminated | Z29: Production | AA29: Janet King | AB29: 2 | AC29: Indeed | AD29: Fully Meets | AE29: 3.39 | AF29: 3 | AG29: 0 | AH29: 2/20/2014 | AI29: 0 | AJ29: 14 | AK29: =DATEDIF(P29, TODAY(), "Y") -> 55 | AL29: =INT((IF(K29=0, TODAY(), W29) - V29) / 365.25) -> 0 | AM29: =IF(K29=0, "Actif", IF(OR(X29="Another position", X29="more money", X29="unhappy", X29="career change", X29="return to school", X29="relocation out of area", X29="medical issues", X29="military", X29="retiring"), "Volontaire", "Involontaire")) -> Volontaire | AN29: =IF(AK29<30, "Moins de 30", IF(AK29<45, "30-44 ans", IF(AK29<60, "45-59 ans", "60 ans et plus"))) -> 45-59 ans | AO29: =IF(H29=1, "PIP", IF(H29=2, "Needs Improvement", IF(H29=3, "Fully Meets", IF(H29=4, "Exceeds", "Non défini")))) -> Fully Meets | AP29: =IF(AND(AE29<3, AF29<3, AJ29>15), "CRITIQUE", IF(OR(AE29<3, AJ29>10), "SURVEILLER", "FAIBLE")) -> SURVEILLER
A30: Brill Donna | B30: 10177 | C30: 1 | D30: 1 | E30: 0 | F30: 5 | G30: 5 | H30: 3 | I30: 0 | J30: 53492 | K30: 1 | L30: 19 | M30: Production Technician I | N30: MA | O30: 1701 | P30: 33109 | Q30: F | R30: Married | S30: US Citizen | T30: No | U30: White | V30: 40943 | W30: 41440 | X30: Another position | Y30: Voluntarily Terminated | Z30: Production | AA30: David Stanley | AB30: 14 | AC30: Google Search | AD30: Fully Meets | AE30: 3.35 | AF30: 4 | AG30: 0 | AH30: 41367 | AI30: 0 | AJ30: 6 | AK30: =DATEDIF(P30, TODAY(), "Y") -> 35 | AL30: =INT((IF(K30=0, TODAY(), W30) - V30) / 365.25) -> 1 | AM30: =IF(K30=0, "Actif", IF(OR(X30="Another position", X30="more money", X30="unhappy", X30="career change", X30="return to school", X30="relocation out of area", X30="medical issues", X30="military", X30="retiring"), "Volontaire", "Involontaire")) -> Volontaire | AN30: =IF(AK30<30, "Moins de 30", IF(AK30<45, "30-44 ans", IF(AK30<60, "45-59 ans", "60 ans et plus"))) -> 30-44 ans | AO30: =IF(H30=1, "PIP", IF(H30=2, "Needs Improvement", IF(H30=3, "Fully Meets", IF(H30=4, "Exceeds", "Non défini")))) -> Fully Meets | AP30: =IF(AND(AE30<3, AF30<3, AJ30>15), "CRITIQUE", IF(OR(AE30<3, AJ30>10), "SURVEILLER", "FAIBLE")) -> FAIBLE
A31: Brown Mia | B31: 10238 | C31: 1 | D31: 1 | E31: 0 | F31: 1 | G31: 1 | H31: 3 | I31: 1 | J31: 63000 | K31: 0 | L31: 1 | M31: Accountant I | N31: MA | O31: 1450 | P31: 32105 | Q31: F | R31: Married | S31: US Citizen | T31: No | U31: Black or African American | V31: 39748 | X31: N/A-StillEmployed | Y31: Active | Z31: Admin Offices | AA31: Brandon R. LeBlanc | AB31: 1 | AC31: Diversity Job Fair | AD31: Fully Meets | AE31: 4.50 | AF31: 2 | AG31: 6 | AH31: 1/15/2019 | AI31: 0 | AJ31: 14 | AK31: =DATEDIF(P31, TODAY(), "Y") -> 38 | AL31: =INT((IF(K31=0, TODAY(), W31) - V31) / 365.25) -> 17 | AM31: =IF(K31=0, "Actif", IF(OR(X31="Another position", X31="more money", X31="unhappy", X31="career change", X31="return to school", X31="relocation out of area", X31="medical issues", X31="military", X31="retiring"), "Volontaire", "Involontaire")) -> Actif | AN31: =IF(AK31<30, "Moins de 30", IF(AK31<45, "30-44 ans", IF(AK31<60, "45-59 ans", "60 ans et plus"))) -> 30-44 ans | AO31: =IF(H31=1, "PIP", IF(H31=2, "Needs Improvement", IF(H31=3, "Fully Meets", IF(H31=4, "Exceeds", "Non défini")))) -> Fully Meets | AP31: =IF(AND(AE31<3, AF31<3, AJ31>15), "CRITIQUE", IF(OR(AE31<3, AJ31>10), "SURVEILLER", "FAIBLE")) -> SURVEILLER
A32: Buccheri Joseph | B32: 10184 | C32: 0 | D32: 0 | E32: 1 | F32: 1 | G32: 5 | H32: 3 | I32: 0 | J32: 65288 | K32: 0 | L32: 20 | M32: Production Technician II | N32: MA | O32: 1013 | P32: 30525 | Q32: M | R32: Single | S32: US Citizen | T32: No | U32: White | V32: 41911 | X32: N/A-StillEmployed | Y32: Active | Z32: Production | AA32: Webster Butler | AC32: Google Search | AD32: Fully Meets | AE32: 3.19 | AF32: 3 | AG32: 0 | AH32: 43467 | AI32: 0 | AJ32: 9 | AK32: =DATEDIF(P32, TODAY(), "Y") -> 42 | AL32: =INT((IF(K32=0, TODAY(), W32) - V32) / 365.25) -> 11 | AM32: =IF(K32=0, "Actif", IF(OR(X32="Another position", X32="more money", X32="unhappy", X32="career change", X32="return to school", X32="relocation out of area", X32="medical issues", X32="military", X32="retiring"), "Volontaire", "Involontaire")) -> Actif | AN32: =IF(AK32<30, "Moins de 30", IF(AK32<45, "30-44 ans", IF(AK32<60, "45-59 ans", "60 ans et plus"))) -> 30-44 ans | AO32: =IF(H32=1, "PIP", IF(H32=2, "Needs Improvement", IF(H32=3, "Fully Meets", IF(H32=4, "Exceeds", "Non défini")))) -> Fully Meets | AP32: =IF(AND(AE32<3, AF32<3, AJ32>15), "CRITIQUE", IF(OR(AE32<3, AJ32>10), "SURVEILLER", "FAIBLE")) -> FAIBLE
A33: Bugali Josephine | B33: 10203 | C33: 0 | D33: 3 | E33: 0 | F33: 3 | G33: 5 | H33: 3 | I33: 1 | J33: 64375 | K33: 0 | L33: 19 | M33: Production Technician I | N33: MA | O33: 2043 | P33: 25506 | Q33: F | R33: Separated | S33: US Citizen | T33: No | U33: Black or African American | V33: 41589 | X33: N/A-StillEmployed | Y33: Active | Z33: Production | AA33: Kissy Sullivan | AB33: 20 | AC33: Diversity Job Fair | AD33: Fully Meets | AE33: 3.50 | AF33: 5 | AG33: 0 | AH33: 1/21/2019 | AI33: 0 | AJ33: 17 | AK33: =DATEDIF(P33, TODAY(), "Y") -> 56 | AL33: =INT((IF(K33=0, TODAY(), W33) - V33) / 365.25) -> 12 | AM33: =IF(K33=0, "Actif", IF(OR(X33="Another position", X33="more money", X33="unhappy", X33="career change", X33="return to school", X33="relocation out of area", X33="medical issues", X33="military", X33="retiring"), "Volontaire", "Involontaire")) -> Actif | AN33: =IF(AK33<30, "Moins de 30", IF(AK33<45, "30-44 ans", IF(AK33<60, "45-59 ans", "60 ans et plus"))) -> 45-59 ans | AO33: =IF(H33=1, "PIP", IF(H33=2, "Needs Improvement", IF(H33=3, "Fully Meets", IF(H33=4, "Exceeds", "Non défini")))) -> Fully Meets | AP33: =IF(AND(AE33<3, AF33<3, AJ33>15), "CRITIQUE", IF(OR(AE33<3, AJ33>10), "SURVEILLER", "FAIBLE")) -> SURVEILLER
A34: Bunbury Jessica | B34: 10188 | C34: 1 | D34: 1 | E34: 0 | F34: 5 | G34: 6 | H34: 3 | I34: 0 | J34: 74326 | K34: 1 | L34: 3 | M34: Area Sales Manager | N34: VA | O34: 21851 | P34: 23382 | Q34: F | R34: Married | S34: Eligible NonCitizen | T34: No | U34: Black or African American | V34: 40770 | W34: 41678 | X34: Another position | Y34: Voluntarily Terminated | Z34: Sales | AA34: John Smith | AB34: 17 | AC34: Google Search | AD34: Fully Meets | AE34: 3.14 | AF34: 5 | AG34: 0 | AH34: 41549 | AI34: 1 | AJ34: 19 | AK34: =DATEDIF(P34, TODAY(), "Y") -> 62 | AL34: =INT((IF(K34=0, TODAY(), W34) - V34) / 365.25) -> 2 | AM34: =IF(K34=0, "Actif", IF(OR(X34="Another position", X34="more money", X34="unhappy", X34="career change", X34="return to school", X34="relocation out of area", X34="medical issues", X34="military", X34="retiring"), "Volontaire", "Involontaire")) -> Volontaire | AN34: =IF(AK34<30, "Moins de 30", IF(AK34<45, "30-44 ans", IF(AK34<60, "45-59 ans", "60 ans et plus"))) -> 60 ans et plus | AO34: =IF(H34=1, "PIP", IF(H34=2, "Needs Improvement", IF(H34=3, "Fully Meets", IF(H34=4, "Exceeds", "Non défini")))) -> Fully Meets | AP34: =IF(AND(AE34<3, AF34<3, AJ34>15), "CRITIQUE", IF(OR(AE34<3, AJ34>10), "SURVEILLER", "FAIBLE")) -> SURVEILLER
A35: Burke Joelle | B35: 10107 | C35: 0 | D35: 0 | E35: 0 | F35: 1 | G35: 5 | H35: 3 | I35: 0 | J35: 63763 | K35: 0 | L35: 20 | M35: Production Technician II | N35: MA | O35: 2148 | P35: 29254 | Q35: F | R35: Single | S35: US Citizen | T35: No | U35: Black or African American | V35: 41032 | X35: N/A-StillEmployed | Y35: Active | Z35: Production | AA35: Amy Dunn | AB35: 11 | AC35: Employee Referral | AD35: Fully Meets | AE35: 4.51 | AF35: 4 | AG35: 0 | AH35: 2/21/2019 | AI35: 0 | AJ35: 3 | AK35: =DATEDIF(P35, TODAY(), "Y") -> 46 | AL35: =INT((IF(K35=0, TODAY(), W35) - V35) / 365.25) -> 13 | AM35: =IF(K35=0, "Actif", IF(OR(X35="Another position", X35="more money", X35="unhappy", X35="career change", X35="return to school", X35="relocation out of area", X35="medical issues", X35="military", X35="retiring"), "Volontaire", "Involontaire")) -> Actif | AN35: =IF(AK35<30, "Moins de 30", IF(AK35<45, "30-44 ans", IF(AK35<60, "45-59 ans", "60 ans et plus"))) -> 45-59 ans | AO35: =IF(H35=1, "PIP", IF(H35=2, "Needs Improvement", IF(H35=3, "Fully Meets", IF(H35=4, "Exceeds", "Non défini")))) -> Fully Meets | AP35: =IF(AND(AE35<3, AF35<3, AJ35>15), "CRITIQUE", IF(OR(AE35<3, AJ35>10), "SURVEILLER", "FAIBLE")) -> FAIBLE
A36: Burkett Benjamin | B36: 10181 | C36: 1 | D36: 1 | E36: 1 | F36: 1 | G36: 5 | H36: 3 | I36: 0 | J36: 62162 | K36: 0 | L36: 20 | M36: Production Technician II | N36: MA | O36: 1890 | P36: 28356 | Q36: M | R36: Married | S36: US Citizen | T36: No | U36: White | V36: 40637 | X36: N/A-StillEmployed | Y36: Active | Z36: Production | AA36: Ketsia Liebig | AB36: 19 | AC36: Indeed | AD36: Fully Meets | AE36: 3.25 | AF36: 5 | AG36: 0 | AH36: 1/14/2019 | AI36: 0 | AJ36: 15 | AK36: =DATEDIF(P36, TODAY(), "Y") -> 48 | AL36: =INT((IF(K36=0, TODAY(), W36) - V36) / 365.25) -> 15 | AM36: =IF(K36=0, "Actif", IF(OR(X36="Another position", X36="more money", X36="unhappy", X36="career change", X36="return to school", X36="relocation out of area", X36="medical issues", X36="military", X36="retiring"), "Volontaire", "Involontaire")) -> Actif | AN36: =IF(AK36<30, "Moins de 30", IF(AK36<45, "30-44 ans", IF(AK36<60, "45-59 ans", "60 ans et plus"))) -> 45-59 ans | AO36: =IF(H36=1, "PIP", IF(H36=2, "Needs Improvement", IF(H36=3, "Fully Meets", IF(H36=4, "Exceeds", "Non défini")))) -> Fully Meets | AP36: =IF(AND(AE36<3, AF36<3, AJ36>15), "CRITIQUE", IF(OR(AE36<3, AJ36>10), "SURVEILLER", "FAIBLE")) -> SURVEILLER
A37: Cady Max | B37: 10150 | C37: 0 | D37: 0 | E37: 1 | F37: 1 | G37: 4 | H37: 3 | I37: 0 | J37: 77692 | K37: 0 | L37: 25 | M37: Software Engineering Manager | N37: MA | O37: 2184 | P37: 24433 | Q37: M | R37: Single | S37: US Citizen | T37: No | U37: White | V37: 40770 | X37: N/A-StillEmployed | Y37: Active | Z37: Software Engineering | AA37: Jennifer Zamora | AB37: 5 | AC37: Google Search | AD37: Fully Meets | AE37: 3.84 | AF37: 3 | AG37: 5 | AH37: 1/21/2019 | AI37: 0 | AJ37: 4 | AK37: =DATEDIF(P37, TODAY(), "Y") -> 59 | AL37: =INT((IF(K37=0, TODAY(), W37) - V37) / 365.25) -> 14 | AM37: =IF(K37=0, "Actif", IF(OR(X37="Another position", X37="more money", X37="unhappy", X37="career change", X37="return to school", X37="relocation out of area", X37="medical issues", X37="military", X37="retiring"), "Volontaire", "Involontaire")) -> Actif | AN37: =IF(AK37<30, "Moins de 30", IF(AK37<45, "30-44 ans", IF(AK37<60, "45-59 ans", "60 ans et plus"))) -> 45-59 ans | AO37: =IF(H37=1, "PIP", IF(H37=2, "Needs Improvement", IF(H37=3, "Fully Meets", IF(H37=4, "Exceeds", "Non défini")))) -> Fully Meets | AP37: =IF(AND(AE37<3, AF37<3, AJ37>15), "CRITIQUE", IF(OR(AE37<3, AJ37>10), "SURVEILLER", "FAIBLE")) -> FAIBLE
A38: Candie Calvin | B38: 10001 | C38: 0 | D38: 0 | E38: 1 | F38: 1 | G38: 5 | H38: 4 | I38: 0 | J38: 72640 | K38: 0 | L38: 18 | M38: Production Manager | N38: MA | O38: 2169 | P38: 30567 | Q38: M | R38: Single | S38: US Citizen | T38: No | U38: White | V38: 42397 | X38: N/A-StillEmployed | Y38: Active | Z38: Production | AA38: Janet King | AB38: 2 | AC38: Indeed | AD38: Exceeds | AE38: 5.00 | AF38: 3 | AG38: 0 | AH38: 2/22/2019 | AI38: 0 | AJ38: 14 | AK38: =DATEDIF(P38, TODAY(), "Y") -> 42 | AL38: =INT((IF(K38=0, TODAY(), W38) - V38) / 365.25) -> 10 | AM38: =IF(K38=0, "Actif", IF(OR(X38="Another position", X38="more money", X38="unhappy", X38="career change", X38="return to school", X38="relocation out of area", X38="medical issues", X38="military", X38="retiring"), "Volontaire", "Involontaire")) -> Actif | AN38: =IF(AK38<30, "Moins de 30", IF(AK38<45, "30-44 ans", IF(AK38<60, "45-59 ans", "60 ans et plus"))) -> 30-44 ans | AO38: =IF(H38=1, "PIP", IF(H38=2, "Needs Improvement", IF(H38=3, "Fully Meets", IF(H38=4, "Exceeds", "Non défini")))) -> Exceeds | AP38: =IF(AND(AE38<3, AF38<3, AJ38>15), "CRITIQUE", IF(OR(AE38<3, AJ38>10), "SURVEILLER", "FAIBLE")) -> SURVEILLER
A39: Carabbio Judith | B39: 10085 | C39: 0 | D39: 0 | E39: 0 | F39: 1 | G39: 4 | H39: 3 | I39: 0 | J39: 93396 | K39: 0 | L39: 24 | M39: Software Engineer | N39: MA | O39: 2132 | P39: 31901 | Q39: F | R39: Single | S39: US Citizen | T39: No | U39: White | V39: 41589 | X39: N/A-StillEmployed | Y39: Active | Z39: Software Engineering | AA39: Alex Sweetwater | AB39: 10 | AC39: Indeed | AD39: Fully Meets | AE39: 4.96 | AF39: 4 | AG39: 6 | AH39: 1/30/2019 | AI39: 0 | AJ39: 3 | AK39: =DATEDIF(P39, TODAY(), "Y") -> 38 | AL39: =INT((IF(K39=0, TODAY(), W39) - V39) / 365.25) -> 12 | AM39: =IF(K39=0, "Actif", IF(OR(X39="Another position", X39="more money", X39="unhappy", X39="career change", X39="return to school", X39="relocation out of area", X39="medical issues", X39="military", X39="retiring"), "Volontaire", "Involontaire")) -> Actif | AN39: =IF(AK39<30, "Moins de 30", IF(AK39<45, "30-44 ans", IF(AK39<60, "45-59 ans", "60 ans et plus"))) -> 30-44 ans | AO39: =IF(H39=1, "PIP", IF(H39=2, "Needs Improvement", IF(H39=3, "Fully Meets", IF(H39=4, "Exceeds", "Non défini")))) -> Fully Meets | AP39: =IF(AND(AE39<3, AF39<3, AJ39>15), "CRITIQUE", IF(OR(AE39<3, AJ39>10), "SURVEILLER", "FAIBLE")) -> FAIBLE
A40: Carey Michael | B40: 10115 | C40: 0 | D40: 0 | E40: 1 | F40: 1 | G40: 5 | H40: 3 | I40: 0 | J40: 52846 | K40: 0 | L40: 19 | M40: Production Technician I | N40: MA | O40: 1701 | P40: 30349 | Q40: M | R40: Single | S40: US Citizen | T40: No | U40: Black or African American | V40: 41729 | X40: N/A-StillEmployed | Y40: Active | Z40: Production | AA40: Kelley Spirea | AB40: 18 | AC40: LinkedIn | AD40: Fully Meets | AE40: 4.43 | AF40: 3 | AG40: 0 | AH40: 43467 | AI40: 0 | AJ40: 14 | AK40: =DATEDIF(P40, TODAY(), "Y") -> 43 | AL40: =INT((IF(K40=0, TODAY(), W40) - V40) / 365.25) -> 12 | AM40: =IF(K40=0, "Actif", IF(OR(X40="Another position", X40="more money", X40="unhappy", X40="career change", X40="return to school", X40="relocation out of area", X40="medical issues", X40="military", X40="retiring"), "Volontaire", "Involontaire")) -> Actif | AN40: =IF(AK40<30, "Moins de 30", IF(AK40<45, "30-44 ans", IF(AK40<60, "45-59 ans", "60 ans et plus"))) -> 30-44 ans | AO40: =IF(H40=1, "PIP", IF(H40=2, "Needs Improvement", IF(H40=3, "Fully Meets", IF(H40=4, "Exceeds", "Non défini")))) -> Fully Meets | AP40: =IF(AND(AE40<3, AF40<3, AJ40>15), "CRITIQUE", IF(OR(AE40<3, AJ40>10), "SURVEILLER", "FAIBLE")) -> SURVEILLER
A41: Carr Claudia N | B41: 10082 | C41: 0 | D41: 0 | E41: 0 | F41: 2 | G41: 3 | H41: 3 | I41: 0 | J41: 100031 | K41: 0 | L41: 27 | M41: Sr. DBA | N41: MA | O41: 1886 | P41: 31569 | Q41: F | R41: Single | S41: US Citizen | T41: No | U41: Black or African American | V41: 42551 | X41: N/A-StillEmployed | Y41: Active | Z41: IT/IS | AA41: Simon Roup | AB41: 4 | AC41: LinkedIn | AD41: Fully Meets | AE41: 5.00 | AF41: 5 | AG41: 6 | AH41: 2/18/2019 | AI41: 0 | AJ41: 7 | AK41: =DATEDIF(P41, TODAY(), "Y") -> 39 | AL41: =INT((IF(K41=0, TODAY(), W41) - V41) / 365.25) -> 9 | AM41: =IF(K41=0, "Actif", IF(OR(X41="Another position", X41="more money", X41="unhappy", X41="career change", X41="return to school", X41="relocation out of area", X41="medical issues", X41="military", X41="retiring"), "Volontaire", "Involontaire")) -> Actif | AN41: =IF(AK41<30, "Moins de 30", IF(AK41<45, "30-44 ans", IF(AK41<60, "45-59 ans", "60 ans et plus"))) -> 30-44 ans | AO41: =IF(H41=1, "PIP", IF(H41=2, "Needs Improvement", IF(H41=3, "Fully Meets", IF(H41=4, "Exceeds", "Non défini")))) -> Fully Meets | AP41: =IF(AND(AE41<3, AF41<3, AJ41>15), "CRITIQUE", IF(OR(AE41<3, AJ41>10), "SURVEILLER", "FAIBLE")) -> FAIBLE
A42: Carter Michelle | B42: 10040 | C42: 0 | D42: 0 | E42: 0 | F42: 1 | G42: 6 | H42: 3 | I42: 0 | J42: 71860 | K42: 0 | L42: 3 | M42: Area Sales Manager | N42: VT | O42: 5664 | P42: 23146 | Q42: F | R42: Single | S42: US Citizen | T42: No | U42: White | V42: 41869 | X42: N/A-StillEmployed | Y42: Active | Z42: Sales | AA42: John Smith | AB42: 17 | AC42: Indeed | AD42: Fully Meets | AE42: 5.00 | AF42: 5 | AG42: 0 | AH42: 1/21/2019 | AI42: 0 | AJ42: 7 | AK42: =DATEDIF(P42, TODAY(), "Y") -> 62 | AL42: =INT((IF(K42=0, TODAY(), W42) - V42) / 365.25) -> 11 | AM42: =IF(K42=0, "Actif", IF(OR(X42="Another position", X42="more money", X42="unhappy", X42="career change", X42="return to school", X42="relocation out of area", X42="medical issues", X42="military", X42="retiring"), "Volontaire", "Involontaire")) -> Actif | AN42: =IF(AK42<30, "Moins de 30", IF(AK42<45, "30-44 ans", IF(AK42<60, "45-59 ans", "60 ans et plus"))) -> 60 ans et plus | AO42: =IF(H42=1, "PIP", IF(H42=2, "Needs Improvement", IF(H42=3, "Fully Meets", IF(H42=4, "Exceeds", "Non défini")))) -> Fully Meets | AP42: =IF(AND(AE42<3, AF42<3, AJ42>15), "CRITIQUE", IF(OR(AE42<3, AJ42>10), "SURVEILLER", "FAIBLE")) -> FAIBLE
A43: Chace Beatrice | B43: 10067 | C43: 0 | D43: 0 | E43: 0 | F43: 1 | G43: 5 | H43: 3 | I43: 0 | J43: 61656 | K43: 0 | L43: 19 | M43: Production Technician I | N43: MA | O43: 2763 | P43: 18660 | Q43: F | R43: Single | S43: US Citizen | T43: No | U43: White | V43: 41911 | X43: N/A-StillEmployed | Y43: Active | Z43: Production | AA43: Michael Albert | AB43: 22 | AC43: Google Search | AD43: Fully Meets | AE43: 5.00 | AF43: 4 | AG43: 0 | AH43: 43801 | AI43: 0 | AJ43: 11 | AK43: =DATEDIF(P43, TODAY(), "Y") -> 75 | AL43: =INT((IF(K43=0, TODAY(), W43) - V43) / 365.25) -> 11 | AM43: =IF(K43=0, "Actif", IF(OR(X43="Another position", X43="more money", X43="unhappy", X43="career change", X43="return to school", X43="relocation out of area", X43="medical issues", X43="military", X43="retiring"), "Volontaire", "Involontaire")) -> Actif | AN43: =IF(AK43<30, "Moins de 30", IF(AK43<45, "30-44 ans", IF(AK43<60, "45-59 ans", "60 ans et plus"))) -> 60 ans et plus | AO43: =IF(H43=1, "PIP", IF(H43=2, "Needs Improvement", IF(H43=3, "Fully Meets", IF(H43=4, "Exceeds", "Non défini")))) -> Fully Meets | AP43: =IF(AND(AE43<3, AF43<3, AJ43>15), "CRITIQUE", IF(OR(AE43<3, AJ43>10), "SURVEILLER", "FAIBLE")) -> SURVEILLER
A44: Champaigne Brian | B44: 10108 | C44: 1 | D44: 1 | E44: 1 | F44: 1 | G44: 3 | H44: 3 | I44: 0 | J44: 110929 | K44: 0 | L44: 5 | M44: BI Director | N44: MA | O44: 2045 | P44: 26544 | Q44: M | R44: Married | S44: US Citizen | T44: No | U44: White | V44: 42530 | X44: N/A-StillEmployed | Y44: Active | Z44: IT/IS | AA44: Jennifer Zamora | AB44: 5 | AC44: Indeed | AD44: Fully Meets | AE44: 4.50 | AF44: 5 | AG44: 7 | AH44: 1/15/2019 | AI44: 0 | AJ44: 8 | AK44: =DATEDIF(P44, TODAY(), "Y") -> 53 | AL44: =INT((IF(K44=0, TODAY(), W44) - V44) / 365.25) -> 9 | AM44: =IF(K44=0, "Actif", IF(OR(X44="Another position", X44="more money", X44="unhappy", X44="career change", X44="return to school", X44="relocation out of area", X44="medical issues", X44="military", X44="retiring"), "Volontaire", "Involontaire")) -> Actif | AN44: =IF(AK44<30, "Moins de 30", IF(AK44<45, "30-44 ans", IF(AK44<60, "45-59 ans", "60 ans et plus"))) -> 45-59 ans | AO44: =IF(H44=1, "PIP", IF(H44=2, "Needs Improvement", IF(H44=3, "Fully Meets", IF(H44=4, "Exceeds", "Non défini")))) -> Fully Meets | AP44: =IF(AND(AE44<3, AF44<3, AJ44>15), "CRITIQUE", IF(OR(AE44<3, AJ44>10), "SURVEILLER", "FAIBLE")) -> FAIBLE
A45: Chan Lin | B45: 10210 | C45: 0 | D45: 0 | E45: 0 | F45: 1 | G45: 5 | H45: 3 | I45: 0 | J45: 54237 | K45: 0 | L45: 19 | M45: Production Technician I | N45: MA | O45: 2170 | P45: 29191 | Q45: F | R45: Single | S45: US Citizen | T45: No | U45: White | V45: 41978 | X45: N/A-StillEmployed | Y45: Active | Z45: Production | AA45: Elijiah Gray | AB45: 16 | AC45: Indeed | AD45: Fully Meets | AE45: 3.30 | AF45: 4 | AG45: 0 | AH45: 2/19/2019 | AI45: 0 | AJ45: 11 | AK45: =DATEDIF(P45, TODAY(), "Y") -> 46 | AL45: =INT((IF(K45=0, TODAY(), W45) - V45) / 365.25) -> 11 | AM45: =IF(K45=0, "Actif", IF(OR(X45="Another position", X45="more money", X45="unhappy", X45="career change", X45="return to school", X45="relocation out of area", X45="medical issues", X45="military", X45="retiring"), "Volontaire", "Involontaire")) -> Actif | AN45: =IF(AK45<30, "Moins de 30", IF(AK45<45, "30-44 ans", IF(AK45<60, "45-59 ans", "60 ans et plus"))) -> 45-59 ans | AO45: =IF(H45=1, "PIP", IF(H45=2, "Needs Improvement", IF(H45=3, "Fully Meets", IF(H45=4, "Exceeds", "Non défini")))) -> Fully Meets | AP45: =IF(AND(AE45<3, AF45<3, AJ45>15), "CRITIQUE", IF(OR(AE45<3, AJ45>10), "SURVEILLER", "FAIBLE")) -> SURVEILLER
A46: Chang Donovan E | B46: 10154 | C46: 0 | D46: 0 | E46: 1 | F46: 1 | G46: 5 | H46: 3 | I46: 0 | J46: 60380 | K46: 0 | L46: 19 | M46: Production Technician I | N46: MA | O46: 1845 | P46: 30552 | Q46: M | R46: Single | S46: US Citizen | T46: No | U46: White | V46: 41493 | X46: N/A-StillEmployed | Y46: Active | Z46: Production | AA46: Webster Butler | AC46: LinkedIn | AD46: Fully Meets | AE46: 3.80 | AF46: 5 | AG46: 0 | AH46: 1/14/2019 | AI46: 0 | AJ46: 4 | AK46: =DATEDIF(P46, TODAY(), "Y") -> 42 | AL46: =INT((IF(K46=0, TODAY(), W46) - V46) / 365.25) -> 12 | AM46: =IF(K46=0, "Actif", IF(OR(X46="Another position", X46="more money", X46="unhappy", X46="career change", X46="return to school", X46="relocation out of area", X46="medical issues", X46="military", X46="retiring"), "Volontaire", "Involontaire")) -> Actif | AN46: =IF(AK46<30, "Moins de 30", IF(AK46<45, "30-44 ans", IF(AK46<60, "45-59 ans", "60 ans et plus"))) -> 30-44 ans | AO46: =IF(H46=1, "PIP", IF(H46=2, "Needs Improvement", IF(H46=3, "Fully Meets", IF(H46=4, "Exceeds", "Non défini")))) -> Fully Meets | AP46: =IF(AND(AE46<3, AF46<3, AJ46>15), "CRITIQUE", IF(OR(AE46<3, AJ46>10), "SURVEILLER", "FAIBLE")) -> FAIBLE
A47: Chigurh Anton | B47: 10200 | C47: 0 | D47: 0 | E47: 1 | F47: 1 | G47: 6 | H47: 3 | I47: 0 | J47: 66808 | K47: 0 | L47: 3 | M47: Area Sales Manager | N47: TX | O47: 78207 | P47: 25878 | Q47: M | R47: Single | S47: Eligible NonCitizen | T47: No | U47: Black or African American | V47: 41043 | X47: N/A-StillEmployed | Y47: Active | Z47: Sales | AA47: Lynn Daneault | AB47: 21 | AC47: Employee Referral | AD47: Fully Meets | AE47: 3.00 | AF47: 5 | AG47: 0 | AH47: 1/19/2019 | AI47: 0 | AJ47: 17 | AK47: =DATEDIF(P47, TODAY(), "Y") -> 55 | AL47: =INT((IF(K47=0, TODAY(), W47) - V47) / 365.25) -> 13 | AM47: =IF(K47=0, "Actif", IF(OR(X47="Another position", X47="more money", X47="unhappy", X47="career change", X47="return to school", X47="relocation out of area", X47="medical issues", X47="military", X47="retiring"), "Volontaire", "Involontaire")) -> Actif | AN47: =IF(AK47<30, "Moins de 30", IF(AK47<45, "30-44 ans", IF(AK47<60, "45-59 ans", "60 ans et plus"))) -> 45-59 ans | AO47: =IF(H47=1, "PIP", IF(H47=2, "Needs Improvement", IF(H47=3, "Fully Meets", IF(H47=4, "Exceeds", "Non défini")))) -> Fully Meets | AP47: =IF(AND(AE47<3, AF47<3, AJ47>15), "CRITIQUE", IF(OR(AE47<3, AJ47>10), "SURVEILLER", "FAIBLE")) -> SURVEILLER
A48: Chivukula Enola | B48: 10240 | C48: 0 | D48: 0 | E48: 0 | F48: 5 | G48: 5 | H48: 3 | I48: 0 | J48: 64786 | K48: 1 | L48: 19 | M48: Production Technician I | N48: MA | O48: 1775 | P48: 30555 | Q48: F | R48: Single | S48: US Citizen | T48: No | U48: White | V48: 40721 | W48: 42323 | X48: relocation out of area | Y48: Voluntarily Terminated | Z48: Production | AA48: Amy Dunn | AB48: 11 | AC48: Indeed | AD48: Fully Meets | AE48: 4.30 | AF48: 4 | AG48: 0 | AH48: 42280 | AI48: 0 | AJ48: 3 | AK48: =DATEDIF(P48, TODAY(), "Y") -> 42 | AL48: =INT((IF(K48=0, TODAY(), W48) - V48) / 365.25) -> 4 | AM48: =IF(K48=0, "Actif", IF(OR(X48="Another position", X48="more money", X48="unhappy", X48="career change", X48="return to school", X48="relocation out of area", X48="medical issues", X48="military", X48="retiring"), "Volontaire", "Involontaire")) -> Volontaire | AN48: =IF(AK48<30, "Moins de 30", IF(AK48<45, "30-44 ans", IF(AK48<60, "45-59 ans", "60 ans et plus"))) -> 30-44 ans | AO48: =IF(H48=1, "PIP", IF(H48=2, "Needs Improvement", IF(H48=3, "Fully Meets", IF(H48=4, "Exceeds", "Non défini")))) -> Fully Meets | AP48: =IF(AND(AE48<3, AF48<3, AJ48>15), "CRITIQUE", IF(OR(AE48<3, AJ48>10), "SURVEILLER", "FAIBLE")) -> FAIBLE
A49: Cierpiszewski Caroline | B49: 10168 | C49: 0 | D49: 0 | E49: 0 | F49: 1 | G49: 5 | H49: 3 | I49: 0 | J49: 64816 | K49: 0 | L49: 19 | M49: Production Technician I | N49: MA | O49: 2044 | P49: 32294 | Q49: F | R49: Single | S49: Non-Citizen | T49: No | U49: Black or African American | V49: 40612 | X49: N/A-StillEmployed | Y49: Active | Z49: Production | AA49: Ketsia Liebig | AB49: 19 | AC49: Indeed | AD49: Fully Meets | AE49: 3.58 | AF49: 5 | AG49: 0 | AH49: 1/30/2019 | AI49: 0 | AJ49: 3 | AK49: =DATEDIF(P49, TODAY(), "Y") -> 37 | AL49: =INT((IF(K49=0, TODAY(), W49) - V49) / 365.25) -> 15 | AM49: =IF(K49=0, "Actif", IF(OR(X49="Another position", X49="more money", X49="unhappy", X49="career change", X49="return to school", X49="relocation out of area", X49="medical issues", X49="military", X49="retiring"), "Volontaire", "Involontaire")) -> Actif | AN49: =IF(AK49<30, "Moins de 30", IF(AK49<45, "30-44 ans", IF(AK49<60, "45-59 ans", "60 ans et plus"))) -> 30-44 ans | AO49: =IF(H49=1, "PIP", IF(H49=2, "Needs Improvement", IF(H49=3, "Fully Meets", IF(H49=4, "Exceeds", "Non défini")))) -> Fully Meets | AP49: =IF(AND(AE49<3, AF49<3, AJ49>15), "CRITIQUE", IF(OR(AE49<3, AJ49>10), "SURVEILLER", "FAIBLE")) -> FAIBLE
A50: Clayton Rick | B50: 10220 | C50: 0 | D50: 0 | E50: 1 | F50: 1 | G50: 3 | H50: 3 | I50: 0 | J50: 68678 | K50: 0 | L50: 14 | M50: IT Support | N50: MA | O50: 2170 | P50: 31176 | Q50: M | R50: Single | S50: US Citizen | T50: No | U50: White | V50: 41038 | X50: N/A-StillEmployed | Y50: Active | Z50: IT/IS | AA50: Eric Dougall | AB50: 6 | AC50: Indeed | AD50: Fully Meets | AE50: 4.70 | AF50: 3 | AG50: 6 | AH50: 2/27/2019 | AI50: 0 | AJ50: 2 | AK50: =DATEDIF(P50, TODAY(), "Y") -> 40 | AL50: =INT((IF(K50=0, TODAY(), W50) - V50) / 365.25) -> 13 | AM50: =IF(K50=0, "Actif", IF(OR(X50="Another position", X50="more money", X50="unhappy", X50="career change", X50="return to school", X50="relocation out of area", X50="medical issues", X50="military", X50="retiring"), "Volontaire", "Involontaire")) -> Actif | AN50: =IF(AK50<30, "Moins de 30", IF(AK50<45, "30-44 ans", IF(AK50<60, "45-59 ans", "60 ans et plus"))) -> 30-44 ans | AO50: =IF(H50=1, "PIP", IF(H50=2, "Needs Improvement", IF(H50=3, "Fully Meets", IF(H50=4, "Exceeds", "Non défini")))) -> Fully Meets | AP50: =IF(AND(AE50<3, AF50<3, AJ50>15), "CRITIQUE", IF(OR(AE50<3, AJ50>10), "SURVEILLER", "FAIBLE")) -> FAIBLE
A51: Cloninger Jennifer | B51: 10275 | C51: 1 | D51: 1 | E51: 0 | F51: 5 | G51: 5 | H51: 3 | I51: 0 | J51: 64066 | K51: 1 | L51: 20 | M51: Production Technician II | N51: MA | O51: 1752 | P51: 29829 | Q51: F | R51: Married | S51: US Citizen | T51: No | U51: White | V51: 40679 | W51: 41456 | X51: unhappy | Y51: Voluntarily Terminated | Z51: Production | AA51: Brannon Miller | AB51: 12 | AC51: Google Search | AD51: Fully Meets | AE51: 4.20 | AF51: 5 | AG51: 0 | AH51: 40973 | AI51: 0 | AJ51: 9 | AK51: =DATEDIF(P51, TODAY(), "Y") -> 44 | AL51: =INT((IF(K51=0, TODAY(), W51) - V51) / 365.25) -> 2 | AM51: =IF(K51=0, "Actif", IF(OR(X51="Another position", X51="more money", X51="unhappy", X51="career change", X51="return to school", X51="relocation out of area", X51="medical issues", X51="military", X51="retiring"), "Volontaire", "Involontaire")) -> Volontaire | AN51: =IF(AK51<30, "Moins de 30", IF(AK51<45, "30-44 ans", IF(AK51<60, "45-59 ans", "60 ans et plus"))) -> 30-44 ans | AO51: =IF(H51=1, "PIP", IF(H51=2, "Needs Improvement", IF(H51=3, "Fully Meets", IF(H51=4, "Exceeds", "Non défini")))) -> Fully Meets | AP51: =IF(AND(AE51<3, AF51<3, AJ51>15), "CRITIQUE", IF(OR(AE51<3, AJ51>10), "SURVEILLER", "FAIBLE")) -> FAIBLE
A52: Close Phil | B52: 10269 | C52: 1 | D52: 1 | E52: 1 | F52: 5 | G52: 5 | H52: 3 | I52: 0 | J52: 59369 | K52: 1 | L52: 20 | M52: Production Technician II | N52: MA | O52: 2169 | P52: 28819 | Q52: M | R52: Married | S52: US Citizen | T52: No | U52: White | V52: 40420 | W52: 40812 | X52: career change | Y52: Voluntarily Terminated | Z52: Production | AA52: David Stanley | AB52: 14 | AC52: Indeed | AD52: Fully Meets | AE52: 4.20 | AF52: 4 | AG52: 0 | AH52: 40638 | AI52: 0 | AJ52: 6 | AK52: =DATEDIF(P52, TODAY(), "Y") -> 47 | AL52: =INT((IF(K52=0, TODAY(), W52) - V52) / 365.25) -> 1 | AM52: =IF(K52=0, "Actif", IF(OR(X52="Another position", X52="more money", X52="unhappy", X52="career change", X52="return to school", X52="relocation out of area", X52="medical issues", X52="military", X52="retiring"), "Volontaire", "Involontaire")) -> Volontaire | AN52: =IF(AK52<30, "Moins de 30", IF(AK52<45, "30-44 ans", IF(AK52<60, "45-59 ans", "60 ans et plus"))) -> 45-59 ans | AO52: =IF(H52=1, "PIP", IF(H52=2, "Needs Improvement", IF(H52=3, "Fully Meets", IF(H52=4, "Exceeds", "Non défini")))) -> Fully Meets | AP52: =IF(AND(AE52<3, AF52<3, AJ52>15), "CRITIQUE", IF(OR(AE52<3, AJ52>10), "SURVEILLER", "FAIBLE")) -> FAIBLE
A53: Clukey Elijian | B53: 10029 | C53: 1 | D53: 1 | E53: 1 | F53: 2 | G53: 5 | H53: 4 | I53: 0 | J53: 50373 | K53: 0 | L53: 19 | M53: Production Technician I | N53: MA | O53: 2134 | P53: 29459 | Q53: M | R53: Married | S53: US Citizen | T53: No | U53: White | V53: 42528 | X53: N/A-StillEmployed | Y53: Active | Z53: Production | AA53: Brannon Miller | AB53: 12 | AC53: Employee Referral | AD53: Exceeds | AE53: 4.10 | AF53: 4 | AG53: 0 | AH53: 2/28/2019 | AI53: 0 | AJ53: 5 | AK53: =DATEDIF(P53, TODAY(), "Y") -> 45 | AL53: =INT((IF(K53=0, TODAY(), W53) - V53) / 365.25) -> 9 | AM53: =IF(K53=0, "Actif", IF(OR(X53="Another position", X53="more money", X53="unhappy", X53="career change", X53="return to school", X53="relocation out of area", X53="medical issues", X53="military", X53="retiring"), "Volontaire", "Involontaire")) -> Actif | AN53: =IF(AK53<30, "Moins de 30", IF(AK53<45, "30-44 ans", IF(AK53<60, "45-59 ans", "60 ans et plus"))) -> 45-59 ans | AO53: =IF(H53=1, "PIP", IF(H53=2, "Needs Improvement", IF(H53=3, "Fully Meets", IF(H53=4, "Exceeds", "Non défini")))) -> Exceeds | AP53: =IF(AND(AE53<3, AF53<3, AJ53>15), "CRITIQUE", IF(OR(AE53<3, AJ53>10), "SURVEILLER", "FAIBLE")) -> FAIBLE
A54: Cockel James | B54: 10261 | C54: 0 | D54: 0 | E54: 1 | F54: 1 | G54: 5 | H54: 3 | I54: 0 | J54: 63108 | K54: 0 | L54: 19 | M54: Production Technician I | N54: MA | O54: 2452 | P54: 28346 | Q54: M | R54: Single | S54: US Citizen | T54: No | U54: White | V54: 41493 | X54: N/A-StillEmployed | Y54: Active | Z54: Production | AA54: David Stanley | AB54: 14 | AC54: Employee Referral | AD54: Fully Meets | AE54: 4.40 | AF54: 5 | AG54: 0 | AH54: 1/14/2019 | AI54: 0 | AJ54: 3 | AK54: =DATEDIF(P54, TODAY(), "Y") -> 48 | AL54: =INT((IF(K54=0, TODAY(), W54) - V54) / 365.25) -> 12 | AM54: =IF(K54=0, "Actif", IF(OR(X54="Another position", X54="more money", X54="unhappy", X54="career change", X54="return to school", X54="relocation out of area", X54="medical issues", X54="military", X54="retiring"), "Volontaire", "Involontaire")) -> Actif | AN54: =IF(AK54<30, "Moins de 30", IF(AK54<45, "30-44 ans", IF(AK54<60, "45-59 ans", "60 ans et plus"))) -> 45-59 ans | AO54: =IF(H54=1, "PIP", IF(H54=2, "Needs Improvement", IF(H54=3, "Fully Meets", IF(H54=4, "Exceeds", "Non défini")))) -> Fully Meets | AP54: =IF(AND(AE54<3, AF54<3, AJ54>15), "CRITIQUE", IF(OR(AE54<3, AJ54>10), "SURVEILLER", "FAIBLE")) -> FAIBLE
A55: Cole Spencer | B55: 10292 | C55: 0 | D55: 0 | E55: 1 | F55: 4 | G55: 5 | H55: 2 | I55: 0 | J55: 59144 | K55: 1 | L55: 19 | M55: Production Technician I | N55: MA | O55: 1880 | P55: 29197 | Q55: M | R55: Single | S55: US Citizen | T55: No | U55: Black or African American | V55: 40854 | W55: 42636 | X55: performance | Y55: Terminated for Cause | Z55: Production | AA55: Kissy Sullivan | AB55: 20 | AC55: LinkedIn | AD55: Needs Improvement | AE55: 2.00 | AF55: 3 | AG55: 0 | AH55: 42374 | AI55: 5 | AJ55: 16 | AK55: =DATEDIF(P55, TODAY(), "Y") -> 46 | AL55: =INT((IF(K55=0, TODAY(), W55) - V55) / 365.25) -> 4 | AM55: =IF(K55=0, "Actif", IF(OR(X55="Another position", X55="more money", X55="unhappy", X55="career change", X55="return to school", X55="relocation out of area", X55="medical issues", X55="military", X55="retiring"), "Volontaire", "Involontaire")) -> Involontaire | AN55: =IF(AK55<30, "Moins de 30", IF(AK55<45, "30-44 ans", IF(AK55<60, "45-59 ans", "60 ans et plus"))) -> 45-59 ans | AO55: =IF(H55=1, "PIP", IF(H55=2, "Needs Improvement", IF(H55=3, "Fully Meets", IF(H55=4, "Exceeds", "Non défini")))) -> Needs Improvement | AP55: =IF(AND(AE55<3, AF55<3, AJ55>15), "CRITIQUE", IF(OR(AE55<3, AJ55>10), "SURVEILLER", "FAIBLE")) -> SURVEILLER
A56: Corleone Michael | B56: 10282 | C56: 0 | D56: 2 | E56: 1 | F56: 1 | G56: 5 | H56: 2 | I56: 0 | J56: 68051 | K56: 0 | L56: 18 | M56: Production Manager | N56: MA | O56: 1803 | P56: 27745 | Q56: M | R56: Divorced | S56: US Citizen | T56: No | U56: White | V56: 40379 | X56: N/A-StillEmployed | Y56: Active | Z56: Production | AA56: Janet King | AB56: 2 | AC56: CareerBuilder | AD56: Needs Improvement | AE56: 4.13 | AF56: 2 | AG56: 0 | AH56: 1/14/2019 | AI56: 3 | AJ56: 3 | AK56: =DATEDIF(P56, TODAY(), "Y") -> 50 | AL56: =INT((IF(K56=0, TODAY(), W56) - V56) / 365.25) -> 15 | AM56: =IF(K56=0, "Actif", IF(OR(X56="Another position", X56="more money", X56="unhappy", X56="career change", X56="return to school", X56="relocation out of area", X56="medical issues", X56="military", X56="retiring"), "Volontaire", "Involontaire")) -> Actif | AN56: =IF(AK56<30, "Moins de 30", IF(AK56<45, "30-44 ans", IF(AK56<60, "45-59 ans", "60 ans et plus"))) -> 45-59 ans | AO56: =IF(H56=1, "PIP", IF(H56=2, "Needs Improvement", IF(H56=3, "Fully Meets", IF(H56=4, "Exceeds", "Non défini")))) -> Needs Improvement | AP56: =IF(AND(AE56<3, AF56<3, AJ56>15), "CRITIQUE", IF(OR(AE56<3, AJ56>10), "SURVEILLER", "FAIBLE")) -> FAIBLE
A57: Corleone Vito | B57: 10019 | C57: 0 | D57: 0 | E57: 1 | F57: 1 | G57: 5 | H57: 4 | I57: 0 | J57: 170500 | K57: 0 | L57: 10 | M57: Director of Operations | N57: MA | O57: 2030 | P57: 30394 | Q57: M | R57: Single | S57: US Citizen | T57: No | U57: Black or African American | V57: 39934 | X57: N/A-StillEmployed | Y57: Active | Z57: Production | AA57: Janet King | AB57: 2 | AC57: Indeed | AD57: Exceeds | AE57: 3.70 | AF57: 5 | AG57: 0 | AH57: 43557 | AI57: 0 | AJ57: 15 | AK57: =DATEDIF(P57, TODAY(), "Y") -> 43 | AL57: =INT((IF(K57=0, TODAY(), W57) - V57) / 365.25) -> 16 | AM57: =IF(K57=0, "Actif", IF(OR(X57="Another position", X57="more money", X57="unhappy", X57="career change", X57="return to school", X57="relocation out of area", X57="medical issues", X57="military", X57="retiring"), "Volontaire", "Involontaire")) -> Actif | AN57: =IF(AK57<30, "Moins de 30", IF(AK57<45, "30-44 ans", IF(AK57<60, "45-59 ans", "60 ans et plus"))) -> 30-44 ans | AO57: =IF(H57=1, "PIP", IF(H57=2, "Needs Improvement", IF(H57=3, "Fully Meets", IF(H57=4, "Exceeds", "Non défini")))) -> Exceeds | AP57: =IF(AND(AE57<3, AF57<3, AJ57>15), "CRITIQUE", IF(OR(AE57<3, AJ57>10), "SURVEILLER", "FAIBLE")) -> SURVEILLER
A58: Cornett Lisa | B58: 10094 | C58: 1 | D58: 1 | E58: 0 | F58: 1 | G58: 5 | H58: 3 | I58: 0 | J58: 63381 | K58: 0 | L58: 19 | M58: Production Technician I | N58: MA | O58: 2189 | P58: 28215 | Q58: F | R58: Married | S58: US Citizen | T58: Yes | U58: White | V58: 42125 | X58: N/A-StillEmployed | Y58: Active | Z58: Production | AA58: Kelley Spirea | AB58: 18 | AC58: Indeed | AD58: Fully Meets | AE58: 4.73 | AF58: 5 | AG58: 0 | AH58: 2/14/2019 | AI58: 0 | AJ58: 6 | AK58: =DATEDIF(P58, TODAY(), "Y") -> 49 | AL58: =INT((IF(K58=0, TODAY(), W58) - V58) / 365.25) -> 10 | AM58: =IF(K58=0, "Actif", IF(OR(X58="Another position", X58="more money", X58="unhappy", X58="career change", X58="return to school", X58="relocation out of area", X58="medical issues", X58="military", X58="retiring"), "Volontaire", "Involontaire")) -> Actif | AN58: =IF(AK58<30, "Moins de 30", IF(AK58<45, "30-44 ans", IF(AK58<60, "45-59 ans", "60 ans et plus"))) -> 45-59 ans | AO58: =IF(H58=1, "PIP", IF(H58=2, "Needs Improvement", IF(H58=3, "Fully Meets", IF(H58=4, "Exceeds", "Non défini")))) -> Fully Meets | AP58: =IF(AND(AE58<3, AF58<3, AJ58>15), "CRITIQUE", IF(OR(AE58<3, AJ58>10), "SURVEILLER", "FAIBLE")) -> FAIBLE
A59: Costello Frank | B59: 10193 | C59: 1 | D59: 1 | E59: 1 | F59: 1 | G59: 3 | H59: 3 | I59: 0 | J59: 83552 | K59: 0 | L59: 9 | M59: Data Analyst | N59: MA | O59: 1810 | P59: 31650 | Q59: M | R59: Married | S59: US Citizen | T59: No | U59: White | V59: 42093 | X59: N/A-StillEmployed | Y59: Active | Z59: IT/IS | AA59: Simon Roup | AB59: 4 | AC59: Indeed | AD59: Fully Meets | AE59: 3.04 | AF59: 3 | AG59: 6 | AH59: 1/22/2019 | AI59: 0 | AJ59: 2 | AK59: =DATEDIF(P59, TODAY(), "Y") -> 39 | AL59: =INT((IF(K59=0, TODAY(), W59) - V59) / 365.25) -> 11 | AM59: =IF(K59=0, "Actif", IF(OR(X59="Another position", X59="more money", X59="unhappy", X59="career change", X59="return to school", X59="relocation out of area", X59="medical issues", X59="military", X59="retiring"), "Volontaire", "Involontaire")) -> Actif | AN59: =IF(AK59<30, "Moins de 30", IF(AK59<45, "30-44 ans", IF(AK59<60, "45-59 ans", "60 ans et plus"))) -> 30-44 ans | AO59: =IF(H59=1, "PIP", IF(H59=2, "Needs Improvement", IF(H59=3, "Fully Meets", IF(H59=4, "Exceeds", "Non défini")))) -> Fully Meets | AP59: =IF(AND(AE59<3, AF59<3, AJ59>15), "CRITIQUE", IF(OR(AE59<3, AJ59>10), "SURVEILLER", "FAIBLE")) -> FAIBLE
A60: Crimmings Jean | B60: 10132 | C60: 0 | D60: 0 | E60: 0 | F60: 2 | G60: 5 | H60: 3 | I60: 0 | J60: 56149 | K60: 0 | L60: 19 | M60: Production Technician I | N60: MA | O60: 1821 | P60: 32054 | Q60: F | R60: Single | S60: US Citizen | T60: No | U60: White | V60: 42528 | X60: N/A-StillEmployed | Y60: Active | Z60: Production | AA60: Michael Albert | AB60: 22 | AC60: LinkedIn | AD60: Fully Meets | AE60: 4.12 | AF60: 5 | AG60: 0 | AH60: 1/28/2019 | AI60: 0 | AJ60: 15 | AK60: =DATEDIF(P60, TODAY(), "Y") -> 38 | AL60: =INT((IF(K60=0, TODAY(), W60) - V60) / 365.25) -> 9 | AM60: =IF(K60=0, "Actif", IF(OR(X60="Another position", X60="more money", X60="unhappy", X60="career change", X60="return to school", X60="relocation out of area", X60="medical issues", X60="military", X60="retiring"), "Volontaire", "Involontaire")) -> Actif | AN60: =IF(AK60<30, "Moins de 30", IF(AK60<45, "30-44 ans", IF(AK60<60, "45-59 ans", "60 ans et plus"))) -> 30-44 ans | AO60: =IF(H60=1, "PIP", IF(H60=2, "Needs Improvement", IF(H60=3, "Fully Meets", IF(H60=4, "Exceeds", "Non défini")))) -> Fully Meets | AP60: =IF(AND(AE60<3, AF60<3, AJ60>15), "CRITIQUE", IF(OR(AE60<3, AJ60>10), "SURVEILLER", "FAIBLE")) -> SURVEILLER
A61: Cross Noah | B61: 10083 | C61: 0 | D61: 0 | E61: 1 | F61: 1 | G61: 3 | H61: 3 | I61: 0 | J61: 92329 | K61: 0 | L61: 28 | M61: Sr. Network Engineer | N61: CT | O61: 6278 | P61: 23994 | Q61: M | R61: Single | S61: US Citizen | T61: No | U61: White | V61: 41923 | X61: N/A-StillEmployed | Y61: Active | Z61: IT/IS | AA61: Peter Monroe | AB61: 7 | AC61: Employee Referral | AD61: Fully Meets | AE61: 5.00 | AF61: 3 | AG61: 4 | AH61: 43497 | AI61: 0 | AJ61: 5 | AK61: =DATEDIF(P61, TODAY(), "Y") -> 60 | AL61: =INT((IF(K61=0, TODAY(), W61) - V61) / 365.25) -> 11 | AM61: =IF(K61=0, "Actif", IF(OR(X61="Another position", X61="more money", X61="unhappy", X61="career change", X61="return to school", X61="relocation out of area", X61="medical issues", X61="military", X61="retiring"), "Volontaire", "Involontaire")) -> Actif | AN61: =IF(AK61<30, "Moins de 30", IF(AK61<45, "30-44 ans", IF(AK61<60, "45-59 ans", "60 ans et plus"))) -> 60 ans et plus | AO61: =IF(H61=1, "PIP", IF(H61=2, "Needs Improvement", IF(H61=3, "Fully Meets", IF(H61=4, "Exceeds", "Non défini")))) -> Fully Meets | AP61: =IF(AND(AE61<3, AF61<3, AJ61>15), "CRITIQUE", IF(OR(AE61<3, AJ61>10), "SURVEILLER", "FAIBLE")) -> FAIBLE
A62: Daneault Lynn | B62: 10099 | C62: 0 | D62: 0 | E62: 0 | F62: 1 | G62: 6 | H62: 3 | I62: 0 | J62: 65729 | K62: 0 | L62: 21 | M62: Sales Manager | N62: VT | O62: 5473 | P62: 32982 | Q62: F | R62: Single | S62: US Citizen | T62: No | U62: White | V62: 41764 | X62: N/A-StillEmployed | Y62: Active | Z62: Sales | AA62: Debra Houlihan | AB62: 15 | AC62: Indeed | AD62: Fully Meets | AE62: 4.62 | AF62: 4 | AG62: 0 | AH62: 1/24/2019 | AI62: 0 | AJ62: 8 | AK62: =DATEDIF(P62, TODAY(), "Y") -> 35 | AL62: =INT((IF(K62=0, TODAY(), W62) - V62) / 365.25) -> 11 | AM62: =IF(K62=0, "Actif", IF(OR(X62="Another position", X62="more money", X62="unhappy", X62="career change", X62="return to school", X62="relocation out of area", X62="medical issues", X62="military", X62="retiring"), "Volontaire", "Involontaire")) -> Actif | AN62: =IF(AK62<30, "Moins de 30", IF(AK62<45, "30-44 ans", IF(AK62<60, "45-59 ans", "60 ans et plus"))) -> 30-44 ans | AO62: =IF(H62=1, "PIP", IF(H62=2, "Needs Improvement", IF(H62=3, "Fully Meets", IF(H62=4, "Exceeds", "Non défini")))) -> Fully Meets | AP62: =IF(AND(AE62<3, AF62<3, AJ62>15), "CRITIQUE", IF(OR(AE62<3, AJ62>10), "SURVEILLER", "FAIBLE")) -> FAIBLE
A63: Daniele Ann | B63: 10212 | C63: 1 | D63: 1 | E63: 0 | F63: 3 | G63: 3 | H63: 3 | I63: 0 | J63: 85028 | K63: 0 | L63: 28 | M63: Sr. Network Engineer | N63: CT | O63: 6033 | P63: 19011 | Q63: F | R63: Married | S63: US Citizen | T63: No | U63: White | V63: 41923 | X63: N/A-StillEmployed | Y63: Active | Z63: IT/IS | AA63: Peter Monroe | AB63: 7 | AC63: LinkedIn | AD63: Fully Meets | AE63: 3.10 | AF63: 5 | AG63: 8 | AH63: 43801 | AI63: 0 | AJ63: 19 | AK63: =DATEDIF(P63, TODAY(), "Y") -> 74 | AL63: =INT((IF(K63=0, TODAY(), W63) - V63) / 365.25) -> 11 | AM63: =IF(K63=0, "Actif", IF(OR(X63="Another position", X63="more money", X63="unhappy", X63="career change", X63="return to school", X63="relocation out of area", X63="medical issues", X63="military", X63="retiring"), "Volontaire", "Involontaire")) -> Actif | AN63: =IF(AK63<30, "Moins de 30", IF(AK63<45, "30-44 ans", IF(AK63<60, "45-59 ans", "60 ans et plus"))) -> 60 ans et plus | AO63: =IF(H63=1, "PIP", IF(H63=2, "Needs Improvement", IF(H63=3, "Fully Meets", IF(H63=4, "Exceeds", "Non défini")))) -> Fully Meets | AP63: =IF(AND(AE63<3, AF63<3, AJ63>15), "CRITIQUE", IF(OR(AE63<3, AJ63>10), "SURVEILLER", "FAIBLE")) -> SURVEILLER
A64: Darson Jene'ya | B64: 10056 | C64: 1 | D64: 1 | E64: 0 | F64: 1 | G64: 5 | H64: 3 | I64: 0 | J64: 57583 | K64: 0 | L64: 19 | M64: Production Technician I | N64: MA | O64: 2110 | P64: 28621 | Q64: F | R64: Married | S64: US Citizen | T64: No | U64: White | V64: 40946 | X64: N/A-StillEmployed | Y64: Active | Z64: Production | AA64: Elijiah Gray | AB64: 16 | AC64: Indeed | AD64: Fully Meets | AE64: 5.00 | AF64: 3 | AG64: 0 | AH64: 2/25/2019 | AI64: 0 | AJ64: 1 | AK64: =DATEDIF(P64, TODAY(), "Y") -> 47 | AL64: =INT((IF(K64=0, TODAY(), W64) - V64) / 365.25) -> 14 | AM64: =IF(K64=0, "Actif", IF(OR(X64="Another position", X64="more money", X64="unhappy", X64="career change", X64="return to school", X64="relocation out of area", X64="medical issues", X64="military", X64="retiring"), "Volontaire", "Involontaire")) -> Actif | AN64: =IF(AK64<30, "Moins de 30", IF(AK64<45, "30-44 ans", IF(AK64<60, "45-59 ans", "60 ans et plus"))) -> 45-59 ans | AO64: =IF(H64=1, "PIP", IF(H64=2, "Needs Improvement", IF(H64=3, "Fully Meets", IF(H64=4, "Exceeds", "Non défini")))) -> Fully Meets | AP64: =IF(AND(AE64<3, AF64<3, AJ64>15), "CRITIQUE", IF(OR(AE64<3, AJ64>10), "SURVEILLER", "FAIBLE")) -> FAIBLE
A65: Davis Daniel | B65: 10143 | C65: 0 | D65: 0 | E65: 1 | F65: 1 | G65: 5 | H65: 3 | I65: 0 | J65: 56294 | K65: 0 | L65: 20 | M65: Production Technician II | N65: MA | O65: 2458 | P65: 29112 | Q65: M | R65: Single | S65: Eligible NonCitizen | T65: No | U65: Two or more races | V65: 40735 | X65: N/A-StillEmployed | Y65: Active | Z65: Production | AA65: Kissy Sullivan | AB65: 20 | AC65: LinkedIn | AD65: Fully Meets | AE65: 3.96 | AF65: 4 | AG65: 0 | AH65: 2/27/2019 | AI65: 0 | AJ65: 6 | AK65: =DATEDIF(P65, TODAY(), "Y") -> 46 | AL65: =INT((IF(K65=0, TODAY(), W65) - V65) / 365.25) -> 14 | AM65: =IF(K65=0, "Actif", IF(OR(X65="Another position", X65="more money", X65="unhappy", X65="career change", X65="return to school", X65="relocation out of area", X65="medical issues", X65="military", X65="retiring"), "Volontaire", "Involontaire")) -> Actif | AN65: =IF(AK65<30, "Moins de 30", IF(AK65<45, "30-44 ans", IF(AK65<60, "45-59 ans", "60 ans et plus"))) -> 45-59 ans | AO65: =IF(H65=1, "PIP", IF(H65=2, "Needs Improvement", IF(H65=3, "Fully Meets", IF(H65=4, "Exceeds", "Non défini")))) -> Fully Meets | AP65: =IF(AND(AE65<3, AF65<3, AJ65>15), "CRITIQUE", IF(OR(AE65<3, AJ65>10), "SURVEILLER", "FAIBLE")) -> FAIBLE
A66: Dee Randy | B66: 10311 | C66: 1 | D66: 1 | E66: 1 | F66: 1 | G66: 6 | H66: 1 | I66: 0 | J66: 56991 | K66: 0 | L66: 19 | M66: Production Technician I | N66: MA | O66: 2138 | P66: 32248 | Q66: M | R66: Married | S66: US Citizen | T66: No | U66: White | V66: 43350 | X66: N/A-StillEmployed | Y66: Active | Z66: Production | AA66: Brannon Miller | AB66: 12 | AC66: Indeed | AD66: Fully Meets | AE66: 4.3 | AF66: 4 | AG66: 3 | AH66: 1/31/2019 | AI66: 2 | AJ66: 2 | AK66: =DATEDIF(P66, TODAY(), "Y") -> 37 | AL66: =INT((IF(K66=0, TODAY(), W66) - V66) / 365.25) -> 7 | AM66: =IF(K66=0, "Actif", IF(OR(X66="Another position", X66="more money", X66="unhappy", X66="career change", X66="return to school", X66="relocation out of area", X66="medical issues", X66="military", X66="retiring"), "Volontaire", "Involontaire")) -> Actif | AN66: =IF(AK66<30, "Moins de 30", IF(AK66<45, "30-44 ans", IF(AK66<60, "45-59 ans", "60 ans et plus"))) -> 30-44 ans | AO66: =IF(H66=1, "PIP", IF(H66=2, "Needs Improvement", IF(H66=3, "Fully Meets", IF(H66=4, "Exceeds", "Non défini")))) -> PIP | AP66: =IF(AND(AE66<3, AF66<3, AJ66>15), "CRITIQUE", IF(OR(AE66<3, AJ66>10), "SURVEILLER", "FAIBLE")) -> FAIBLE
A67: DeGweck James | B67: 10070 | C67: 1 | D67: 1 | E67: 1 | F67: 5 | G67: 5 | H67: 3 | I67: 0 | J67: 55722 | K67: 1 | L67: 19 | M67: Production Technician I | N67: MA | O67: 1810 | P67: 28429 | Q67: M | R67: Married | S67: US Citizen | T67: No | U67: White | V67: 40679 | W67: 42588 | X67: unhappy | Y67: Voluntarily Terminated | Z67: Production | AA67: Webster Butler | AB67: 39 | AC67: Indeed | AD67: Fully Meets | AE67: 5.00 | AF67: 4 | AG67: 0 | AH67: 42404 | AI67: 0 | AJ67: 14 | AK67: =DATEDIF(P67, TODAY(), "Y") -> 48 | AL67: =INT((IF(K67=0, TODAY(), W67) - V67) / 365.25) -> 5 | AM67: =IF(K67=0, "Actif", IF(OR(X67="Another position", X67="more money", X67="unhappy", X67="career change", X67="return to school", X67="relocation out of area", X67="medical issues", X67="military", X67="retiring"), "Volontaire", "Involontaire")) -> Volontaire | AN67: =IF(AK67<30, "Moins de 30", IF(AK67<45, "30-44 ans", IF(AK67<60, "45-59 ans", "60 ans et plus"))) -> 45-59 ans | AO67: =IF(H67=1, "PIP", IF(H67=2, "Needs Improvement", IF(H67=3, "Fully Meets", IF(H67=4, "Exceeds", "Non défini")))) -> Fully Meets | AP67: =IF(AND(AE67<3, AF67<3, AJ67>15), "CRITIQUE", IF(OR(AE67<3, AJ67>10), "SURVEILLER", "FAIBLE")) -> SURVEILLER
A68: Del Bosque Keyla | B68: 10155 | C68: 0 | D68: 0 | E68: 0 | F68: 1 | G68: 4 | H68: 3 | I68: 0 | J68: 101199 | K68: 0 | L68: 24 | M68: Software Engineer | N68: MA | O68: 2176 | P68: 28982 | Q68: F | R68: Single | S68: US Citizen | T68: No | U68: Black or African American | V68: 41153 | X68: N/A-StillEmployed | Y68: Active | Z68: Software Engineering | AA68: Alex Sweetwater | AB68: 10 | AC68: CareerBuilder | AD68: Fully Meets | AE68: 3.79 | AF68: 5 | AG68: 5 | AH68: 1/25/2019 | AI68: 0 | AJ68: 8 | AK68: =DATEDIF(P68, TODAY(), "Y") -> 46 | AL68: =INT((IF(K68=0, TODAY(), W68) - V68) / 365.25) -> 13 | AM68: =IF(K68=0, "Actif", IF(OR(X68="Another position", X68="more money", X68="unhappy", X68="career change", X68="return to school", X68="relocation out of area", X68="medical issues", X68="military", X68="retiring"), "Volontaire", "Involontaire")) -> Actif | AN68: =IF(AK68<30, "Moins de 30", IF(AK68<45, "30-44 ans", IF(AK68<60, "45-59 ans", "60 ans et plus"))) -> 45-59 ans | AO68: =IF(H68=1, "PIP", IF(H68=2, "Needs Improvement", IF(H68=3, "Fully Meets", IF(H68=4, "Exceeds", "Non défini")))) -> Fully Meets | AP68: =IF(AND(AE68<3, AF68<3, AJ68>15), "CRITIQUE", IF(OR(AE68<3, AJ68>10), "SURVEILLER", "FAIBLE")) -> FAIBLE
A69: Delarge Alex | B69: 10306 | C69: 0 | D69: 0 | E69: 1 | F69: 1 | G69: 6 | H69: 1 | I69: 0 | J69: 61568 | K69: 0 | L69: 3 | M69: Area Sales Manager | N69: AL | O69: 36006 | P69: 27436 | Q69: M | R69: Single | S69: US Citizen | T69: No | U69: Two or more races | V69: 41911 | X69: N/A-StillEmployed | Y69: Active | Z69: Sales | AA69: John Smith | AB69: 17 | AC69: Indeed | AD69: PIP | AE69: 1.93 | AF69: 3 | AG69: 0 | AH69: 1/30/2019 | AI69: 6 | AJ69: 5 | AK69: =DATEDIF(P69, TODAY(), "Y") -> 51 | AL69: =INT((IF(K69=0, TODAY(), W69) - V69) / 365.25) -> 11 | AM69: =IF(K69=0, "Actif", IF(OR(X69="Another position", X69="more money", X69="unhappy", X69="career change", X69="return to school", X69="relocation out of area", X69="medical issues", X69="military", X69="retiring"), "Volontaire", "Involontaire")) -> Actif | AN69: =IF(AK69<30, "Moins de 30", IF(AK69<45, "30-44 ans", IF(AK69<60, "45-59 ans", "60 ans et plus"))) -> 45-59 ans | AO69: =IF(H69=1, "PIP", IF(H69=2, "Needs Improvement", IF(H69=3, "Fully Meets", IF(H69=4, "Exceeds", "Non défini")))) -> PIP | AP69: =IF(AND(AE69<3, AF69<3, AJ69>15), "CRITIQUE", IF(OR(AE69<3, AJ69>10), "SURVEILLER", "FAIBLE")) -> FAIBLE
A70: Demita Carla | B70: 10100 | C70: 0 | D70: 3 | E70: 0 | F70: 5 | G70: 5 | H70: 3 | I70: 0 | J70: 58275 | K70: 1 | L70: 20 | M70: Production Technician II | N70: MA | O70: 2343 | P70: 18684 | Q70: F | R70: Separated | S70: US Citizen | T70: No | U70: Black or African American | V70: 40637 | W70: 42105 | X70: more money | Y70: Voluntarily Terminated | Z70: Production | AA70: Kelley Spirea | AB70: 18 | AC70: Google Search | AD70: Fully Meets | AE70: 4.62 | AF70: 5 | AG70: 0 | AH70: 42160 | AI70: 0 | AJ70: 1 | AK70: =DATEDIF(P70, TODAY(), "Y") -> 75 | AL70: =INT((IF(K70=0, TODAY(), W70) - V70) / 365.25) -> 4 | AM70: =IF(K70=0, "Actif", IF(OR(X70="Another position", X70="more money", X70="unhappy", X70="career change", X70="return to school", X70="relocation out of area", X70="medical issues", X70="military", X70="retiring"), "Volontaire", "Involontaire")) -> Volontaire | AN70: =IF(AK70<30, "Moins de 30", IF(AK70<45, "30-44 ans", IF(AK70<60, "45-59 ans", "60 ans et plus"))) -> 60 ans et plus | AO70: =IF(H70=1, "PIP", IF(H70=2, "Needs Improvement", IF(H70=3, "Fully Meets", IF(H70=4, "Exceeds", "Non défini")))) -> Fully Meets | AP70: =IF(AND(AE70<3, AF70<3, AJ70>15), "CRITIQUE", IF(OR(AE70<3, AJ70>10), "SURVEILLER", "FAIBLE")) -> FAIBLE
A71: Desimone Carl | B71: 10310 | C71: 1 | D71: 1 | E71: 1 | F71: 1 | G71: 5 | H71: 1 | I71: 0 | J71: 53189 | K71: 0 | L71: 19 | M71: Production Technician I | N71: MA | O71: 2061 | P71: 24581 | Q71: M | R71: Married | S71: US Citizen | T71: No | U71: White | V71: 41827 | X71: N/A-StillEmployed | Y71: Active | Z71: Production | AA71: Amy Dunn | AB71: 11 | AC71: Indeed | AD71: PIP | AE71: 1.12 | AF71: 2 | AG71: 0 | AH71: 1/31/2019 | AI71: 4 | AJ71: 9 | AK71: =DATEDIF(P71, TODAY(), "Y") -> 58 | AL71: =INT((IF(K71=0, TODAY(), W71) - V71) / 365.25) -> 11 | AM71: =IF(K71=0, "Actif", IF(OR(X71="Another position", X71="more money", X71="unhappy", X71="career change", X71="return to school", X71="relocation out of area", X71="medical issues", X71="military", X71="retiring"), "Volontaire", "Involontaire")) -> Actif | AN71: =IF(AK71<30, "Moins de 30", IF(AK71<45, "30-44 ans", IF(AK71<60, "45-59 ans", "60 ans et plus"))) -> 45-59 ans | AO71: =IF(H71=1, "PIP", IF(H71=2, "Needs Improvement", IF(H71=3, "Fully Meets", IF(H71=4, "Exceeds", "Non défini")))) -> PIP | AP71: =IF(AND(AE71<3, AF71<3, AJ71>15), "CRITIQUE", IF(OR(AE71<3, AJ71>10), "SURVEILLER", "FAIBLE")) -> FAIBLE
A72: DeVito Tommy | B72: 10197 | C72: 0 | D72: 0 | E72: 1 | F72: 1 | G72: 3 | H72: 3 | I72: 0 | J72: 96820 | K72: 0 | L72: 4 | M72: BI Developer | N72: MA | O72: 2045 | P72: 30415 | Q72: M | R72: Single | S72: US Citizen | T72: No | U72: White | V72: 42781 | X72: N/A-StillEmployed | Y72: Active | Z72: IT/IS | AA72: Brian Champaigne | AB72: 13 | AC72: Indeed | AD72: Fully Meets | AE72: 3.01 | AF72: 5 | AG72: 7 | AH72: 1/23/2019 | AI72: 0 | AJ72: 15 | AK72: =DATEDIF(P72, TODAY(), "Y") -> 42 | AL72: =INT((IF(K72=0, TODAY(), W72) - V72) / 365.25) -> 9 | AM72: =IF(K72=0, "Actif", IF(OR(X72="Another position", X72="more money", X72="unhappy", X72="career change", X72="return to school", X72="relocation out of area", X72="medical issues", X72="military", X72="retiring"), "Volontaire", "Involontaire")) -> Actif | AN72: =IF(AK72<30, "Moins de 30", IF(AK72<45, "30-44 ans", IF(AK72<60, "45-59 ans", "60 ans et plus"))) -> 30-44 ans | AO72: =IF(H72=1, "PIP", IF(H72=2, "Needs Improvement", IF(H72=3, "Fully Meets", IF(H72=4, "Exceeds", "Non défini")))) -> Fully Meets | AP72: =IF(AND(AE72<3, AF72<3, AJ72>15), "CRITIQUE", IF(OR(AE72<3, AJ72>10), "SURVEILLER", "FAIBLE")) -> SURVEILLER
A73: Dickinson Geoff | B73: 10276 | C73: 0 | D73: 0 | E73: 1 | F73: 1 | G73: 5 | H73: 3 | I73: 0 | J73: 51259 | K73: 0 | L73: 19 | M73: Production Technician I | N73: MA | O73: 2180 | P73: 30270 | Q73: M | R73: Single | S73: US Citizen | T73: No | U73: White | V73: 41978 | X73: N/A-StillEmployed | Y73: Active | Z73: Production | AA73: Ketsia Liebig | AB73: 19 | AC73: Indeed | AD73: Fully Meets | AE73: 4.30 | AF73: 4 | AG73: 0 | AH73: 2/19/2019 | AI73: 0 | AJ73: 1 | AK73: =DATEDIF(P73, TODAY(), "Y") -> 43 | AL73: =INT((IF(K73=0, TODAY(), W73) - V73) / 365.25) -> 11 | AM73: =IF(K73=0, "Actif", IF(OR(X73="Another position", X73="more money", X73="unhappy", X73="career change", X73="return to school", X73="relocation out of area", X73="medical issues", X73="military", X73="retiring"), "Volontaire", "Involontaire")) -> Actif | AN73: =IF(AK73<30, "Moins de 30", IF(AK73<45, "30-44 ans", IF(AK73<60, "45-59 ans", "60 ans et plus"))) -> 30-44 ans | AO73: =IF(H73=1, "PIP", IF(H73=2, "Needs Improvement", IF(H73=3, "Fully Meets", IF(H73=4, "Exceeds", "Non défini")))) -> Fully Meets | AP73: =IF(AND(AE73<3, AF73<3, AJ73>15), "CRITIQUE", IF(OR(AE73<3, AJ73>10), "SURVEILLER", "FAIBLE")) -> FAIBLE
A74: Dietrich Jenna | B74: 10304 | C74: 0 | D74: 0 | E74: 0 | F74: 1 | G74: 6 | H74: 1 | I74: 0 | J74: 59231 | K74: 0 | L74: 3 | M74: Area Sales Manager | N74: WA | O74: 98052 | P74: 31911 | Q74: F | R74: Single | S74: US Citizen | T74: Yes | U74: White | V74: 40959 | X74: N/A-StillEmployed | Y74: Active | Z74: Sales | AA74: John Smith | AB74: 17 | AC74: Website | AD74: PIP | AE74: 2.30 | AF74: 1 | AG74: 0 | AH74: 1/29/2019 | AI74: 2 | AJ74: 17 | AK74: =DATEDIF(P74, TODAY(), "Y") -> 38 | AL74: =INT((IF(K74=0, TODAY(), W74) - V74) / 365.25) -> 14 | AM74: =IF(K74=0, "Actif", IF(OR(X74="Another position", X74="more money", X74="unhappy", X74="career change", X74="return to school", X74="relocation out of area", X74="medical issues", X74="military", X74="retiring"), "Volontaire", "Involontaire")) -> Actif | AN74: =IF(AK74<30, "Moins de 30", IF(AK74<45, "30-44 ans", IF(AK74<60, "45-59 ans", "60 ans et plus"))) -> 30-44 ans | AO74: =IF(H74=1, "PIP", IF(H74=2, "Needs Improvement", IF(H74=3, "Fully Meets", IF(H74=4, "Exceeds", "Non défini")))) -> PIP | AP74: =IF(AND(AE74<3, AF74<3, AJ74>15), "CRITIQUE", IF(OR(AE74<3, AJ74>10), "SURVEILLER", "FAIBLE")) -> SURVEILLER
A75: DiNocco Lily | B75: 10284 | C75: 1 | D75: 1 | E75: 0 | F75: 1 | G75: 5 | H75: 2 | I75: 0 | J75: 61584 | K75: 0 | L75: 19 | M75: Production Technician I | N75: MA | O75: 2351 | P75: 28533 | Q75: F | R75: Married | S75: US Citizen | T75: No | U75: Black or African American | V75: 41456 | X75: N/A-StillEmployed | Y75: Active | Z75: Production | AA75: Brannon Miller | AB75: 12 | AC75: Indeed | AD75: Needs Improvement | AE75: 3.88 | AF75: 4 | AG75: 0 | AH75: 1/18/2019 | AI75: 0 | AJ75: 6 | AK75: =DATEDIF(P75, TODAY(), "Y") -> 48 | AL75: =INT((IF(K75=0, TODAY(), W75) - V75) / 365.25) -> 12 | AM75: =IF(K75=0, "Actif", IF(OR(X75="Another position", X75="more money", X75="unhappy", X75="career change", X75="return to school", X75="relocation out of area", X75="medical issues", X75="military", X75="retiring"), "Volontaire", "Involontaire")) -> Actif | AN75: =IF(AK75<30, "Moins de 30", IF(AK75<45, "30-44 ans", IF(AK75<60, "45-59 ans", "60 ans et plus"))) -> 45-59 ans | AO75: =IF(H75=1, "PIP", IF(H75=2, "Needs Improvement", IF(H75=3, "Fully Meets", IF(H75=4, "Exceeds", "Non défini")))) -> Needs Improvement | AP75: =IF(AND(AE75<3, AF75<3, AJ75>15), "CRITIQUE", IF(OR(AE75<3, AJ75>10), "SURVEILLER", "FAIBLE")) -> FAIBLE
A76: Dobrin Denisa S | B76: 10207 | C76: 0 | D76: 0 | E76: 0 | F76: 1 | G76: 5 | H76: 3 | I76: 0 | J76: 46335 | K76: 0 | L76: 19 | M76: Production Technician I | N76: MA | O76: 2125 | P76: 31603 | Q76: F | R76: Single | S76: US Citizen | T76: Yes | U76: White | V76: 40943 | X76: N/A-StillEmployed | Y76: Active | Z76: Production | AA76: David Stanley | AB76: 14 | AC76: CareerBuilder | AD76: Fully Meets | AE76: 3.40 | AF76: 5 | AG76: 0 | AH76: 2/19/2019 | AI76: 0 | AJ76: 15 | AK76: =DATEDIF(P76, TODAY(), "Y") -> 39 | AL76: =INT((IF(K76=0, TODAY(), W76) - V76) / 365.25) -> 14 | AM76: =IF(K76=0, "Actif", IF(OR(X76="Another position", X76="more money", X76="unhappy", X76="career change", X76="return to school", X76="relocation out of area", X76="medical issues", X76="military", X76="retiring"), "Volontaire", "Involontaire")) -> Actif | AN76: =IF(AK76<30, "Moins de 30", IF(AK76<45, "30-44 ans", IF(AK76<60, "45-59 ans", "60 ans et plus"))) -> 30-44 ans | AO76: =IF(H76=1, "PIP", IF(H76=2, "Needs Improvement", IF(H76=3, "Fully Meets", IF(H76=4, "Exceeds", "Non défini")))) -> Fully Meets | AP76: =IF(AND(AE76<3, AF76<3, AJ76>15), "CRITIQUE", IF(OR(AE76<3, AJ76>10), "SURVEILLER", "FAIBLE")) -> SURVEILLER
A77: Dolan Linda | B77: 10133 | C77: 1 | D77: 1 | E77: 0 | F77: 1 | G77: 3 | H77: 3 | I77: 0 | J77: 70621 | K77: 0 | L77: 14 | M77: IT Support | N77: MA | O77: 2119 | P77: 32342 | Q77: F | R77: Married | S77: US Citizen | T77: No | U77: White | V77: 42125 | X77: N/A-StillEmployed | Y77: Active | Z77: IT/IS | AA77: Peter Monroe | AB77: 7 | AC77: Employee Referral | AD77: Fully Meets | AE77: 4.11 | AF77: 4 | AG77: 6 | AH77: 2/25/2019 | AI77: 0 | AJ77: 16 | AK77: =DATEDIF(P77, TODAY(), "Y") -> 37 | AL77: =INT((IF(K77=0, TODAY(), W77) - V77) / 365.25) -> 10 | AM77: =IF(K77=0, "Actif", IF(OR(X77="Another position", X77="more money", X77="unhappy", X77="career change", X77="return to school", X77="relocation out of area", X77="medical issues", X77="military", X77="retiring"), "Volontaire", "Involontaire")) -> Actif | AN77: =IF(AK77<30, "Moins de 30", IF(AK77<45, "30-44 ans", IF(AK77<60, "45-59 ans", "60 ans et plus"))) -> 30-44 ans | AO77: =IF(H77=1, "PIP", IF(H77=2, "Needs Improvement", IF(H77=3, "Fully Meets", IF(H77=4, "Exceeds", "Non défini")))) -> Fully Meets | AP77: =IF(AND(AE77<3, AF77<3, AJ77>15), "CRITIQUE", IF(OR(AE77<3, AJ77>10), "SURVEILLER", "FAIBLE")) -> SURVEILLER
A78: Dougall Eric | B78: 10028 | C78: 0 | D78: 0 | E78: 1 | F78: 1 | G78: 3 | H78: 4 | I78: 0 | J78: 138888 | K78: 0 | L78: 13 | M78: IT Manager - Support | N78: MA | O78: 1886 | P78: 25818 | Q78: M | R78: Single | S78: US Citizen | T78: No | U78: Black or African American | V78: 41760 | X78: N/A-StillEmployed | Y78: Active | Z78: IT/IS | AA78: Jennifer Zamora | AB78: 5 | AC78: Indeed | AD78: Exceeds | AE78: 4.30 | AF78: 5 | AG78: 5 | AH78: 43556 | AI78: 0 | AJ78: 4 | AK78: =DATEDIF(P78, TODAY(), "Y") -> 55 | AL78: =INT((IF(K78=0, TODAY(), W78) - V78) / 365.25) -> 11 | AM78: =IF(K78=0, "Actif", IF(OR(X78="Another position", X78="more money", X78="unhappy", X78="career change", X78="return to school", X78="relocation out of area", X78="medical issues", X78="military", X78="retiring"), "Volontaire", "Involontaire")) -> Actif | AN78: =IF(AK78<30, "Moins de 30", IF(AK78<45, "30-44 ans", IF(AK78<60, "45-59 ans", "60 ans et plus"))) -> 45-59 ans | AO78: =IF(H78=1, "PIP", IF(H78=2, "Needs Improvement", IF(H78=3, "Fully Meets", IF(H78=4, "Exceeds", "Non défini")))) -> Exceeds | AP78: =IF(AND(AE78<3, AF78<3, AJ78>15), "CRITIQUE", IF(OR(AE78<3, AJ78>10), "SURVEILLER", "FAIBLE")) -> FAIBLE
A79: Driver Elle | B79: 10006 | C79: 0 | D79: 0 | E79: 0 | F79: 1 | G79: 6 | H79: 4 | I79: 0 | J79: 74241 | K79: 0 | L79: 3 | M79: Area Sales Manager | N79: CA | O79: 90007 | P79: 32366 | Q79: F | R79: Single | S79: US Citizen | T79: No | U79: White | V79: 40817 | X79: N/A-StillEmployed | Y79: Active | Z79: Sales | AA79: Lynn Daneault | AB79: 21 | AC79: Indeed | AD79: Exceeds | AE79: 4.77 | AF79: 5 | AG79: 0 | AH79: 1/27/2019 | AI79: 0 | AJ79: 14 | AK79: =DATEDIF(P79, TODAY(), "Y") -> 37 | AL79: =INT((IF(K79=0, TODAY(), W79) - V79) / 365.25) -> 14 | AM79: =IF(K79=0, "Actif", IF(OR(X79="Another position", X79="more money", X79="unhappy", X79="career change", X79="return to school", X79="relocation out of area", X79="medical issues", X79="military", X79="retiring"), "Volontaire", "Involontaire")) -> Actif | AN79: =IF(AK79<30, "Moins de 30", IF(AK79<45, "30-44 ans", IF(AK79<60, "45-59 ans", "60 ans et plus"))) -> 30-44 ans | AO79: =IF(H79=1, "PIP", IF(H79=2, "Needs Improvement", IF(H79=3, "Fully Meets", IF(H79=4, "Exceeds", "Non défini")))) -> Exceeds | AP79: =IF(AND(AE79<3, AF79<3, AJ79>15), "CRITIQUE", IF(OR(AE79<3, AJ79>10), "SURVEILLER", "FAIBLE")) -> SURVEILLER
A80: Dunn Amy | B80: 10105 | C80: 0 | D80: 0 | E80: 0 | F80: 1 | G80: 5 | H80: 3 | I80: 0 | J80: 75188 | K80: 0 | L80: 18 | M80: Production Manager | N80: MA | O80: 1731 | P80: 26996 | Q80: F | R80: Single | S80: US Citizen | T80: No | U80: White | V80: 41900 | X80: N/A-StillEmployed | Y80: Active | Z80: Production | AA80: Janet King | AB80: 2 | AC80: Google Search | AD80: Fully Meets | AE80: 4.52 | AF80: 4 | AG80: 0 | AH80: 1/15/2019 | AI80: 0 | AJ80: 4 | AK80: =DATEDIF(P80, TODAY(), "Y") -> 52 | AL80: =INT((IF(K80=0, TODAY(), W80) - V80) / 365.25) -> 11 | AM80: =IF(K80=0, "Actif", IF(OR(X80="Another position", X80="more money", X80="unhappy", X80="career change", X80="return to school", X80="relocation out of area", X80="medical issues", X80="military", X80="retiring"), "Volontaire", "Involontaire")) -> Actif | AN80: =IF(AK80<30, "Moins de 30", IF(AK80<45, "30-44 ans", IF(AK80<60, "45-59 ans", "60 ans et plus"))) -> 45-59 ans | AO80: =IF(H80=1, "PIP", IF(H80=2, "Needs Improvement", IF(H80=3, "Fully Meets", IF(H80=4, "Exceeds", "Non défini")))) -> Fully Meets | AP80: =IF(AND(AE80<3, AF80<3, AJ80>15), "CRITIQUE", IF(OR(AE80<3, AJ80>10), "SURVEILLER", "FAIBLE")) -> FAIBLE
A81: Dunne Amy | B81: 10211 | C81: 1 | D81: 1 | E81: 0 | F81: 1 | G81: 5 | H81: 3 | I81: 0 | J81: 62514 | K81: 0 | L81: 19 | M81: Production Technician I | N81: MA | O81: 1749 | P81: 26930 | Q81: F | R81: Married | S81: US Citizen | T81: No | U81: White | V81: 40294 | X81: N/A-StillEmployed | Y81: Active | Z81: Production | AA81: Ketsia Liebig | AB81: 19 | AC81: Google Search | AD81: Fully Meets | AE81: 2.90 | AF81: 3 | AG81: 0 | AH81: 1/21/2019 | AI81: 0 | AJ81: 6 | AK81: =DATEDIF(P81, TODAY(), "Y") -> 52 | AL81: =INT((IF(K81=0, TODAY(), W81) - V81) / 365.25) -> 15 | AM81: =IF(K81=0, "Actif", IF(OR(X81="Another position", X81="more money", X81="unhappy", X81="career change", X81="return to school", X81="relocation out of area", X81="medical issues", X81="military", X81="retiring"), "Volontaire", "Involontaire")) -> Actif | AN81: =IF(AK81<30, "Moins de 30", IF(AK81<45, "30-44 ans", IF(AK81<60, "45-59 ans", "60 ans et plus"))) -> 45-59 ans | AO81: =IF(H81=1, "PIP", IF(H81=2, "Needs Improvement", IF(H81=3, "Fully Meets", IF(H81=4, "Exceeds", "Non défini")))) -> Fully Meets | AP81: =IF(AND(AE81<3, AF81<3, AJ81>15), "CRITIQUE", IF(OR(AE81<3, AJ81>10), "SURVEILLER", "FAIBLE")) -> FAIBLE
A82: Eaton Marianne | B82: 10064 | C82: 1 | D82: 1 | E82: 0 | F82: 5 | G82: 5 | H82: 3 | I82: 0 | J82: 60070 | K82: 1 | L82: 19 | M82: Production Technician I | N82: MA | O82: 2343 | P82: 33367 | Q82: F | R82: Married | S82: US Citizen | T82: No | U82: White | V82: 40637 | W82: 42892 | X82: military | Y82: Voluntarily Terminated | Z82: Production | AA82: Kissy Sullivan | AB82: 20 | AC82: Google Search | AD82: Fully Meets | AE82: 5.00 | AF82: 3 | AG82: 0 | AH82: 42982 | AI82: 0 | AJ82: 7 | AK82: =DATEDIF(P82, TODAY(), "Y") -> 34 | AL82: =INT((IF(K82=0, TODAY(), W82) - V82) / 365.25) -> 6 | AM82: =IF(K82=0, "Actif", IF(OR(X82="Another position", X82="more money", X82="unhappy", X82="career change", X82="return to school", X82="relocation out of area", X82="medical issues", X82="military", X82="retiring"), "Volontaire", "Involontaire")) -> Volontaire | AN82: =IF(AK82<30, "Moins de 30", IF(AK82<45, "30-44 ans", IF(AK82<60, "45-59 ans", "60 ans et plus"))) -> 30-44 ans | AO82: =IF(H82=1, "PIP", IF(H82=2, "Needs Improvement", IF(H82=3, "Fully Meets", IF(H82=4, "Exceeds", "Non défini")))) -> Fully Meets | AP82: =IF(AND(AE82<3, AF82<3, AJ82>15), "CRITIQUE", IF(OR(AE82<3, AJ82>10), "SURVEILLER", "FAIBLE")) -> FAIBLE
A83: Engdahl Jean | B83: 10247 | C83: 0 | D83: 0 | E83: 1 | F83: 1 | G83: 5 | H83: 3 | I83: 0 | J83: 48888 | K83: 0 | L83: 19 | M83: Production Technician I | N83: MA | O83: 2026 | P83: 27180 | Q83: M | R83: Single | S83: US Citizen | T83: No | U83: White | V83: 41923 | X83: N/A-StillEmployed | Y83: Active | Z83: Production | AA83: Kelley Spirea | AB83: 18 | AC83: LinkedIn | AD83: Fully Meets | AE83: 4.70 | AF83: 5 | AG83: 0 | AH83: 2/13/2019 | AI83: 0 | AJ83: 8 | AK83: =DATEDIF(P83, TODAY(), "Y") -> 51 | AL83: =INT((IF(K83=0, TODAY(), W83) - V83) / 365.25) -> 11 | AM83: =IF(K83=0, "Actif", IF(OR(X83="Another position", X83="more money", X83="unhappy", X83="career change", X83="return to school", X83="relocation out of area", X83="medical issues", X83="military", X83="retiring"), "Volontaire", "Involontaire")) -> Actif | AN83: =IF(AK83<30, "Moins de 30", IF(AK83<45, "30-44 ans", IF(AK83<60, "45-59 ans", "60 ans et plus"))) -> 45-59 ans | AO83: =IF(H83=1, "PIP", IF(H83=2, "Needs Improvement", IF(H83=3, "Fully Meets", IF(H83=4, "Exceeds", "Non défini")))) -> Fully Meets | AP83: =IF(AND(AE83<3, AF83<3, AJ83>15), "CRITIQUE", IF(OR(AE83<3, AJ83>10), "SURVEILLER", "FAIBLE")) -> FAIBLE
A84: England Rex | B84: 10235 | C84: 1 | D84: 1 | E84: 1 | F84: 1 | G84: 5 | H84: 3 | I84: 0 | J84: 54285 | K84: 0 | L84: 19 | M84: Production Technician I | N84: MA | O84: 2045 | P84: 28727 | Q84: M | R84: Married | S84: US Citizen | T84: No | U84: White | V84: 41729 | X84: N/A-StillEmployed | Y84: Active | Z84: Production | AA84: Kelley Spirea | AB84: 18 | AC84: Employee Referral | AD84: Fully Meets | AE84: 4.20 | AF84: 3 | AG84: 0 | AH84: 43770 | AI84: 0 | AJ84: 3 | AK84: =DATEDIF(P84, TODAY(), "Y") -> 47 | AL84: =INT((IF(K84=0, TODAY(), W84) - V84) / 365.25) -> 12 | AM84: =IF(K84=0, "Actif", IF(OR(X84="Another position", X84="more money", X84="unhappy", X84="career change", X84="return to school", X84="relocation out of area", X84="medical issues", X84="military", X84="retiring"), "Volontaire", "Involontaire")) -> Actif | AN84: =IF(AK84<30, "Moins de 30", IF(AK84<45, "30-44 ans", IF(AK84<60, "45-59 ans", "60 ans et plus"))) -> 45-59 ans | AO84: =IF(H84=1, "PIP", IF(H84=2, "Needs Improvement", IF(H84=3, "Fully Meets", IF(H84=4, "Exceeds", "Non défini")))) -> Fully Meets | AP84: =IF(AND(AE84<3, AF84<3, AJ84>15), "CRITIQUE", IF(OR(AE84<3, AJ84>10), "SURVEILLER", "FAIBLE")) -> FAIBLE
A85: Erilus Angela | B85: 10299 | C85: 0 | D85: 3 | E85: 0 | F85: 1 | G85: 5 | H85: 1 | I85: 0 | J85: 56847 | K85: 0 | L85: 20 | M85: Production Technician II | N85: MA | O85: 2133 | P85: 32745 | Q85: F | R85: Separated | S85: US Citizen | T85: No | U85: White | V85: 41827 | X85: N/A-StillEmployed | Y85: Active | Z85: Production | AA85: Michael Albert | AB85: 22 | AC85: Indeed | AD85: PIP | AE85: 3.00 | AF85: 1 | AG85: 0 | AH85: 2/25/2019 | AI85: 2 | AJ85: 5 | AK85: =DATEDIF(P85, TODAY(), "Y") -> 36 | AL85: =INT((IF(K85=0, TODAY(), W85) - V85) / 365.25) -> 11 | AM85: =IF(K85=0, "Actif", IF(OR(X85="Another position", X85="more money", X85="unhappy", X85="career change", X85="return to school", X85="relocation out of area", X85="medical issues", X85="military", X85="retiring"), "Volontaire", "Involontaire")) -> Actif | AN85: =IF(AK85<30, "Moins de 30", IF(AK85<45, "30-44 ans", IF(AK85<60, "45-59 ans", "60 ans et plus"))) -> 30-44 ans | AO85: =IF(H85=1, "PIP", IF(H85=2, "Needs Improvement", IF(H85=3, "Fully Meets", IF(H85=4, "Exceeds", "Non défini")))) -> PIP | AP85: =IF(AND(AE85<3, AF85<3, AJ85>15), "CRITIQUE", IF(OR(AE85<3, AJ85>10), "SURVEILLER", "FAIBLE")) -> FAIBLE
A86: Estremera Miguel | B86: 10280 | C86: 0 | D86: 0 | E86: 1 | F86: 4 | G86: 5 | H86: 2 | I86: 0 | J86: 60340 | K86: 1 | L86: 19 | M86: Production Technician I | N86: MA | O86: 2129 | P86: 30356 | Q86: M | R86: Single | S86: US Citizen | T86: No | U86: White | V86: 40943 | W86: 43370 | X86: attendance | Y86: Terminated for Cause | Z86: Production | AA86: Michael Albert | AB86: 22 | AC86: Google Search | AD86: Needs Improvement | AE86: 5.00 | AF86: 4 | AG86: 0 | AH86: 43438 | AI86: 5 | AJ86: 16 | AK86: =DATEDIF(P86, TODAY(), "Y") -> 43 | AL86: =INT((IF(K86=0, TODAY(), W86) - V86) / 365.25) -> 6 | AM86: =IF(K86=0, "Actif", IF(OR(X86="Another position", X86="more money", X86="unhappy", X86="career change", X86="return to school", X86="relocation out of area", X86="medical issues", X86="military", X86="retiring"), "Volontaire", "Involontaire")) -> Involontaire | AN86: =IF(AK86<30, "Moins de 30", IF(AK86<45, "30-44 ans", IF(AK86<60, "45-59 ans", "60 ans et plus"))) -> 30-44 ans | AO86: =IF(H86=1, "PIP", IF(H86=2, "Needs Improvement", IF(H86=3, "Fully Meets", IF(H86=4, "Exceeds", "Non défini")))) -> Needs Improvement | AP86: =IF(AND(AE86<3, AF86<3, AJ86>15), "CRITIQUE", IF(OR(AE86<3, AJ86>10), "SURVEILLER", "FAIBLE")) -> SURVEILLER
A87: Evensen April | B87: 10296 | C87: 0 | D87: 0 | E87: 0 | F87: 4 | G87: 5 | H87: 2 | I87: 0 | J87: 59124 | K87: 1 | L87: 19 | M87: Production Technician I | N87: MA | O87: 2458 | P87: 32664 | Q87: F | R87: Single | S87: US Citizen | T87: No | U87: White | V87: 41687 | W87: 43156 | X87: no-call, no-show | Y87: Terminated for Cause | Z87: Production | AA87: Elijiah Gray | AB87: 16 | AC87: Google Search | AD87: Needs Improvement | AE87: 2.30 | AF87: 3 | AG87: 0 | AH87: 1/15/2017 | AI87: 5 | AJ87: 19 | AK87: =DATEDIF(P87, TODAY(), "Y") -> 36 | AL87: =INT((IF(K87=0, TODAY(), W87) - V87) / 365.25) -> 4 | AM87: =IF(K87=0, "Actif", IF(OR(X87="Another position", X87="more money", X87="unhappy", X87="career change", X87="return to school", X87="relocation out of area", X87="medical issues", X87="military", X87="retiring"), "Volontaire", "Involontaire")) -> Involontaire | AN87: =IF(AK87<30, "Moins de 30", IF(AK87<45, "30-44 ans", IF(AK87<60, "45-59 ans", "60 ans et plus"))) -> 30-44 ans | AO87: =IF(H87=1, "PIP", IF(H87=2, "Needs Improvement", IF(H87=3, "Fully Meets", IF(H87=4, "Exceeds", "Non défini")))) -> Needs Improvement | AP87: =IF(AND(AE87<3, AF87<3, AJ87>15), "CRITIQUE", IF(OR(AE87<3, AJ87>10), "SURVEILLER", "FAIBLE")) -> SURVEILLER
A88: Exantus Susan | B88: 10290 | C88: 1 | D88: 1 | E88: 0 | F88: 4 | G88: 4 | H88: 2 | I88: 0 | J88: 99280 | K88: 1 | L88: 24 | M88: Software Engineer | N88: MA | O88: 1749 | P88: 31912 | Q88: F | R88: Married | S88: US Citizen | T88: No | U88: Black or African American | V88: 40579 | W88: 41400 | X88: attendance | Y88: Terminated for Cause | Z88: Software Engineering | AA88: Alex Sweetwater | AB88: 10 | AC88: Indeed | AD88: Needs Improvement | AE88: 2.10 | AF88: 5 | AG88: 4 | AH88: 41190 | AI88: 4 | AJ88: 19 | AK88: =DATEDIF(P88, TODAY(), "Y") -> 38 | AL88: =INT((IF(K88=0, TODAY(), W88) - V88) / 365.25) -> 2 | AM88: =IF(K88=0, "Actif", IF(OR(X88="Another position", X88="more money", X88="unhappy", X88="career change", X88="return to school", X88="relocation out of area", X88="medical issues", X88="military", X88="retiring"), "Volontaire", "Involontaire")) -> Involontaire | AN88: =IF(AK88<30, "Moins de 30", IF(AK88<45, "30-44 ans", IF(AK88<60, "45-59 ans", "60 ans et plus"))) -> 30-44 ans | AO88: =IF(H88=1, "PIP", IF(H88=2, "Needs Improvement", IF(H88=3, "Fully Meets", IF(H88=4, "Exceeds", "Non défini")))) -> Needs Improvement | AP88: =IF(AND(AE88<3, AF88<3, AJ88>15), "CRITIQUE", IF(OR(AE88<3, AJ88>10), "SURVEILLER", "FAIBLE")) -> SURVEILLER
A89: Faller Megan | B89: 10263 | C89: 1 | D89: 1 | E89: 0 | F89: 1 | G89: 5 | H89: 3 | I89: 0 | J89: 71776 | K89: 0 | L89: 20 | M89: Production Technician II | N89: MA | O89: 1824 | P89: 28755 | Q89: F | R89: Married | S89: US Citizen | T89: No | U89: Black or African American | V89: 41827 | X89: N/A-StillEmployed | Y89: Active | Z89: Production | AA89: Elijiah Gray | AB89: 16 | AC89: LinkedIn | AD89: Fully Meets | AE89: 4.40 | AF89: 5 | AG89: 0 | AH89: 2/22/2019 | AI89: 0 | AJ89: 17 | AK89: =DATEDIF(P89, TODAY(), "Y") -> 47 | AL89: =INT((IF(K89=0, TODAY(), W89) - V89) / 365.25) -> 11 | AM89: =IF(K89=0, "Actif", IF(OR(X89="Another position", X89="more money", X89="unhappy", X89="career change", X89="return to school", X89="relocation out of area", X89="medical issues", X89="military", X89="retiring"), "Volontaire", "Involontaire")) -> Actif | AN89: =IF(AK89<30, "Moins de 30", IF(AK89<45, "30-44 ans", IF(AK89<60, "45-59 ans", "60 ans et plus"))) -> 45-59 ans | AO89: =IF(H89=1, "PIP", IF(H89=2, "Needs Improvement", IF(H89=3, "Fully Meets", IF(H89=4, "Exceeds", "Non défini")))) -> Fully Meets | AP89: =IF(AND(AE89<3, AF89<3, AJ89>15), "CRITIQUE", IF(OR(AE89<3, AJ89>10), "SURVEILLER", "FAIBLE")) -> SURVEILLER
A90: Fancett Nicole | B90: 10136 | C90: 0 | D90: 0 | E90: 0 | F90: 1 | G90: 5 | H90: 3 | I90: 0 | J90: 65902 | K90: 0 | L90: 20 | M90: Production Technician II | N90: MA | O90: 2324 | P90: 32047 | Q90: F | R90: Single | S90: US Citizen | T90: No | U90: Black or African American | V90: 41687 | X90: N/A-StillEmployed | Y90: Active | Z90: Production | AA90: Webster Butler | AC90: LinkedIn | AD90: Fully Meets | AE90: 4.00 | AF90: 4 | AG90: 0 | AH90: 43647 | AI90: 0 | AJ90: 7 | AK90: =DATEDIF(P90, TODAY(), "Y") -> 38 | AL90: =INT((IF(K90=0, TODAY(), W90) - V90) / 365.25) -> 12 | AM90: =IF(K90=0, "Actif", IF(OR(X90="Another position", X90="more money", X90="unhappy", X90="career change", X90="return to school", X90="relocation out of area", X90="medical issues", X90="military", X90="retiring"), "Volontaire", "Involontaire")) -> Actif | AN90: =IF(AK90<30, "Moins de 30", IF(AK90<45, "30-44 ans", IF(AK90<60, "45-59 ans", "60 ans et plus"))) -> 30-44 ans | AO90: =IF(H90=1, "PIP", IF(H90=2, "Needs Improvement", IF(H90=3, "Fully Meets", IF(H90=4, "Exceeds", "Non défini")))) -> Fully Meets | AP90: =IF(AND(AE90<3, AF90<3, AJ90>15), "CRITIQUE", IF(OR(AE90<3, AJ90>10), "SURVEILLER", "FAIBLE")) -> FAIBLE
A91: Ferguson Susan | B91: 10189 | C91: 1 | D91: 1 | E91: 0 | F91: 5 | G91: 5 | H91: 3 | I91: 0 | J91: 57748 | K91: 1 | L91: 19 | M91: Production Technician I | N91: MA | O91: 2176 | P91: 20193 | Q91: F | R91: Married | S91: US Citizen | T91: No | U91: White | V91: 40735 | W91: 42507 | X91: military | Y91: Voluntarily Terminated | Z91: Production | AA91: Webster Butler | AB91: 39 | AC91: Google Search | AD91: Fully Meets | AE91: 3.13 | AF91: 3 | AG91: 0 | AH91: 42462 | AI91: 0 | AJ91: 16 | AK91: =DATEDIF(P91, TODAY(), "Y") -> 70 | AL91: =INT((IF(K91=0, TODAY(), W91) - V91) / 365.25) -> 4 | AM91: =IF(K91=0, "Actif", IF(OR(X91="Another position", X91="more money", X91="unhappy", X91="career change", X91="return to school", X91="relocation out of area", X91="medical issues", X91="military", X91="retiring"), "Volontaire", "Involontaire")) -> Volontaire | AN91: =IF(AK91<30, "Moins de 30", IF(AK91<45, "30-44 ans", IF(AK91<60, "45-59 ans", "60 ans et plus"))) -> 60 ans et plus | AO91: =IF(H91=1, "PIP", IF(H91=2, "Needs Improvement", IF(H91=3, "Fully Meets", IF(H91=4, "Exceeds", "Non défini")))) -> Fully Meets | AP91: =IF(AND(AE91<3, AF91<3, AJ91>15), "CRITIQUE", IF(OR(AE91<3, AJ91>10), "SURVEILLER", "FAIBLE")) -> SURVEILLER
A92: Fernandes Nilson | B92: 10308 | C92: 1 | D92: 1 | E92: 1 | F92: 1 | G92: 5 | H92: 1 | I92: 0 | J92: 64057 | K92: 0 | L92: 19 | M92: Production Technician I | N92: MA | O92: 2132 | P92: 32799 | Q92: M | R92: Married | S92: US Citizen | T92: No | U92: White | V92: 42313 | X92: N/A-StillEmployed | Y92: Active | Z92: Production | AA92: Amy Dunn | AB92: 11 | AC92: Indeed | AD92: PIP | AE92: 1.56 | AF92: 5 | AG92: 0 | AH92: 43525 | AI92: 6 | AJ92: 15 | AK92: =DATEDIF(P92, TODAY(), "Y") -> 36 | AL92: =INT((IF(K92=0, TODAY(), W92) - V92) / 365.25) -> 10 | AM92: =IF(K92=0, "Actif", IF(OR(X92="Another position", X92="more money", X92="unhappy", X92="career change", X92="return to school", X92="relocation out of area", X92="medical issues", X92="military", X92="retiring"), "Volontaire", "Involontaire")) -> Actif | AN92: =IF(AK92<30, "Moins de 30", IF(AK92<45, "30-44 ans", IF(AK92<60, "45-59 ans", "60 ans et plus"))) -> 30-44 ans | AO92: =IF(H92=1, "PIP", IF(H92=2, "Needs Improvement", IF(H92=3, "Fully Meets", IF(H92=4, "Exceeds", "Non défini")))) -> PIP | AP92: =IF(AND(AE92<3, AF92<3, AJ92>15), "CRITIQUE", IF(OR(AE92<3, AJ92>10), "SURVEILLER", "FAIBLE")) -> SURVEILLER
A93: Fett Boba | B93: 10309 | C93: 0 | D93: 0 | E93: 1 | F93: 1 | G93: 3 | H93: 1 | I93: 0 | J93: 53366 | K93: 0 | L93: 15 | M93: Network Engineer | N93: MA | O93: 2138 | P93: 31946 | Q93: M | R93: Single | S93: US Citizen | T93: No | U93: White | V93: 42093 | X93: N/A-StillEmployed | Y93: Active | Z93: IT/IS | AA93: Peter Monroe | AB93: 7 | AC93: LinkedIn | AD93: PIP | AE93: 1.20 | AF93: 3 | AG93: 6 | AH93: 43557 | AI93: 3 | AJ93: 2 | AK93: =DATEDIF(P93, TODAY(), "Y") -> 38 | AL93: =INT((IF(K93=0, TODAY(), W93) - V93) / 365.25) -> 11 | AM93: =IF(K93=0, "Actif", IF(OR(X93="Another position", X93="more money", X93="unhappy", X93="career change", X93="return to school", X93="relocation out of area", X93="medical issues", X93="military", X93="retiring"), "Volontaire", "Involontaire")) -> Actif | AN93: =IF(AK93<30, "Moins de 30", IF(AK93<45, "30-44 ans", IF(AK93<60, "45-59 ans", "60 ans et plus"))) -> 30-44 ans | AO93: =IF(H93=1, "PIP", IF(H93=2, "Needs Improvement", IF(H93=3, "Fully Meets", IF(H93=4, "Exceeds", "Non défini")))) -> PIP | AP93: =IF(AND(AE93<3, AF93<3, AJ93>15), "CRITIQUE", IF(OR(AE93<3, AJ93>10), "SURVEILLER", "FAIBLE")) -> FAIBLE
A94: Fidelia Libby | B94: 10049 | C94: 1 | D94: 1 | E94: 0 | F94: 1 | G94: 5 | H94: 3 | I94: 0 | J94: 58530 | K94: 0 | L94: 19 | M94: Production Technician I | N94: MA | O94: 2155 | P94: 29661 | Q94: F | R94: Married | S94: US Citizen | T94: No | U94: White | V94: 41153 | X94: N/A-StillEmployed | Y94: Active | Z94: Production | AA94: Brannon Miller | AB94: 12 | AC94: Google Search | AD94: Fully Meets | AE94: 5.00 | AF94: 5 | AG94: 0 | AH94: 1/29/2019 | AI94: 0 | AJ94: 19 | AK94: =DATEDIF(P94, TODAY(), "Y") -> 45 | AL94: =INT((IF(K94=0, TODAY(), W94) - V94) / 365.25) -> 13 | AM94: =IF(K94=0, "Actif", IF(OR(X94="Another position", X94="more money", X94="unhappy", X94="career change", X94="return to school", X94="relocation out of area", X94="medical issues", X94="military", X94="retiring"), "Volontaire", "Involontaire")) -> Actif | AN94: =IF(AK94<30, "Moins de 30", IF(AK94<45, "30-44 ans", IF(AK94<60, "45-59 ans", "60 ans et plus"))) -> 45-59 ans | AO94: =IF(H94=1, "PIP", IF(H94=2, "Needs Improvement", IF(H94=3, "Fully Meets", IF(H94=4, "Exceeds", "Non défini")))) -> Fully Meets | AP94: =IF(AND(AE94<3, AF94<3, AJ94>15), "CRITIQUE", IF(OR(AE94<3, AJ94>10), "SURVEILLER", "FAIBLE")) -> SURVEILLER
A95: Fitzpatrick Michael J | B95: 10093 | C95: 0 | D95: 0 | E95: 1 | F95: 5 | G95: 5 | H95: 3 | I95: 0 | J95: 72609 | K95: 1 | L95: 20 | M95: Production Technician II | N95: MA | O95: 2143 | P95: 29596 | Q95: M | R95: Single | S95: US Citizen | T95: Yes | U95: White | V95: 40679 | W95: 41449 | X95: hours | Y95: Voluntarily Terminated | Z95: Production | AA95: Amy Dunn | AB95: 11 | AC95: Google Search | AD95: Fully Meets | AE95: 4.76 | AF95: 5 | AG95: 0 | AH95: 41398 | AI95: 0 | AJ95: 20 | AK95: =DATEDIF(P95, TODAY(), "Y") -> 45 | AL95: =INT((IF(K95=0, TODAY(), W95) - V95) / 365.25) -> 2 | AM95: =IF(K95=0, "Actif", IF(OR(X95="Another position", X95="more money", X95="unhappy", X95="career change", X95="return to school", X95="relocation out of area", X95="medical issues", X95="military", X95="retiring"), "Volontaire", "Involontaire")) -> Involontaire | AN95: =IF(AK95<30, "Moins de 30", IF(AK95<45, "30-44 ans", IF(AK95<60, "45-59 ans", "60 ans et plus"))) -> 45-59 ans | AO95: =IF(H95=1, "PIP", IF(H95=2, "Needs Improvement", IF(H95=3, "Fully Meets", IF(H95=4, "Exceeds", "Non défini")))) -> Fully Meets | AP95: =IF(AND(AE95<3, AF95<3, AJ95>15), "CRITIQUE", IF(OR(AE95<3, AJ95>10), "SURVEILLER", "FAIBLE")) -> SURVEILLER
A96: Foreman Tanya | B96: 10163 | C96: 1 | D96: 1 | E96: 0 | F96: 5 | G96: 5 | H96: 3 | I96: 0 | J96: 55965 | K96: 1 | L96: 20 | M96: Production Technician II | N96: MA | O96: 2170 | P96: 30539 | Q96: F | R96: Married | S96: US Citizen | T96: No | U96: White | V96: 40637 | W96: 41518 | X96: career change | Y96: Voluntarily Terminated | Z96: Production | AA96: Ketsia Liebig | AB96: 19 | AC96: Google Search | AD96: Fully Meets | AE96: 3.66 | AF96: 3 | AG96: 0 | AH96: 41091 | AI96: 0 | AJ96: 6 | AK96: =DATEDIF(P96, TODAY(), "Y") -> 42 | AL96: =INT((IF(K96=0, TODAY(), W96) - V96) / 365.25) -> 2 | AM96: =IF(K96=0, "Actif", IF(OR(X96="Another position", X96="more money", X96="unhappy", X96="career change", X96="return to school", X96="relocation out of area", X96="medical issues", X96="military", X96="retiring"), "Volontaire", "Involontaire")) -> Volontaire | AN96: =IF(AK96<30, "Moins de 30", IF(AK96<45, "30-44 ans", IF(AK96<60, "45-59 ans", "60 ans et plus"))) -> 30-44 ans | AO96: =IF(H96=1, "PIP", IF(H96=2, "Needs Improvement", IF(H96=3, "Fully Meets", IF(H96=4, "Exceeds", "Non défini")))) -> Fully Meets | AP96: =IF(AND(AE96<3, AF96<3, AJ96>15), "CRITIQUE", IF(OR(AE96<3, AJ96>10), "SURVEILLER", "FAIBLE")) -> FAIBLE
A97: Forrest Alex | B97: 10305 | C97: 1 | D97: 1 | E97: 1 | F97: 1 | G97: 6 | H97: 3 | I97: 0 | J97: 70187 | K97: 1 | L97: 3 | M97: Area Sales Manager | N97: MA | O97: 2330 | P97: 27582 | Q97: M | R97: Married | S97: US Citizen | T97: No | U97: White | V97: 41911 | W97: 43331 | X97: Fatal attraction | Y97: Terminated for Cause | Z97: Sales | AA97: Lynn Daneault | AB97: 21 | AC97: Employee Referral | AD97: PIP | AE97: 2.00 | AF97: 5 | AG97: 0 | AH97: 1/28/2019 | AI97: 4 | AJ97: 7 | AK97: =DATEDIF(P97, TODAY(), "Y") -> 50 | AL97: =INT((IF(K97=0, TODAY(), W97) - V97) / 365.25) -> 3 | AM97: =IF(K97=0, "Actif", IF(OR(X97="Another position", X97="more money", X97="unhappy", X97="career change", X97="return to school", X97="relocation out of area", X97="medical issues", X97="military", X97="retiring"), "Volontaire", "Involontaire")) -> Involontaire | AN97: =IF(AK97<30, "Moins de 30", IF(AK97<45, "30-44 ans", IF(AK97<60, "45-59 ans", "60 ans et plus"))) -> 45-59 ans | AO97: =IF(H97=1, "PIP", IF(H97=2, "Needs Improvement", IF(H97=3, "Fully Meets", IF(H97=4, "Exceeds", "Non défini")))) -> Fully Meets | AP97: =IF(AND(AE97<3, AF97<3, AJ97>15), "CRITIQUE", IF(OR(AE97<3, AJ97>10), "SURVEILLER", "FAIBLE")) -> FAIBLE
A98: Foss Jason | B98: 10015 | C98: 0 | D98: 0 | E98: 1 | F98: 1 | G98: 3 | H98: 4 | I98: 0 | J98: 178000 | K98: 0 | L98: 12 | M98: IT Director | N98: MA | O98: 1460 | P98: 29348 | Q98: M | R98: Single | S98: US Citizen | T98: No | U98: Black or African American | V98: 40648 | X98: N/A-StillEmployed | Y98: Active | Z98: IT/IS | AA98: Jennifer Zamora | AB98: 5 | AC98: Indeed | AD98: Exceeds | AE98: 5.00 | AF98: 5 | AG98: 5 | AH98: 43647 | AI98: 0 | AJ98: 15 | AK98: =DATEDIF(P98, TODAY(), "Y") -> 45 | AL98: =INT((IF(K98=0, TODAY(), W98) - V98) / 365.25) -> 14 | AM98: =IF(K98=0, "Actif", IF(OR(X98="Another position", X98="more money", X98="unhappy", X98="career change", X98="return to school", X98="relocation out of area", X98="medical issues", X98="military", X98="retiring"), "Volontaire", "Involontaire")) -> Actif | AN98: =IF(AK98<30, "Moins de 30", IF(AK98<45, "30-44 ans", IF(AK98<60, "45-59 ans", "60 ans et plus"))) -> 45-59 ans | AO98: =IF(H98=1, "PIP", IF(H98=2, "Needs Improvement", IF(H98=3, "Fully Meets", IF(H98=4, "Exceeds", "Non défini")))) -> Exceeds | AP98: =IF(AND(AE98<3, AF98<3, AJ98>15), "CRITIQUE", IF(OR(AE98<3, AJ98>10), "SURVEILLER", "FAIBLE")) -> SURVEILLER
A99: Foster-Baker Amy | B99: 10080 | C99: 1 | D99: 1 | E99: 0 | F99: 1 | G99: 1 | H99: 3 | I99: 0 | J99: 99351 | K99: 0 | L99: 26 | M99: Sr. Accountant | N99: MA | O99: 2050 | P99: 28961 | Q99: F | R99: Married | S99: US Citizen | T99: no | U99: White | V99: 39934 | X99: N/A-StillEmployed | Y99: Active | Z99: Admin Offices | AA99: Board of Directors | AB99: 9 | AC99: Other | AD99: Fully Meets | AE99: 5.00 | AF99: 3 | AG99: 2 | AH99: 43679 | AI99: 0 | AJ99: 3 | AK99: =DATEDIF(P99, TODAY(), "Y") -> 46 | AL99: =INT((IF(K99=0, TODAY(), W99) - V99) / 365.25) -> 16 | AM99: =IF(K99=0, "Actif", IF(OR(X99="Another position", X99="more money", X99="unhappy", X99="career change", X99="return to school", X99="relocation out of area", X99="medical issues", X99="military", X99="retiring"), "Volontaire", "Involontaire")) -> Actif | AN99: =IF(AK99<30, "Moins de 30", IF(AK99<45, "30-44 ans", IF(AK99<60, "45-59 ans", "60 ans et plus"))) -> 45-59 ans | AO99: =IF(H99=1, "PIP", IF(H99=2, "Needs Improvement", IF(H99=3, "Fully Meets", IF(H99=4, "Exceeds", "Non défini")))) -> Fully Meets | AP99: =IF(AND(AE99<3, AF99<3, AJ99>15), "CRITIQUE", IF(OR(AE99<3, AJ99>10), "SURVEILLER", "FAIBLE")) -> FAIBLE
A100: Fraval Maruk | B100: 10258 | C100: 0 | D100: 0 | E100: 1 | F100: 1 | G100: 6 | H100: 3 | I100: 0 | J100: 67251 | K100: 0 | L100: 3 | M100: Area Sales Manager | N100: CT | O100: 6050 | P100: 23251 | Q100: M | R100: Single | S100: US Citizen | T100: No | U100: Black or African American | V100: 40703 | X100: N/A-StillEmployed | Y100: Active | Z100: Sales | AA100: Lynn Daneault | AB100: 21 | AC100: CareerBuilder | AD100: Fully Meets | AE100: 4.30 | AF100: 3 | AG100: 0 | AH100: 1/27/2019 | AI100: 2 | AJ100: 7 | AK100: =DATEDIF(P100, TODAY(), "Y") -> 62 | AL100: =INT((IF(K100=0, TODAY(), W100) - V100) / 365.25) -> 14 | AM100: =IF(K100=0, "Actif", IF(OR(X100="Another position", X100="more money", X100="unhappy", X100="career change", X100="return to school", X100="relocation out of area", X100="medical issues", X100="military", X100="retiring"), "Volontaire", "Involontaire")) -> Actif | AN100: =IF(AK100<30, "Moins de 30", IF(AK100<45, "30-44 ans", IF(AK100<60, "45-59 ans", "60 ans et plus"))) -> 60 ans et plus | AO100: =IF(H100=1, "PIP", IF(H100=2, "Needs Improvement", IF(H100=3, "Fully Meets", IF(H100=4, "Exceeds", "Non défini")))) -> Fully Meets | AP100: =IF(AND(AE100<3, AF100<3, AJ100>15), "CRITIQUE", IF(OR(AE100<3, AJ100>10), "SURVEILLER", "FAIBLE")) -> FAIBLE
...

Sheet DASHBOARD
A1: YEYEHOU ERIC | B1: 46027 | C1: Analyse RH - Turnover & Performance
A2: DASHBOARD RH – ANALYSE DU TURNOVER ET DE LA PERFORMANCE | R2: Corrélation
A4: Effectif total | B4: =COUNTA(Feuil1!A2:A311) -> 310
A5: Taux de turnover : | B5: =SUM(Feuil1!K2:K311)/COUNTA(Feuil1!A2:A311) -> 0.33548387 | R5: Corrélation Satisfaction / Absences : | S5: =CORREL(Feuil1!AF2:AF311, Feuil1!AJ2:AJ311) -> 0.081236201
A6: Salaire moyen : | B6: =AVERAGE(Feuil1!J2:J311) -> 69098.023
R7: Salaire moyen - Hommes : | S7: =SUMIF(Feuil1!Q2:Q311, "*M*", Feuil1!J2:J311) / COUNTIF(Feuil1!Q2:Q311, "*M*") -> 70629.4
R8: alaire moyen - Femmes : | S8: =SUMIF(Feuil1!Q2:Q311, "*F*", Feuil1!J2:J311) / COUNTIF(Feuil1!Q2:Q311, "*F*") -> 67916.674
R9: Écart absolu (€) : | S9: =S7-S8 -> 2712.7257
R10: Écart relatif (%) : | S10: =(S7-S8)/S8 -> 0.039941969
